[
  {
    "url": "https://www.sbimf.com/sbimf-scheme-details/sbi-large-cap-fund-(formerly-known-as-sbi-bluechip-fund)-43",
    "title": "SBI Large Cap Fund",
    "content": "SBI Large Cap Fund (Formerly known as SBI Bluechip Fund)\nScheme Type :\nAn open ended equity scheme predominantly investing in large cap stocks\nEQUITY\nOpen Ended\nAn open ended equity scheme predominantly investing in large cap stocks\nVERY HIGH Risk\nReturns                                                     for Regular-Growth\n12.07%\n12.07%\n5.52%\n14.08%\n19.03%\nSince Inception\n1 Year\n3 Year\n5 Year\nSince Inception\nSince Inception\n1 Year\n3 Year\n5 Year\nReturns for Direct growth\n15.39%\n15.39%\n6.24%\n14.88%\n19.89%\nSince Inception\n1 Year\n3 Year\n5 Year\nSince Inception\nSince Inception\n1 Year\n3 Year\n5 Year\nAUM as on 31 Oct 2025\n₹54705.44Cr\nDate of Allotment\n14 Feb, 2006\nExit Load\n12%\nview details\nFor exit within 30 days from the date of allotment - 0.25%;\nFor exit after 30 days and within 90 days from the date of allotment -0.10%\nFor exit after 90 days from the date of allotment - Nil.\nBenchmark :\nScheme Benchmark: BSE 100 TRI\nAdditional Benchmark: BSE Sensex TRI\nSuitable for :\nLong-Term Capital Appreciation\nCompare Fund\nInvest\nEnter SIP Amount\nEnter SIP Amount\nMin. Amount Rs.\n500\nEnter Lumpsum Amount\nEnter Lumpsum Amount\nMin. Lumpsum amount Rs.\n5,000\n(For Additional Investment Rs. 1,000)\nAdd to Cart\nProceed to Invest\n4165 people\nare already invested\nHistorical NAV\nSBI Large Cap Fund (Formerly known as SBI Bluechip Fund) - Regular Plan - Growth\nSBI Large Cap Fund (Formerly known as SBI Bluechip Fund) - Regular Plan - IDCW\nSBI Large Cap Fund (Formerly known as SBI Bluechip Fund) - Regular Plan - Growth\nSBI Large Cap Fund (Formerly known as SBI Bluechip Fund) - Direct Plan - IDCW\nSBI Large Cap Fund (Formerly known as SBI Bluechip Fund) - Direct Plan - Growth\n1 Year\n1 Year\n3 Year\n5 Year\nNAV as on\nNov 17, 2025\nNAV stands for Net Asset Value.\n₹\n95.293\n(\n+0.32% one day change\n)\nCreated with Highcharts 8.1.2\nValues\nNov 2…\nNov 2024\nDec 2024\nJan 2025\nFeb 2025\nMar 2025\nApr 2025\nMay 2025\nJun 2025\nJul 2025\nAug 2025\nSep 2025\nOct 2025\nNov 2025\n80\n85\n90\n95\n100\nPast Performance may or may not be sustained in future\nInvestment Criteria\nMin Lumpsum\n₹ 5,000\n& in multiples of 1\nMin Add Lumpsum\n₹ 1,000\n& in multiples of 1\nMin SIP Amount\n₹ 500\nReturns Calculator\nMonthly SIP\nLumpsum\nMonthly SIP\nMonthly SIP\nLumpsum\nEnter Investment Amount\n5 %\n6 %\n7 %\n8 %\n9 %\n10 %\n11 %\n12 %\n13 %\n14 %\n15 %\n16 %\n17 %\n18 %\n19 %\n20 %\n21 %\n22 %\n5 %\n5 %\n6 %\n7 %\n8 %\n9 %\n10 %\n11 %\n12 %\n13 %\n14 %\n15 %\n16 %\n17 %\n18 %\n19 %\n20 %\n21 %\n22 %\nDuration\n1Y\nNet Return\n₹6,165.009\nFund Overview\nPortfolio Breakup\nPerformance\nDocuments\nFund Data\nFund Overview\nSBI Large Cap Fund aims to provide investors with opportunities for long-term growth in capital through an active management of investments in a diversified basket of large cap equity\nThe fund invests a minimum of 80% in large cap stocks*. Generally, Large cap stocks are well established companies having good brand equity and are possibly market leaders in their industries\nSBI Large Cap Fund has the flexibility to invest up to 20% in equities other than large caps or debt and/or money market instruments\nThe fund follows a blend of growth and value style of investing with a combination of top down and bottom-up investment strategy for stock selection across sectors\n*Large Cap Stocks are – 1st -100th company in terms of full market capitalization.\nMr. Saurabh Pant -\nSaurabh Pant has over 16 years experience in capital markets. He joined SBI Funds Management Limited as a research analyst and currently manages equity funds. Saurabh is a Commerce graduate and holds a Master'sDegree in Business Economics from the University of Delhi.\n...\nSee More\nManaging this fund since\nApr 2024\nMore Funds\nmanaged by\nMr. Saurabh Pant\nVideos for\nSBI Large Cap Fund (Formerly known as SBI Bluechip Fund)\nProduct Label\nThis product is suitable for investors who are seeking*\nLong term capital appreciation\nInvestment in equity and equity-related instruments of large cap companies.\n*Investors should consult their financial advisors if in doubt whether the product is suitable for them.\nRiskometer\nSBI Large Cap Fund (Formerly known as SBI Bluechip Fund)\nLow\nLow to Moderate\nModerate\nModerately High\nHigh\nVery High\nRISKOMETER\nThe risk of the scheme is\nVery High\nBenchmark Riskometer\nBSE 100 TRI\nLow\nLow to Moderate\nModerate\nModerately High\nHigh\nVery High\nRISKOMETER\nThe risk of the benchmark is\nVery High\nPortfolio Breakup\nTop Holdings\n(as on\n31 Oct 2025\n)\nCreated with Highcharts 8.1.2\n7.88%\n7.35%\n7.13%\n5.45%\n3.96%\n3.95%\n0\n2\n4\n6\n8\n10\n12\n14\n16\n18\nRELIANCE INDUSTRIES LTD.\nHDFC BANK LTD.\nICICI BANK LTD.\nLARSEN & TOUBRO LTD.\nINFOSYS LTD.\nEICHER MOTORS LTD.\nView all holdings\nSector Allocations\nCreated with Highcharts 8.1.2\n30.57%\n8.85%\n8.54%\n6.7%\n5.95%\n5.65%\n0\n2\n4\n6\n8\n10\n12\n14\n16\n18\n20\n22\n24\n26\n28\n30\n32\n34\n36\n38\n40\nFINANCIAL SERVICES\nOIL, GAS & CONSUMABLE FUELS\nAUTOMOBILE AND AUTO COMPONENTS\nFAST MOVING CONSUMER GOODS\nHEALTHCARE\nINFORMATION TECHNOLOGY\nView all allocations\nAll Holdings\n(as on\n31 Oct 2025\n)\nAll Allocations\nPerformance\nRegular Growth\nDirect Growth\nCompounded Annualized Growth Rate Performance\n1Y\n3Y\n5Y\n10Y\nSince Inception\nSBI Large Cap Fund\n5.52%\n14.08%\n19.03%\n12.83%\n12.07%\nScheme Benchmark: BSE 100 TRI\nBenchmark\n7.06%\n15.08%\n19.67%\n14.13%\n13.09%\nAdditional Benchmark: BSE Sensex TRI\nAdditional Benchmark\n6.99%\n12.77%\n17.59%\n13.53%\n12.85%\nCurrent Value of Standard Investment of ₹10,000\n1Y\n3Y\n5Y\n10Y\nSince Inception\nSBI Large Cap Fund\n₹10552\n₹14854\n₹23921\n₹33475\n₹94599\nScheme Benchmark: BSE 100 TRI\nBenchmark\n₹10706\n₹15247\n₹24572\n₹37565\n₹113180\nAdditional Benchmark: BSE Sensex TRI\nAdditional Benchmark\n₹10699\n₹14346\n₹22502\n₹35630\n₹108489\nNotes:\nDifferent plans shall have different expense structure. In case of return calculated the IDCW option, it is assumed that dividend declared under the schemes have been reinvested at the prevailing NAV\nPast performance may or may not be sustained in future and same may not necessarily provide the basis for comparison with other investment\nLoad is not considered for computation of returns\nPeriod for which scheme’s performance has been provided is computed basis last day of the month-end preceding the date of advertisement. In case, the start/end date of the concerned period is a non-business day, the NAV of the previous date is considered for computation of returns\nThe data of the last working day has been considered for the calculation of performance\nWherever TRI data since inception for benchmarks is not available, benchmark performance is calculated using composite of CAGR and TRI values of the benchmark\nThe performance of the schemes is benchmarked to the Total Return variant of the Index\nTo view other open ended funds managed by the fund manager go to the Fund Manager section\nCompounded Annualized Growth Rate Performance\n1Y\n3Y\n5Y\n10Y\nSince Inception\nSBI Large Cap Fund\n6.24%\n14.88%\n19.89%\n13.8%\n15.39%\nScheme Benchmark: BSE 100 TRI\nBenchmark\n7.06%\n15.08%\n19.67%\n14.13%\n13.92%\nAdditional Benchmark: BSE Sensex TRI\nAdditional Benchmark\n6.99%\n12.77%\n17.59%\n13.53%\n13.48%\nCurrent Value of Standard Investment of ₹10,000\n1Y\n3Y\n5Y\n10Y\nSince Inception\nSBI Large Cap Fund\n₹10624\n₹15168\n₹24792\n₹36473\n₹62795\nScheme Benchmark: BSE 100 TRI\nBenchmark\n₹10706\n₹15247\n₹24572\n₹37565\n₹53293\nAdditional Benchmark: BSE Sensex TRI\nAdditional Benchmark\n₹10699\n₹14346\n₹22502\n₹35630\n₹50714\nNotes:\nDifferent plans shall have different expense structure. In case of return calculated the IDCW option, it is assumed that dividend declared under the schemes have been reinvested at the prevailing NAV\nPast performance may or may not be sustained in future and same may not necessarily provide the basis for comparison with other investment\nLoad is not considered for computation of returns\nPeriod for which scheme’s performance has been provided is computed basis last day of the month-end preceding the date of advertisement. In case, the start/end date of the concerned period is a non-business day, the NAV of the previous date is considered for computation of returns\nThe data of the last working day has been considered for the calculation of performance\nWherever TRI data since inception for benchmarks is not available, benchmark performance is calculated using composite of DCAGR and TRI values of the benchmark\nThe performance of the schemes is benchmarked to the Total Return variant of the Index\nTo view other open ended funds managed by the fund manager go to the Fund Manager section\nDocuments\nFile Name\nFile Type\nFile Size\nSBI Largecap Fund  Factsheet October 2025\n1  MB\nSBI Large Cap Fund MONTHLY PORTFOLIO - OCTOBER 2025\n82  KB\nSID - SBI Large Cap Fund (Formerly known as Bluechip Fund)\n1  MB\nKIM - SBI Large Cap Fund (Formerly known as Bluechip Fund)\n371  KB\nDownload\nFund Data\nQuantitative Data\nExpense Ratio Regular  in % (as on 31 Oct ,2025)\n:\n1.48\nExpense Ratio Direct  in % (as on 31 Oct ,2025)\n:\n0.81\nTracking Error Regular (as on 14 Nov ,2025)\n:\n2.4542 %\nSharpe Ratio\n:\n0.64\nStandard Deviation\n:\n11.36%\nBeta\n:\n0.9\n*Tracking Error is computed using Total Returns Index for 1 Year Period ending  14 Nov ,2025 based on day-end NAV respectively.\n**All expense ratios are inclusive of GST on Management Fees\nIDCW History\nChoose Plan\nSBI Large Cap Fund (Formerly known as SBI Bluechip Fund) - Regular Plan - IDCW\nSBI Large Cap Fund (Formerly known as SBI Bluechip Fund) - Regular Plan - IDCW\nSBI Large Cap Fund (Formerly known as SBI Bluechip Fund) - Direct Plan - IDCW\nRecord Date\nIDCW*\nNAV(₹)\n23 Sep 2016\n1\n18.59640\n17 Jul 2015\n2.5\n17.68800\n21 Mar 2014\n1.8\n12.76180\nFace Value: ₹ 10\nPursuant to payment of IDCW, the NAV of IDCW Option of schemes/plans would fall to the extent of payout and statutory levy, if applicable.\nAfter dividend distribution tax.\nFAQ Section\nHow to Invest in SBI Large Cap Fund (Formerly known as SBI Bluechip Fund)?\n> Log in to the website.\n> Choose between Lumpsum or Systematic Investment Plan (SIP).\n> Choose your bank and preferred payment method.\n> An OTP will be sent to your registered email ID and mobile number.\n> Your transaction will be processed after OTP verification.\nWhat is the current NAV of SBI Large Cap Fund (Formerly known as SBI Bluechip Fund)?\nLatest closing NAV as on 17 Nov, 2025 for SBI Large Cap Fund (Formerly known as SBI Bluechip Fund) - Regular Plan - Growth is Rs. 95.293\nWhat is the AUM of SBI Large Cap Fund (Formerly known as SBI Bluechip Fund)?\nAUM of SBI Large Cap Fund (Formerly known as SBI Bluechip Fund) is 54705.44 Cr.\nWhat is the Riskometer level of SBI Large Cap Fund (Formerly known as SBI Bluechip Fund)?\nSBI Large Cap Fund (Formerly known as SBI Bluechip Fund) is rated as a VERY HIGH. Benchmark Riskometer for this fund is S&P BSE 100 Index.\nWhat are the top holdings of SBI Large Cap Fund (Formerly known as SBI Bluechip Fund)?\nTop Holdings for the fund as per percentage of amount invested is as follows:\n> RELIANCE INDUSTRIES LTD. : 7.88 %\n> HDFC BANK LTD. : 7.35 %\n> ICICI BANK LTD. : 7.13 %\n> LARSEN & TOUBRO LTD. : 5.45 %\n> INFOSYS LTD. : 3.96 %\n> EICHER MOTORS LTD. : 3.95 %\nIs there any lock-in period for SBI Large Cap Fund (Formerly known as SBI Bluechip Fund)?\nNo lock-in period is applicable for this fund.\nWhat is the expense ratio of SBI Large Cap Fund (Formerly known as SBI Bluechip Fund)?\nExpense ratio for Regular scheme is 1.48% as on 31 Oct 2025 and Expense Ratio for Direct Scheme is 0.81% as on 31 Oct 2025\nHow can I redeem my investments in SBI Large Cap Fund (Formerly known as SBI Bluechip Fund)?\n> Login to your account.\n> In the Dashboard, go to the Portfolio Snapshot section and click on Transact > Redeem.\n> Enter the Amount/Units you wish to redeem.\n> An OTP will be sent to your registered email ID/mobile number.\n> After OTP verification, your redemption will be processed in 3 business working days.\nWhat are the top sectors SBI Large Cap Fund (Formerly known as SBI Bluechip Fund) has invested in?\nSector Allocations for as per percentage of amount invested is as follows:\n> FINANCIAL SERVICES : 30.57 %\n> OIL, GAS & CONSUMABLE FUELS : 8.85 %\n> AUTOMOBILE AND AUTO COMPONENTS : 8.54 %\n> FAST MOVING CONSUMER GOODS : 6.7 %\n> HEALTHCARE : 5.95 %\n> INFORMATION TECHNOLOGY : 5.65 %\nWho manages the SBI Large Cap Fund (Formerly known as SBI Bluechip Fund)?\nThe Fund manager for this fund is:\n> Mr. Saurabh Pant since April 2024\nWhat is the minimum investment in SBI Large Cap Fund (Formerly known as SBI Bluechip Fund)?\nMinimum Lumpsum Amount applicable for this fund is Rs. 5000 in multiples of 1.\nMinimum Additional Lumpsum Amount applicable for this fund is Rs. 1000 in multiples of 1.\nMinimum SIP Amount applicable for fund is Rs. 500\nStart your investment in\n×\nSBI Magnum Fund Ultra Short Duration\nEdit Plan\nDirect - Growth\nDirect - IDCW\nRegular - Growth\nRegular - IDCW\nSelect IDCW option\nReinvest\nPayout\nIDCW option is required.\nSBI Magnum Fund Ultra Short Duration\nDirect - Growth\nMonthly SIP\n₹500\nStart Date\n26 Feb 2023\nEdit\nExisting Scheme in Cart\nLooks like you already have an existing\nSIP\nin this this scheme in your cart.\nSIP\ndetails listed below:\nEXISTING\nSIP\nDETAILS\nScheme Name\nSBI Magnum Fund Ultra Short Duration - Direct Growth\nSIP\nAmount\n500\nFrequency\nWeekly\nStart Date\n3 June 2023\nEnd Date\n3 June 2032\nTop-up Frequency\nYearly\nTop-up in\nAmount\nTop-up Percent\n5%\nAdd to Cart without Top-up\nAdd to Cart with Top-up\nProceed with existing SIP\nProceed with new SIP\nProceed with existing Lumpsum\nProceed with new Lumpsum\nLumpsum\nStart SIP\nLumpsum Amount\n₹\nMinimum Amount is Rs\nfor Lumpsum/Additional Purchase as applicable\nPlease enter Lumpsum Amount.\nMaximum Amount is Rs 1000000000 for Lumpsum/Additional Purchase as applicable\nAmount should be in multiple of Rs\nfor Lumpsum/Additional Purchase as applicable\nDemat Option\ni\nUnits will be allocated to your Demat Account\nNSDL\nCDSL\nDemat Account No\nIN\nPlease enter a valid 14 digit Demat Account Number\nPlease enter a valid 16 digit Demat Account Number\nDemat Account Number is required\nSIP Amount\n₹\n₹500\n₹1000\n₹2500\nEnter SIP amount.\nSIP amount must be greater than\nfor a\nSIP\nInvestment amount for SBI Small Cap Fund is restricted to Rs.25000 per PAN (first holder/Guardian) per month.\nMaximum Amount is Rs 100000000 for SIP as applicable.\nAmount should be in multiple of Rs\nfor a SIP\nSIP Frequency\nMonthly\nWeekly\nYearly\nMonthly\nWeekly\nYearly\nSIP Start Date\nSelect Day of Installment.\nSIP Tenure\n5 Year\n10 Year\n25 Year\n30 Year\nSelect Custom Date\n5 Year\n10 Year\n25 Year\n30 Year\nSelect Custom Date\nSIP will start on\n& run till\nOne Last Step, Top-Up\nTop-up in\nPercentage\nAmount\nTop-up Frequency\nHalf Yearly\nYearly\nTop-up Percentage\n5%\n10%\n15%\n20%\n25%\n30%\n35%\n40%\n45%\n50%\n55%\n60%\n65%\n70%\n75%\n80%\n85%\n90%\n95%\n100%\n5%\n10%\n15%\n20%\n25%\n30%\n35%\n40%\n45%\n50%\n55%\n60%\n65%\n70%\n75%\n80%\n85%\n90%\n95%\n100%\nTop-up Amount\n₹\nSIP Top Up amount must be greater than Rs 500 amount\nSIP Top Up amount must be in multiples of Rs.500\nSIP Top Up amount is required\nSIP Top Up amount must be less than ₹ 1,00,00,000\nNo. of top-ups\n1\n2\n3\n4\n5\n6\n7\n8\n9\n10\n11\n12\n13\n14\n15\n16\n17\n18\n19\n20\n21\n22\n23\n24\n25\n26\n27\n28\n29\n30\n31\n32\n33\n34\n35\n36\n37\n38\n39\n40\n41\n42\n43\n44\n45\n46\n47\n48\n49\n50\n1\n2\n3\n4\n5\n6\n7\n8\n9\n10\n11\n12\n13\n14\n15\n16\n17\n18\n19\n20\n21\n22\n23\n24\n25\n26\n27\n28\n29\n30\n31\n32\n33\n34\n35\n36\n37\n38\n39\n40\n41\n42\n43\n44\n45\n46\n47\n48\n49\n50\nPlease select No. of topups.\nMax SIP Amount : ₹\nTop Up Max Amount must not Exceed ₹1,00,00,000/-\nThe remaining tenure of your SIP is less than\nto top up a SIP please ensure a minimum of\nare available.\nTop up Till\nSelect Day of Installment.\nMax SIP Amount: ₹\nTop Up Max Amount must not Exceed ₹1,00,00,000/-\nYour top up will end on date\nBy opting out of SIP top-up, you lose out on multiplying your wealth\nSetup Auto Transfer\nAs you grow older, we can dynamically shift your Investments to\na more conservative plan\nLearn More\nThis fund has a lock in period of 5 years or till the investor\nattains the age of 65 whichever is earlier\nI want to top-up my SIP amount\nYour peers (20-30 yrs) usually top-up their SIPs annually\nTop-up Frequency\nHalf-yearly\nYearly\nTop-up in\nAmount\nPercentage\nTop-up Amount\n₹\nMax. amount ₹5,000\nTop-up Till\nAdd to Cart\nInvest Now\nProceed without Top-up\nProceed with Top-up\nHow Auto Transfer Work\nIn case of Auto Transfer, all investment will be made depending on the investor's age. at the time\nof investment into the suitable corresponding investment Plan.Association of investment plan to\nage-groups and risk appetite of investors is illustrated in the following table.\nAge Range(year)\nplan\nUpto 40\nAggresive\n40-50\nAggresive Hybrid\n50-60\nConservative Hybrid\nAbove 60\nConservative\nBasis your date of birth\nregistered in this folio\nis most suitable to you.The fund is subject to a lock in of 5 Years.\nClose\nSetup Auto Transfer\nEmail\nFrom\n*\nEnter Name\nEnter Name\nPlease provide name\nTo\n*\nEnter Email\nEnter Email\nPlease provide valid email(s)\n(max upto 10 email id's allowed separated by ,)\nSubject\n*\nSend\nReset\nFund Overview\nPortfolio Breakup\nPerformance\nFund Data\nSimilar Funds\nView All Funds\nReceive Assistance\nEnter Name\nEnter Name\nPlease enter name\nEnter City\nEnter City\nPlease enter city\nEnter Mobile Number\nEnter Mobile Number\nPlease enter a mobile number\nPlease enter a valid mobile number\nEnter Email ID\nEnter Email ID\nPlease enter an email ID\nPlease enter a valid email ID\nSubmit\nCancel\nLoading...\nMessage Sent!\nGo Back\nSuccess\nFailure\nMessage Sent!\nGo Back\nX",
    "tables": [
      {
        "headers": [
          "Compounded Annualized Growth Rate Performance",
          "1Y",
          "3Y",
          "5Y",
          "10Y",
          "Since Inception"
        ],
        "rows": [
          [
            "SBI Large Cap Fund",
            "5.52%",
            "14.08%",
            "19.03%",
            "12.83%",
            "12.07%"
          ],
          [
            "Scheme Benchmark: BSE 100 TRIBenchmark",
            "7.06%",
            "15.08%",
            "19.67%",
            "14.13%",
            "13.09%"
          ],
          [
            "Additional Benchmark: BSE Sensex TRIAdditional Benchmark",
            "6.99%",
            "12.77%",
            "17.59%",
            "13.53%",
            "12.85%"
          ]
        ]
      },
      {
        "headers": [
          "Current Value of Standard Investment of ₹10,000",
          "1Y",
          "3Y",
          "5Y",
          "10Y",
          "Since Inception"
        ],
        "rows": [
          [
            "SBI Large Cap Fund",
            "₹10552",
            "₹14854",
            "₹23921",
            "₹33475",
            "₹94599"
          ],
          [
            "Scheme Benchmark: BSE 100 TRIBenchmark",
            "₹10706",
            "₹15247",
            "₹24572",
            "₹37565",
            "₹113180"
          ],
          [
            "Additional Benchmark: BSE Sensex TRIAdditional Benchmark",
            "₹10699",
            "₹14346",
            "₹22502",
            "₹35630",
            "₹108489"
          ]
        ]
      },
      {
        "headers": [
          "Compounded Annualized Growth Rate Performance",
          "1Y",
          "3Y",
          "5Y",
          "10Y",
          "Since Inception"
        ],
        "rows": [
          [
            "SBI Large Cap Fund",
            "6.24%",
            "14.88%",
            "19.89%",
            "13.8%",
            "15.39%"
          ],
          [
            "Scheme Benchmark: BSE 100 TRIBenchmark",
            "7.06%",
            "15.08%",
            "19.67%",
            "14.13%",
            "13.92%"
          ],
          [
            "Additional Benchmark: BSE Sensex TRIAdditional Benchmark",
            "6.99%",
            "12.77%",
            "17.59%",
            "13.53%",
            "13.48%"
          ]
        ]
      },
      {
        "headers": [
          "Current Value of Standard Investment of ₹10,000",
          "1Y",
          "3Y",
          "5Y",
          "10Y",
          "Since Inception"
        ],
        "rows": [
          [
            "SBI Large Cap Fund",
            "₹10624",
            "₹15168",
            "₹24792",
            "₹36473",
            "₹62795"
          ],
          [
            "Scheme Benchmark: BSE 100 TRIBenchmark",
            "₹10706",
            "₹15247",
            "₹24572",
            "₹37565",
            "₹53293"
          ],
          [
            "Additional Benchmark: BSE Sensex TRIAdditional Benchmark",
            "₹10699",
            "₹14346",
            "₹22502",
            "₹35630",
            "₹50714"
          ]
        ]
      },
      {
        "headers": [
          "File Name",
          "File Type",
          "File Size"
        ],
        "rows": [
          [
            "SBI Largecap Fund  Factsheet October 2025",
            "",
            "1  MB"
          ],
          [
            "SBI Large Cap Fund MONTHLY PORTFOLIO - OCTOBER 2025",
            "",
            "82  KB"
          ],
          [
            "SID - SBI Large Cap Fund (Formerly known as Bluechip Fund)",
            "",
            "1  MB"
          ],
          [
            "KIM - SBI Large Cap Fund (Formerly known as Bluechip Fund)",
            "",
            "371  KB"
          ]
        ]
      },
      {
        "headers": [
          "Quantitative Data"
        ],
        "rows": [
          [
            "Expense Ratio Regular  in % (as on 31 Oct ,2025)",
            ":",
            "1.48"
          ],
          [
            "Expense Ratio Direct  in % (as on 31 Oct ,2025)",
            ":",
            "0.81"
          ],
          [
            "Tracking Error Regular (as on 14 Nov ,2025)",
            ":",
            "2.4542 %"
          ],
          [
            "Sharpe Ratio",
            ":",
            "0.64"
          ],
          [
            "Standard Deviation",
            ":",
            "11.36%"
          ],
          [
            "Beta",
            ":",
            "0.9"
          ]
        ]
      },
      {
        "headers": [
          "Record Date",
          "IDCW*",
          "NAV(₹)"
        ],
        "rows": [
          [
            "23 Sep 2016",
            "1",
            "18.59640"
          ],
          [
            "17 Jul 2015",
            "2.5",
            "17.68800"
          ],
          [
            "21 Mar 2014",
            "1.8",
            "12.76180"
          ]
        ]
      },
      {
        "headers": [
          "Age Range(year)",
          "plan"
        ],
        "rows": [
          [
            "Upto 40",
            "Aggresive"
          ],
          [
            "40-50",
            "Aggresive Hybrid"
          ],
          [
            "50-60",
            "Conservative Hybrid"
          ],
          [
            "Above 60",
            "Conservative"
          ]
        ]
      }
    ],
    "metadata": {
      "url": "https://www.sbimf.com/sbimf-scheme-details/sbi-large-cap-fund-(formerly-known-as-sbi-bluechip-fund)-43",
      "title": "SBI Large Cap Fund",
      "last_modified": null,
      "breadcrumbs": []
    },
    "factual_data": {
      "expense_ratio_regular": "1.48",
      "expense_ratio_direct": "0.81",
      "exit_load": "12",
      "minimum_sip": "500",
      "minimum_lumpsum": "5000",
      "lock_in_period": "5",
      "riskometer": "100",
      "benchmark": "performance is calculated using composite of CAGR and TRI values of the benchmark\nThe performance of the schemes is benchmarked to the Total Return variant of the Index"
    },
    "scraped_date": "2025-11-17T22:21:00.835616",
    "scheme_name": "SBI Large Cap Fund",
    "document_type": "scheme_details",
    "scheme_name_validated": true,
    "match_score": 1.0
  },
  {
    "url": "https://www.sbimf.com/sbimf-scheme-details/sbi-multicap-fund-609",
    "title": "SBI Multicap Fund",
    "content": "SBI Multicap Fund\nScheme Type :\nAn open ended equity scheme investing across large cap, midcap, small cap stocks\nEQUITY\nOpen Ended\nAn open ended equity scheme investing across large cap, midcap, small cap stocks\nVERY HIGH Risk\nReturns                                                     for Regular-Growth\n16.29%\n16.29%\n6.04%\n16.53%\nNA\nSince Inception\n1 Year\n3 Year\n5 Year\nSince Inception\nSince Inception\n1 Year\n3 Year\n5 Year\nReturns for Direct growth\n17.37%\n17.37%\n6.92%\n17.54%\nNA\nSince Inception\n1 Year\n3 Year\n5 Year\nSince Inception\nSince Inception\n1 Year\n3 Year\n5 Year\nAUM as on 31 Oct 2025\n₹23996.8Cr\nDate of Allotment\n08 Mar, 2022\nExit Load\n12%\nview details\nFor exit within 30 days from the date of allotment - 0.25%\nFor exit after 30 days and within 90 days from the date of allotment -0.10%\nFor exit after 90 days from the date of allotment - Nil\nBenchmark :\nScheme Benchmark: Nifty500 Multicap 50:25:25 TRI\nAdditional Benchmark: BSE Sensex TRI\nSuitable for :\nLong-Term Capital Appreciation\nCapital growth\nCompare Fund\nInvest\nEnter SIP Amount\nEnter SIP Amount\nMin. Amount Rs.\n500\nEnter Lumpsum Amount\nEnter Lumpsum Amount\nMin. Lumpsum amount Rs.\n5,000\n(For Additional Investment Rs. 1,000)\nAdd to Cart\nProceed to Invest\n24 people\nare already invested\nHistorical NAV\nSBI Multicap Fund- Regular Plan - Growth\nSBI Multicap Fund- Regular Plan - Growth\nSBI Multicap Fund- Direct Plan - IDCW\nSBI Multicap Fund- Regular Plan - IDCW\nSBI Multicap Fund- Direct Plan - Growth\n1 Year\n1 Year\n3 Year\n5 Year\nNAV as on\nNov 17, 2025\nNAV stands for Net Asset Value.\n₹\n17.4025\n(\n+0.36% one day change\n)\nPast Performance may or may not be sustained in future\nInvestment Criteria\nMin Lumpsum\n₹ 5,000\n& in multiples of 1\nMin Add Lumpsum\n₹ 1,000\n& in multiples of 1\nMin SIP Amount\n₹ 500\nReturns Calculator\nMonthly SIP\nLumpsum\nMonthly SIP\nMonthly SIP\nLumpsum\nEnter Investment Amount\n5 %\n6 %\n7 %\n8 %\n9 %\n10 %\n11 %\n12 %\n13 %\n14 %\n15 %\n16 %\n17 %\n18 %\n19 %\n20 %\n21 %\n22 %\n5 %\n5 %\n6 %\n7 %\n8 %\n9 %\n10 %\n11 %\n12 %\n13 %\n14 %\n15 %\n16 %\n17 %\n18 %\n19 %\n20 %\n21 %\n22 %\nDuration\n1Y\nNet Return\n₹6,165.009\nFund Overview\nPortfolio Breakup\nPerformance\nDocuments\nFund Data\nFund Overview\nTo provide investors with opportunities for long term growth in capital from a diversified portfolio of equity and equity related instruments across market capitalization. However, there can be no assurance that the investment objective of the Scheme will be realized.\nThe scheme will follow a bottom-up approach to stock-picking and choose companies across sectors The scheme will invest in diversified portfolio of stocks across market capitalization.\nLarge Cap Stocks – 1st -100th company in terms of full market capitalization. Mid Cap:101st to 250th company in terms of full market capitalization. Small Cap: 251st company onwards in\nterms of full market capitalization. The exposure across these stocks will be in line with limits/classification defined by AMFI/SEBI from time to time\nMr. R Srinivasan -\nR Srinivasan has over 30 years’ rich experience in the financial services space. He has been associated with SBI Funds Management Limited since 2009 and as CIO – Equity directly manages a number of funds. He was formerly the Head of Equity. Srinivasan is a postgraduate in Commerce and has done his MFM from the University of Mumbai.\n...\nSee More\nManaging this fund since\nMar 2022\nMore Funds\nmanaged by\nMr. R Srinivasan\nMr. Saurabh Pant -\nSaurabh Pant has over 16 years experience in capital markets. He joined SBI Funds Management Limited as a research analyst and currently manages equity funds. Saurabh is a Commerce graduate and holds a Master'sDegree in Business Economics from the University of Delhi.\n...\nSee More\nManaging this fund since\nApr 2024\nMore Funds\nmanaged by\nMr. Saurabh Pant\nProduct Label\nThis product is suitable for investors who are seeking*\nLong term wealth creation\nInvestment predominantly in equity and equity related securities across market capitalisation\n*Investors should consult their financial advisors if in doubt whether the product is suitable for them.\nRiskometer\nSBI Multicap Fund\nLow\nLow to Moderate\nModerate\nModerately High\nHigh\nVery High\nRISKOMETER\nThe risk of the scheme is\nVery High\nBenchmark Riskometer\nNifty500 Multicap 50:25:25 TRI\nLow\nLow to Moderate\nModerate\nModerately High\nHigh\nVery High\nRISKOMETER\nThe risk of the benchmark is\nVery High\nPortfolio Breakup\nTop Holdings\n(as on\n31 Oct 2025\n)\nCreated with Highcharts 8.1.2\n5.05%\n4.1%\n3.95%\n3.52%\n3.41%\n3.26%\n0\n2\n4\n6\n8\n10\n12\n14\n16\nCASH, CASH EQUIVALENTS AND OTHERS\nKOTAK MAHINDRA BANK LTD.\nHDFC BANK LTD.\nK.P.R. MILL LTD.\nADANI POWER LTD.\nBAJAJ FINSERV LTD.\nView all holdings\nSector Allocations\nCreated with Highcharts 8.1.2\n23.21%\n10.38%\n9.77%\n6.8%\n5.79%\n5.65%\n0\n2\n4\n6\n8\n10\n12\n14\n16\n18\n20\n22\n24\n26\n28\n30\n32\n34\nFINANCIAL SERVICES\nCONSUMER DURABLES\nCONSUMER SERVICES\nMETALS & MINING\nPOWER\nHEALTHCARE\nView all allocations\nAll Holdings\n(as on\n31 Oct 2025\n)\nAll Allocations\nPerformance\nRegular Growth\nDirect Growth\nCompounded Annualized Growth Rate Performance\n1Y\n3Y\n5Y\n10Y\nSince Inception\nSBI MultiCap Fund\n6.04%\n16.53%\nNA\nNA\n16.29%\nScheme Benchmark: Nifty500 Multicap 50:25:25 TRI\nBenchmark\n4.47%\n19.02%\nNA\nNA\n19.33%\nAdditional Benchmark: BSE Sensex TRI\nAdditional Benchmark\n6.99%\n12.77%\nNA\nNA\n14.67%\nCurrent Value of Standard Investment of ₹10,000\n1Y\n3Y\n5Y\n10Y\nSince Inception\nSBI MultiCap Fund\n₹10604\n₹15829\nNA\nNA\n₹17351\nScheme Benchmark: Nifty500 Multicap 50:25:25 TRI\nBenchmark\n₹10447\n₹16868\nNA\nNA\n₹19070\nAdditional Benchmark: BSE Sensex TRI\nAdditional Benchmark\n₹10699\n₹14346\nNA\nNA\n₹16487\nNotes:\nDifferent plans shall have different expense structure. In case of return calculated the IDCW option, it is assumed that dividend declared under the schemes have been reinvested at the prevailing NAV\nPast performance may or may not be sustained in future and same may not necessarily provide the basis for comparison with other investment\nLoad is not considered for computation of returns\nPeriod for which scheme’s performance has been provided is computed basis last day of the month-end preceding the date of advertisement. In case, the start/end date of the concerned period is a non-business day, the NAV of the previous date is considered for computation of returns\nThe data of the last working day has been considered for the calculation of performance\nWherever TRI data since inception for benchmarks is not available, benchmark performance is calculated using composite of CAGR and TRI values of the benchmark\nThe performance of the schemes is benchmarked to the Total Return variant of the Index\nTo view other open ended funds managed by the fund manager go to the Fund Manager section\nCompounded Annualized Growth Rate Performance\n1Y\n3Y\n5Y\n10Y\nSince Inception\nSBI MultiCap Fund\n6.92%\n17.54%\nNA\nNA\n17.37%\nScheme Benchmark: Nifty500 Multicap 50:25:25 TRI\nBenchmark\n4.47%\n19.02%\nNA\nNA\n19.33%\nAdditional Benchmark: BSE Sensex TRI\nAdditional Benchmark\n6.99%\n12.77%\nNA\nNA\n14.67%\nCurrent Value of Standard Investment of ₹10,000\n1Y\n3Y\n5Y\n10Y\nSince Inception\nSBI MultiCap Fund\n₹10692\n₹16247\nNA\nNA\n₹17947\nScheme Benchmark: Nifty500 Multicap 50:25:25 TRI\nBenchmark\n₹10447\n₹16868\nNA\nNA\n₹19070\nAdditional Benchmark: BSE Sensex TRI\nAdditional Benchmark\n₹10699\n₹14346\nNA\nNA\n₹16487\nNotes:\nDifferent plans shall have different expense structure. In case of return calculated the IDCW option, it is assumed that dividend declared under the schemes have been reinvested at the prevailing NAV\nPast performance may or may not be sustained in future and same may not necessarily provide the basis for comparison with other investment\nLoad is not considered for computation of returns\nPeriod for which scheme’s performance has been provided is computed basis last day of the month-end preceding the date of advertisement. In case, the start/end date of the concerned period is a non-business day, the NAV of the previous date is considered for computation of returns\nThe data of the last working day has been considered for the calculation of performance\nWherever TRI data since inception for benchmarks is not available, benchmark performance is calculated using composite of DCAGR and TRI values of the benchmark\nThe performance of the schemes is benchmarked to the Total Return variant of the Index\nTo view other open ended funds managed by the fund manager go to the Fund Manager section\nDocuments\nFund Data\nQuantitative Data\nExpense Ratio Regular  in % (as on 31 Oct ,2025)\n:\n1.65\nExpense Ratio Direct  in % (as on 31 Oct ,2025)\n:\n0.81\nSource: CRISIL Fund Analyser\nRisk Free rate: FBIL Overnight Mibor rate (9.39% as on 01 Jan, 0001) basis for ratio calculation : 3 Years Monthly Data points\n**All expense ratios are inclusive of GST on Management Fees\nIDCW History\nChoose Plan\nSBI Multicap Fund- Direct Plan - IDCW\nSBI Multicap Fund- Direct Plan - IDCW\nSBI Multicap Fund- Regular Plan - IDCW\nFAQ Section\nStart your investment in\n×\nSBI Magnum Fund Ultra Short Duration\nEdit Plan\nDirect - Growth\nDirect - IDCW\nRegular - Growth\nRegular - IDCW\nSelect IDCW option\nReinvest\nPayout\nIDCW option is required.\nSBI Magnum Fund Ultra Short Duration\nDirect - Growth\nMonthly SIP\n₹500\nStart Date\n26 Feb 2023\nEdit\nExisting Scheme in Cart\nLooks like you already have an existing\nSIP\nin this this scheme in your cart.\nSIP\ndetails listed below:\nEXISTING\nSIP\nDETAILS\nScheme Name\nSBI Magnum Fund Ultra Short Duration - Direct Growth\nSIP\nAmount\n500\nFrequency\nWeekly\nStart Date\n3 June 2023\nEnd Date\n3 June 2032\nTop-up Frequency\nYearly\nTop-up in\nAmount\nTop-up Percent\n5%\nAdd to Cart without Top-up\nAdd to Cart with Top-up\nProceed with existing SIP\nProceed with new SIP\nProceed with existing Lumpsum\nProceed with new Lumpsum\nLumpsum\nStart SIP\nLumpsum Amount\n₹\nMinimum Amount is Rs\nfor Lumpsum/Additional Purchase as applicable\nPlease enter Lumpsum Amount.\nMaximum Amount is Rs 1000000000 for Lumpsum/Additional Purchase as applicable\nAmount should be in multiple of Rs\nfor Lumpsum/Additional Purchase as applicable\nDemat Option\ni\nUnits will be allocated to your Demat Account\nNSDL\nCDSL\nDemat Account No\nIN\nPlease enter a valid 14 digit Demat Account Number\nPlease enter a valid 16 digit Demat Account Number\nDemat Account Number is required\nSIP Amount\n₹\n₹500\n₹1000\n₹2500\nEnter SIP amount.\nSIP amount must be greater than\nfor a\nSIP\nInvestment amount for SBI Small Cap Fund is restricted to Rs.25000 per PAN (first holder/Guardian) per month.\nMaximum Amount is Rs 100000000 for SIP as applicable.\nAmount should be in multiple of Rs\nfor a SIP\nSIP Frequency\nMonthly\nWeekly\nYearly\nMonthly\nWeekly\nYearly\nSIP Start Date\nSelect Day of Installment.\nSIP Tenure\n5 Year\n10 Year\n25 Year\n30 Year\nSelect Custom Date\n5 Year\n10 Year\n25 Year\n30 Year\nSelect Custom Date\nSIP will start on\n& run till\nOne Last Step, Top-Up\nTop-up in\nPercentage\nAmount\nTop-up Frequency\nHalf Yearly\nYearly\nTop-up Percentage\n5%\n10%\n15%\n20%\n25%\n30%\n35%\n40%\n45%\n50%\n55%\n60%\n65%\n70%\n75%\n80%\n85%\n90%\n95%\n100%\n5%\n10%\n15%\n20%\n25%\n30%\n35%\n40%\n45%\n50%\n55%\n60%\n65%\n70%\n75%\n80%\n85%\n90%\n95%\n100%\nTop-up Amount\n₹\nSIP Top Up amount must be greater than Rs 500 amount\nSIP Top Up amount must be in multiples of Rs.500\nSIP Top Up amount is required\nSIP Top Up amount must be less than ₹ 1,00,00,000\nNo. of top-ups\n1\n2\n3\n4\n5\n6\n7\n8\n9\n10\n11\n12\n13\n14\n15\n16\n17\n18\n19\n20\n21\n22\n23\n24\n25\n26\n27\n28\n29\n30\n31\n32\n33\n34\n35\n36\n37\n38\n39\n40\n41\n42\n43\n44\n45\n46\n47\n48\n49\n50\n1\n2\n3\n4\n5\n6\n7\n8\n9\n10\n11\n12\n13\n14\n15\n16\n17\n18\n19\n20\n21\n22\n23\n24\n25\n26\n27\n28\n29\n30\n31\n32\n33\n34\n35\n36\n37\n38\n39\n40\n41\n42\n43\n44\n45\n46\n47\n48\n49\n50\nPlease select No. of topups.\nMax SIP Amount : ₹\nTop Up Max Amount must not Exceed ₹1,00,00,000/-\nThe remaining tenure of your SIP is less than\nto top up a SIP please ensure a minimum of\nare available.\nTop up Till\nSelect Day of Installment.\nMax SIP Amount: ₹\nTop Up Max Amount must not Exceed ₹1,00,00,000/-\nYour top up will end on date\nBy opting out of SIP top-up, you lose out on multiplying your wealth\nSetup Auto Transfer\nAs you grow older, we can dynamically shift your Investments to\na more conservative plan\nLearn More\nThis fund has a lock in period of 5 years or till the investor\nattains the age of 65 whichever is earlier\nI want to top-up my SIP amount\nYour peers (20-30 yrs) usually top-up their SIPs annually\nTop-up Frequency\nHalf-yearly\nYearly\nTop-up in\nAmount\nPercentage\nTop-up Amount\n₹\nMax. amount ₹5,000\nTop-up Till\nAdd to Cart\nInvest Now\nProceed without Top-up\nProceed with Top-up\nHow Auto Transfer Work\nIn case of Auto Transfer, all investment will be made depending on the investor's age. at the time\nof investment into the suitable corresponding investment Plan.Association of investment plan to\nage-groups and risk appetite of investors is illustrated in the following table.\nAge Range(year)\nplan\nUpto 40\nAggresive\n40-50\nAggresive Hybrid\n50-60\nConservative Hybrid\nAbove 60\nConservative\nBasis your date of birth\nregistered in this folio\nis most suitable to you.The fund is subject to a lock in of 5 Years.\nClose\nSetup Auto Transfer\nEmail\nFrom\n*\nEnter Name\nEnter Name\nPlease provide name\nTo\n*\nEnter Email\nEnter Email\nPlease provide valid email(s)\n(max upto 10 email id's allowed separated by ,)\nSubject\n*\nSend\nReset\nFund Overview\nPortfolio Breakup\nPerformance\nFund Data\nSimilar Funds\nView All Funds\nReceive Assistance\nEnter Name\nEnter Name\nPlease enter name\nEnter City\nEnter City\nPlease enter city\nEnter Mobile Number\nEnter Mobile Number\nPlease enter a mobile number\nPlease enter a valid mobile number\nEnter Email ID\nEnter Email ID\nPlease enter an email ID\nPlease enter a valid email ID\nSubmit\nCancel\nLoading...\nMessage Sent!\nGo Back\nSuccess\nFailure\nMessage Sent!\nGo Back\nX",
    "tables": [
      {
        "headers": [
          "Compounded Annualized Growth Rate Performance",
          "1Y",
          "3Y",
          "5Y",
          "10Y",
          "Since Inception"
        ],
        "rows": [
          [
            "SBI MultiCap Fund",
            "6.04%",
            "16.53%",
            "NA",
            "NA",
            "16.29%"
          ],
          [
            "Scheme Benchmark: Nifty500 Multicap 50:25:25 TRIBenchmark",
            "4.47%",
            "19.02%",
            "NA",
            "NA",
            "19.33%"
          ],
          [
            "Additional Benchmark: BSE Sensex TRIAdditional Benchmark",
            "6.99%",
            "12.77%",
            "NA",
            "NA",
            "14.67%"
          ]
        ]
      },
      {
        "headers": [
          "Current Value of Standard Investment of ₹10,000",
          "1Y",
          "3Y",
          "5Y",
          "10Y",
          "Since Inception"
        ],
        "rows": [
          [
            "SBI MultiCap Fund",
            "₹10604",
            "₹15829",
            "NA",
            "NA",
            "₹17351"
          ],
          [
            "Scheme Benchmark: Nifty500 Multicap 50:25:25 TRIBenchmark",
            "₹10447",
            "₹16868",
            "NA",
            "NA",
            "₹19070"
          ],
          [
            "Additional Benchmark: BSE Sensex TRIAdditional Benchmark",
            "₹10699",
            "₹14346",
            "NA",
            "NA",
            "₹16487"
          ]
        ]
      },
      {
        "headers": [
          "Compounded Annualized Growth Rate Performance",
          "1Y",
          "3Y",
          "5Y",
          "10Y",
          "Since Inception"
        ],
        "rows": [
          [
            "SBI MultiCap Fund",
            "6.92%",
            "17.54%",
            "NA",
            "NA",
            "17.37%"
          ],
          [
            "Scheme Benchmark: Nifty500 Multicap 50:25:25 TRIBenchmark",
            "4.47%",
            "19.02%",
            "NA",
            "NA",
            "19.33%"
          ],
          [
            "Additional Benchmark: BSE Sensex TRIAdditional Benchmark",
            "6.99%",
            "12.77%",
            "NA",
            "NA",
            "14.67%"
          ]
        ]
      },
      {
        "headers": [
          "Current Value of Standard Investment of ₹10,000",
          "1Y",
          "3Y",
          "5Y",
          "10Y",
          "Since Inception"
        ],
        "rows": [
          [
            "SBI MultiCap Fund",
            "₹10692",
            "₹16247",
            "NA",
            "NA",
            "₹17947"
          ],
          [
            "Scheme Benchmark: Nifty500 Multicap 50:25:25 TRIBenchmark",
            "₹10447",
            "₹16868",
            "NA",
            "NA",
            "₹19070"
          ],
          [
            "Additional Benchmark: BSE Sensex TRIAdditional Benchmark",
            "₹10699",
            "₹14346",
            "NA",
            "NA",
            "₹16487"
          ]
        ]
      },
      {
        "headers": [
          "Quantitative Data"
        ],
        "rows": [
          [
            "Expense Ratio Regular  in % (as on 31 Oct ,2025)",
            ":",
            "1.65"
          ],
          [
            "Expense Ratio Direct  in % (as on 31 Oct ,2025)",
            ":",
            "0.81"
          ]
        ]
      },
      {
        "headers": [
          "Age Range(year)",
          "plan"
        ],
        "rows": [
          [
            "Upto 40",
            "Aggresive"
          ],
          [
            "40-50",
            "Aggresive Hybrid"
          ],
          [
            "50-60",
            "Conservative Hybrid"
          ],
          [
            "Above 60",
            "Conservative"
          ]
        ]
      }
    ],
    "metadata": {
      "url": "https://www.sbimf.com/sbimf-scheme-details/sbi-multicap-fund-609",
      "title": "SBI Multicap Fund",
      "last_modified": null,
      "breadcrumbs": []
    },
    "factual_data": {
      "expense_ratio_regular": "16.29",
      "expense_ratio_direct": "17.37",
      "exit_load": "12",
      "minimum_sip": null,
      "minimum_lumpsum": null,
      "lock_in_period": "5",
      "riskometer": "500",
      "benchmark": "performance is calculated using composite of CAGR and TRI values of the benchmark\nThe performance of the schemes is benchmarked to the Total Return variant of the Index"
    },
    "scraped_date": "2025-11-17T22:21:14.354058",
    "scheme_name": "SBI Multicap Fund",
    "document_type": "scheme_details",
    "scheme_name_validated": true,
    "match_score": 1.0
  },
  {
    "url": "https://groww.in/mutual-funds/sbi-multicap-fund-direct-growth",
    "title": "SBI Multicap Fund Direct Growth - NAV, Mutual Fund Performance & Portfolio",
    "content": "Stocks\nInvest in Stocks\nInvest in stocks, ETFs, IPOs with fast orders. Track returns on your stock holdings and view real-time P&L on your positions.\nIntraday\nMonitor top intraday performers in real time\nETFs\nGet the best of Mutual Funds and flexibility of Stocks\nIPO\nTrack upcoming and ongoing IPOs\nMTFs\nBuy now, pay later\nStock Screener\nFilter based on RSI, PE ratio and more\nStock Events\nDividends, bonus, buybacks and more\nDemat Account\nBegin your stock market journey\nShare Market Today\nLive news updates from stock market\nF&O\nTrade in Futures & Options\nTrade in F&O using the terminal. View charts, indicators, track your orders , P&L and watchlists in a single space\nIndices\nTrack markets across the globe\nTerminal\nTrack charts, orders, positions, watchlists in one place\nOption chain\nAnalyse chains, view payoffs, create baskets\nPledge\nGet extra balance for trading\nCommodities\nTrade in Crude Oil, Gold, Silver and more\nAPI trading\nSet up and execute trades through our API\nMutual Funds\nInvest in Mutual Funds\nInvest in direct mutual funds at zero charges via lump sump investments or SIPs\nMutual Fund Houses\nKnow about AMCs, funds, fund managers\nNFO’s\nTrack all active NFOs in one place\nMutual Funds by Groww\nMutual funds by Groww designed for your investment goals\nMutual Funds screener\nFilter funds based on risk, fund size and more\nTrack Funds\nImport funds and track all investments in a single place\nCompare Funds\nMore\nSIP calculator\nEstimate returns on a SIP\nBrokerage calculator\nEstimate charges for your trade/investment\nMargin calculator\nEstimate balance needed to buy/sell a stock\nSWP calculator\nReturns on your systematic withdrawal plan\nPricing\nBrokerage and charges on Groww\nBlog\nSearch Groww...\nCtrl+K\nLogin/Sign up\nSBI Multicap Fund Direct Growth\nEquity\nMulti Cap\nVery High Risk\n+\n1\n0\n1\n2\n3\n4\n5\n6\n7\n8\n9\n8\n0\n1\n2\n3\n4\n5\n6\n7\n8\n9\n.\n3\n0\n1\n2\n3\n4\n5\n6\n7\n8\n9\n2\n0\n1\n2\n3\n4\n5\n6\n7\n8\n9\n%\n3Y annualised\n+0.37%\n1D\n1M\n6M\n1Y\n3Y\nAll\nNAV: 14 Nov 2025\n₹17.94\nRating\n3\nMin. SIP amount\n₹500\nFund size\n₹23,986.25Cr\nReturn calculator\nMonthly SIP\nOne-Time\n₹5,000 per month\nOver the past\n6 months\n1 year\n3 years\nTotal investment of ₹\n30,000\nWould have become ₹\n28,184\n(-\n6.05\n%)\nHoldings (63)\nName\nSector\nInstrument\nAssets\nKotak Mahindra Bank Ltd.\nFinancial\nEquity\n4.10%\nHDFC Bank Ltd.\nFinancial\nEquity\n3.95%\nK.P.R. Mill Ltd.\nTextiles\nEquity\n3.52%\nAdani Power Ltd.\nEnergy\nEquity\n3.41%\nBajaj Finserv Ltd.\nFinancial\nEquity\n3.26%\nHindalco Industries Ltd.\nMetals & Mining\nEquity\n3.19%\nICICI Bank Ltd.\nFinancial\nEquity\n3.04%\nBharti Airtel Ltd.\nCommunication\nEquity\n2.95%\nParadeep Phosphates Ltd.\nChemicals\nEquity\n2.85%\nDalmia Bharat Ltd.\nConstruction\nEquity\n2.75%\nJubilant FoodWorks Ltd.\nServices\nEquity\n2.74%\nAsian Paints Ltd.\nChemicals\nEquity\n2.73%\nDivi's Laboratories Ltd.\nHealthcare\nEquity\n2.58%\nNMDC Ltd.\nMetals & Mining\nEquity\n2.50%\nIndus Towers Ltd.\nCommunication\nEquity\n2.49%\nTorrent Power Ltd.\nEnergy\nEquity\n2.38%\nMuthoot Finance Ltd.\nFinancial\nEquity\n2.05%\nUnited Breweries Ltd.\nConsumer Staples\nEquity\n2.03%\nBlue Star Ltd.\nConsumer Discretionary\nEquity\n2.03%\nBerger Paints India Ltd.\nChemicals\nEquity\n1.97%\nKrishna Institute of Medical Sciences Ltd\nHealthcare\nEquity\n1.95%\nAxis Bank Ltd.\nFinancial\nEquity\n1.82%\nVishal Mega Mart Ltd.\nServices\nEquity\n1.63%\nKalpataru Projects International Ltd.\nCapital Goods\nEquity\n1.54%\nAptus Value Housing Finance India Ltd.\nFinancial\nEquity\n1.41%\nEIH Ltd.\nServices\nEquity\n1.40%\nInfosys Ltd.\nTechnology\nEquity\n1.38%\nV-Mart Retail Ltd.\nServices\nEquity\n1.38%\nTTK Prestige Ltd.\nConsumer Discretionary\nEquity\n1.34%\nPage Industries Ltd.\nTextiles\nEquity\n1.32%\nCarborundum Universal Ltd.\nMetals & Mining\nEquity\n1.32%\nAether Industries Ltd.\nChemicals\nEquity\n1.26%\nEternal Ltd.\nServices\nEquity\n1.22%\nV-Guard Industries Ltd.\nConsumer Discretionary\nEquity\n1.20%\nJSW Cement Ltd.\nConstruction\nEquity\n1.14%\nArchean Chemical Industries Ltd.\nChemicals\nEquity\n1.13%\nJupiter Life Line Hospitals Ltd.\nHealthcare\nEquity\n1.12%\nMrs. Bectors Food Specialities Ltd.\nConsumer Staples\nEquity\n1.12%\nTata Steel Ltd.\nMetals & Mining\nEquity\n1.11%\nThe Federal Bank Ltd.\nFinancial\nEquity\n0.99%\nSona BLW Precision Forgings Ltd.\nAutomobile\nEquity\n0.99%\nPetronet LNG Ltd.\nEnergy\nEquity\n0.88%\nState Bank of India\nFinancial\nEquity\n0.78%\nNazara Technologies Ltd.\nTechnology\nEquity\n0.78%\nCanara Bank\nFinancial\nEquity\n0.77%\nPunjab National Bank\nFinancial\nEquity\n0.75%\nElgi Equipments Ltd.\nCapital Goods\nEquity\n0.70%\nBalkrishna Industries Ltd.\nAutomobile\nEquity\n0.64%\nKalpataru Ltd.\nOthers\nEquity\n0.56%\nVIP Industries Ltd.\nConsumer Discretionary\nEquity\n0.51%\nGOI\nSovereign\nGOI Sec\n0.43%\nSai Silks (Kalamandir) Ltd.\nTextiles\nEquity\n0.42%\nElectronics Mart India Ltd.\nServices\nEquity\n0.41%\nStanley Lifestyles Ltd.\nConsumer Discretionary\nEquity\n0.31%\nRelaxo Footwears Ltd.\nConsumer Staples\nEquity\n0.29%\nHDB Financial Services Ltd.\nFinancial\nEquity\n0.29%\nBrigade Hotel Ventures Ltd.\nServices\nEquity\n0.29%\nBrainbees Solutions Ltd.\nConsumer Staples\nEquity\n0.28%\nEscorts Kubota Ltd.\nAutomobile\nEquity\n0.28%\nReserve Bank of India\nFinancial\nT-Bills\n0.21%\nDeepak Fertilisers And Petrochemicals Corporation Ltd.\nChemicals\nEquity\n0.08%\nReserve Bank of India\nFinancial\nT-Bills\n0.06%\nCraftsman Automation Ltd.\nAutomobile\nEquity\n0.05%\nSee All\nMinimum investment amounts\nMin. for 1st investment\n₹5,000\nMin. for 2nd investment onwards\n₹1,000\nMin. for SIP\n₹500\nUnderstand terms\nAnnualised returns\nAverage of the yearly returns of a mutual fund over a given period.\nAbsolute returns\nThe total return of a mutual fund over a given period.\nReturns and rankings\nCategory: Equity Multi Cap\nAnnualised returns\nAbsolute returns\n6M\n1Y\n3Y\nAll\nFund returns\nNA\n10.5%\n18.3%\n17.2%\nCategory average\nNA\n6.4%\n18.9%\nNA\nRank with in category\nNA\n7\n14\nNA\nUnderstand terms\nPeer Comparison\nEquity, Multi Cap funds\nRating\n1Y\n3Y\nFund Size(Cr)\nKotak Multicap Fund Direct Growth\n4\n10.3%\n24.8%\n21,541.46\nAxis Multicap Fund Direct Growth\n4\n9.2%\n23.5%\n9,099.31\nNippon India Multi Cap Fund Direct Growth\n5\n7.9%\n22.8%\n49,313.70\nHDFC Multi Cap Fund Direct Growth\n4\n7.9%\n22.2%\n19,732.03\nICICI Prudential Multicap Fund Direct Plan Growth\n4\n7.4%\n20.8%\n16,067.20\nUnderstand terms\nExpense ratio\nA fee payable to a mutual fund house for managing your mutual fund investments. It is the total percentage of a company’s fund assets used for administrative, management, advertising, and other expenses.\nTax\nA percentage of your capital gains payable to the government upon exiting  your mutual fund investments. Taxation is categorized as long-term capital gains (LTCG) and short-term capital gains (STCG) depending on your holding period and the type of fund.\nExit load\nA fee payable to a mutual fund house for exiting a fund (fully or partially) before the completion of a specified period from the date of investment.\nStamp duty\nA form of tax payable for the purchase or sale of an asset or security.\nPast expense ratio & exit load\nExpense ratio\nExit load\n16 Nov 2025 -\nPresent\n0.81%\n15 Nov 2025 -\n16 Nov 2025\n0.81%\n14 Nov 2025 -\n15 Nov 2025\n0.81%\n13 Nov 2025 -\n14 Nov 2025\n0.81%\n12 Nov 2025 -\n13 Nov 2025\n0.81%\n11 Nov 2025 -\n12 Nov 2025\n0.81%\n10 Nov 2025 -\n11 Nov 2025\n0.81%\n09 Nov 2025 -\n10 Nov 2025\n0.81%\n08 Nov 2025 -\n09 Nov 2025\n0.81%\n07 Nov 2025 -\n08 Nov 2025\n0.81%\n06 Nov 2025 -\n07 Nov 2025\n0.81%\n05 Nov 2025 -\n06 Nov 2025\n0.81%\n04 Nov 2025 -\n05 Nov 2025\n0.81%\n03 Nov 2025 -\n04 Nov 2025\n0.81%\n02 Nov 2025 -\n03 Nov 2025\n0.81%\n01 Nov 2025 -\n02 Nov 2025\n0.81%\n31 Oct 2025 -\n01 Nov 2025\n0.81%\n30 Oct 2025 -\n31 Oct 2025\n0.81%\n29 Oct 2025 -\n30 Oct 2025\n0.81%\n28 Oct 2025 -\n29 Oct 2025\n0.81%\n27 Oct 2025 -\n28 Oct 2025\n0.81%\n26 Oct 2025 -\n27 Oct 2025\n0.81%\n25 Oct 2025 -\n26 Oct 2025\n0.81%\n24 Oct 2025 -\n25 Oct 2025\n0.81%\n23 Oct 2025 -\n24 Oct 2025\n0.81%\n22 Oct 2025 -\n23 Oct 2025\n0.81%\n21 Oct 2025 -\n22 Oct 2025\n0.81%\n20 Oct 2025 -\n21 Oct 2025\n0.81%\n19 Oct 2025 -\n20 Oct 2025\n0.81%\n18 Oct 2025 -\n19 Oct 2025\n0.81%\n17 Oct 2025 -\n18 Oct 2025\n0.81%\n16 Oct 2025 -\n17 Oct 2025\n0.81%\n15 Oct 2025 -\n16 Oct 2025\n0.81%\n14 Oct 2025 -\n15 Oct 2025\n0.81%\n13 Oct 2025 -\n14 Oct 2025\n0.81%\n12 Oct 2025 -\n13 Oct 2025\n0.81%\n11 Oct 2025 -\n12 Oct 2025\n0.81%\n10 Oct 2025 -\n11 Oct 2025\n0.81%\n09 Oct 2025 -\n10 Oct 2025\n0.81%\n08 Oct 2025 -\n09 Oct 2025\n0.81%\n07 Oct 2025 -\n08 Oct 2025\n0.81%\n06 Oct 2025 -\n07 Oct 2025\n0.81%\n05 Oct 2025 -\n06 Oct 2025\n0.81%\n04 Oct 2025 -\n05 Oct 2025\n0.81%\n03 Oct 2025 -\n04 Oct 2025\n0.81%\n02 Oct 2025 -\n03 Oct 2025\n0.81%\n01 Oct 2025 -\n02 Oct 2025\n0.81%\n30 Sep 2025 -\n01 Oct 2025\n0.82%\n29 Sep 2025 -\n30 Sep 2025\n0.82%\n28 Sep 2025 -\n29 Sep 2025\n0.82%\n27 Sep 2025 -\n28 Sep 2025\n0.82%\n26 Sep 2025 -\n27 Sep 2025\n0.82%\n25 Sep 2025 -\n26 Sep 2025\n0.81%\n24 Sep 2025 -\n25 Sep 2025\n0.81%\n23 Sep 2025 -\n24 Sep 2025\n0.83%\n22 Sep 2025 -\n23 Sep 2025\n0.83%\n21 Sep 2025 -\n22 Sep 2025\n0.83%\n20 Sep 2025 -\n21 Sep 2025\n0.83%\n19 Sep 2025 -\n20 Sep 2025\n0.83%\n18 Sep 2025 -\n19 Sep 2025\n0.83%\n17 Sep 2025 -\n18 Sep 2025\n0.83%\n16 Sep 2025 -\n17 Sep 2025\n0.84%\n15 Sep 2025 -\n16 Sep 2025\n0.84%\n14 Sep 2025 -\n15 Sep 2025\n0.84%\n13 Sep 2025 -\n14 Sep 2025\n0.84%\n12 Sep 2025 -\n13 Sep 2025\n0.84%\n11 Sep 2025 -\n12 Sep 2025\n0.84%\n10 Sep 2025 -\n11 Sep 2025\n0.84%\n09 Sep 2025 -\n10 Sep 2025\n0.84%\n08 Sep 2025 -\n09 Sep 2025\n0.84%\n07 Sep 2025 -\n08 Sep 2025\n0.84%\n06 Sep 2025 -\n07 Sep 2025\n0.84%\n05 Sep 2025 -\n06 Sep 2025\n0.84%\n04 Sep 2025 -\n05 Sep 2025\n0.84%\n03 Sep 2025 -\n04 Sep 2025\n0.84%\n02 Sep 2025 -\n03 Sep 2025\n0.85%\n01 Sep 2025 -\n02 Sep 2025\n0.85%\n31 Aug 2025 -\n01 Sep 2025\n0.85%\n30 Aug 2025 -\n31 Aug 2025\n0.85%\n29 Aug 2025 -\n30 Aug 2025\n0.85%\n28 Aug 2025 -\n29 Aug 2025\n0.85%\n27 Aug 2025 -\n28 Aug 2025\n0.85%\n26 Aug 2025 -\n27 Aug 2025\n0.85%\n25 Aug 2025 -\n26 Aug 2025\n0.84%\n24 Aug 2025 -\n25 Aug 2025\n0.84%\n23 Aug 2025 -\n24 Aug 2025\n0.84%\n22 Aug 2025 -\n23 Aug 2025\n0.85%\n21 Aug 2025 -\n22 Aug 2025\n0.84%\n20 Aug 2025 -\n21 Aug 2025\n0.84%\n19 Aug 2025 -\n20 Aug 2025\n0.84%\n18 Aug 2025 -\n19 Aug 2025\n0.85%\n17 Aug 2025 -\n18 Aug 2025\n0.85%\n16 Aug 2025 -\n17 Aug 2025\n0.85%\n15 Aug 2025 -\n16 Aug 2025\n0.85%\n14 Aug 2025 -\n15 Aug 2025\n0.85%\n13 Aug 2025 -\n14 Aug 2025\n0.85%\n12 Aug 2025 -\n13 Aug 2025\n0.85%\n11 Aug 2025 -\n12 Aug 2025\n0.85%\n10 Aug 2025 -\n11 Aug 2025\n0.85%\n09 Aug 2025 -\n10 Aug 2025\n0.85%\n08 Aug 2025 -\n09 Aug 2025\n0.85%\n07 Aug 2025 -\n08 Aug 2025\n0.85%\n06 Aug 2025 -\n07 Aug 2025\n0.85%\n05 Aug 2025 -\n06 Aug 2025\n0.85%\n04 Aug 2025 -\n05 Aug 2025\n0.85%\n03 Aug 2025 -\n04 Aug 2025\n0.85%\n02 Aug 2025 -\n03 Aug 2025\n0.85%\n01 Aug 2025 -\n02 Aug 2025\n0.85%\n31 Jul 2025 -\n01 Aug 2025\n0.85%\n30 Jul 2025 -\n31 Jul 2025\n0.85%\n29 Jul 2025 -\n30 Jul 2025\n0.85%\n28 Jul 2025 -\n29 Jul 2025\n0.85%\n27 Jul 2025 -\n28 Jul 2025\n0.85%\n26 Jul 2025 -\n27 Jul 2025\n0.85%\n25 Jul 2025 -\n26 Jul 2025\n0.85%\n24 Jul 2025 -\n25 Jul 2025\n0.84%\n23 Jul 2025 -\n24 Jul 2025\n0.84%\n22 Jul 2025 -\n23 Jul 2025\n0.85%\n21 Jul 2025 -\n22 Jul 2025\n0.85%\n20 Jul 2025 -\n21 Jul 2025\n0.85%\n19 Jul 2025 -\n20 Jul 2025\n0.85%\n18 Jul 2025 -\n19 Jul 2025\n0.85%\n17 Jul 2025 -\n18 Jul 2025\n0.85%\n16 Jul 2025 -\n17 Jul 2025\n0.85%\n15 Jul 2025 -\n16 Jul 2025\n0.85%\n14 Jul 2025 -\n15 Jul 2025\n0.85%\n13 Jul 2025 -\n14 Jul 2025\n0.85%\n12 Jul 2025 -\n13 Jul 2025\n0.85%\n11 Jul 2025 -\n12 Jul 2025\n0.85%\n10 Jul 2025 -\n11 Jul 2025\n0.85%\n09 Jul 2025 -\n10 Jul 2025\n0.85%\n08 Jul 2025 -\n09 Jul 2025\n0.85%\n07 Jul 2025 -\n08 Jul 2025\n0.85%\n06 Jul 2025 -\n07 Jul 2025\n0.85%\n05 Jul 2025 -\n06 Jul 2025\n0.85%\n04 Jul 2025 -\n05 Jul 2025\n0.85%\n03 Jul 2025 -\n04 Jul 2025\n0.85%\n02 Jul 2025 -\n03 Jul 2025\n0.85%\n01 Jul 2025 -\n02 Jul 2025\n0.85%\n30 Jun 2025 -\n01 Jul 2025\n0.85%\n29 Jun 2025 -\n30 Jun 2025\n0.85%\n28 Jun 2025 -\n29 Jun 2025\n0.85%\n27 Jun 2025 -\n28 Jun 2025\n0.85%\n26 Jun 2025 -\n27 Jun 2025\n0.85%\n25 Jun 2025 -\n26 Jun 2025\n0.85%\n24 Jun 2025 -\n25 Jun 2025\n0.85%\n23 Jun 2025 -\n24 Jun 2025\n0.86%\n22 Jun 2025 -\n23 Jun 2025\n0.86%\n21 Jun 2025 -\n22 Jun 2025\n0.86%\n20 Jun 2025 -\n21 Jun 2025\n0.86%\n19 Jun 2025 -\n20 Jun 2025\n0.86%\n18 Jun 2025 -\n19 Jun 2025\n0.86%\n17 Jun 2025 -\n18 Jun 2025\n0.86%\n16 Jun 2025 -\n17 Jun 2025\n0.86%\n15 Jun 2025 -\n16 Jun 2025\n0.86%\n14 Jun 2025 -\n15 Jun 2025\n0.86%\n13 Jun 2025 -\n14 Jun 2025\n0.86%\n12 Jun 2025 -\n13 Jun 2025\n0.86%\n11 Jun 2025 -\n12 Jun 2025\n0.86%\n10 Jun 2025 -\n11 Jun 2025\n0.86%\n09 Jun 2025 -\n10 Jun 2025\n0.86%\n08 Jun 2025 -\n09 Jun 2025\n0.86%\n07 Jun 2025 -\n08 Jun 2025\n0.86%\n06 Jun 2025 -\n07 Jun 2025\n0.86%\n05 Jun 2025 -\n06 Jun 2025\n0.86%\n04 Jun 2025 -\n05 Jun 2025\n0.86%\n03 Jun 2025 -\n04 Jun 2025\n0.86%\n02 Jun 2025 -\n03 Jun 2025\n0.86%\n01 Jun 2025 -\n02 Jun 2025\n0.86%\n31 May 2025 -\n01 Jun 2025\n0.86%\n30 May 2025 -\n31 May 2025\n0.86%\n29 May 2025 -\n30 May 2025\n0.86%\n28 May 2025 -\n29 May 2025\n0.86%\n27 May 2025 -\n28 May 2025\n0.86%\n26 May 2025 -\n27 May 2025\n0.86%\n25 May 2025 -\n26 May 2025\n0.86%\n24 May 2025 -\n25 May 2025\n0.86%\n23 May 2025 -\n24 May 2025\n0.86%\n22 May 2025 -\n23 May 2025\n0.86%\n21 May 2025 -\n22 May 2025\n0.86%\n20 May 2025 -\n21 May 2025\n0.86%\n19 May 2025 -\n20 May 2025\n0.86%\n18 May 2025 -\n19 May 2025\n0.86%\n17 May 2025 -\n18 May 2025\n0.86%\n16 May 2025 -\n17 May 2025\n0.86%\n15 May 2025 -\n16 May 2025\n0.86%\n14 May 2025 -\n15 May 2025\n0.86%\n13 May 2025 -\n14 May 2025\n0.86%\n12 May 2025 -\n13 May 2025\n0.86%\n11 May 2025 -\n12 May 2025\n0.86%\n10 May 2025 -\n11 May 2025\n0.86%\n09 May 2025 -\n10 May 2025\n0.86%\n08 May 2025 -\n09 May 2025\n0.86%\n30 Apr 2025 -\n08 May 2025\n0.86%\n02 Apr 2025 -\n30 Apr 2025\n0.87%\n01 Apr 2025 -\n02 Apr 2025\n0.87%\n31 Mar 2025 -\n01 Apr 2025\n0.87%\n30 Mar 2025 -\n31 Mar 2025\n0.87%\n29 Mar 2025 -\n30 Mar 2025\n0.87%\n28 Mar 2025 -\n29 Mar 2025\n0.87%\n27 Mar 2025 -\n28 Mar 2025\n0.84%\n26 Mar 2025 -\n27 Mar 2025\n0.84%\n25 Mar 2025 -\n26 Mar 2025\n0.84%\n24 Mar 2025 -\n25 Mar 2025\n0.84%\n23 Mar 2025 -\n24 Mar 2025\n0.84%\n22 Mar 2025 -\n23 Mar 2025\n0.84%\n21 Mar 2025 -\n22 Mar 2025\n0.84%\n20 Mar 2025 -\n21 Mar 2025\n0.84%\n19 Mar 2025 -\n20 Mar 2025\n0.84%\n18 Mar 2025 -\n19 Mar 2025\n0.84%\n17 Mar 2025 -\n18 Mar 2025\n0.85%\n16 Mar 2025 -\n17 Mar 2025\n0.85%\n15 Mar 2025 -\n16 Mar 2025\n0.85%\n14 Mar 2025 -\n15 Mar 2025\n0.85%\n13 Mar 2025 -\n14 Mar 2025\n0.85%\n12 Mar 2025 -\n13 Mar 2025\n0.85%\n11 Mar 2025 -\n12 Mar 2025\n0.85%\n10 Mar 2025 -\n11 Mar 2025\n0.85%\n09 Mar 2025 -\n10 Mar 2025\n0.85%\n08 Mar 2025 -\n09 Mar 2025\n0.85%\n07 Mar 2025 -\n08 Mar 2025\n0.85%\n06 Mar 2025 -\n07 Mar 2025\n0.89%\n05 Mar 2025 -\n06 Mar 2025\n0.89%\n04 Mar 2025 -\n05 Mar 2025\n0.89%\n03 Mar 2025 -\n04 Mar 2025\n0.89%\n02 Mar 2025 -\n03 Mar 2025\n0.89%\n01 Mar 2025 -\n02 Mar 2025\n0.89%\n28 Feb 2025 -\n01 Mar 2025\n0.89%\n27 Feb 2025 -\n28 Feb 2025\n0.89%\n26 Feb 2025 -\n27 Feb 2025\n0.88%\n25 Feb 2025 -\n26 Feb 2025\n0.88%\n24 Feb 2025 -\n25 Feb 2025\n0.88%\n23 Feb 2025 -\n24 Feb 2025\n0.88%\n22 Feb 2025 -\n23 Feb 2025\n0.88%\n21 Feb 2025 -\n22 Feb 2025\n0.88%\n20 Feb 2025 -\n21 Feb 2025\n0.88%\n19 Feb 2025 -\n20 Feb 2025\n0.88%\n18 Feb 2025 -\n19 Feb 2025\n0.88%\n17 Feb 2025 -\n18 Feb 2025\n0.88%\n16 Feb 2025 -\n17 Feb 2025\n0.88%\n15 Feb 2025 -\n16 Feb 2025\n0.88%\n14 Feb 2025 -\n15 Feb 2025\n0.88%\n13 Feb 2025 -\n14 Feb 2025\n0.87%\n12 Feb 2025 -\n13 Feb 2025\n0.87%\n11 Feb 2025 -\n12 Feb 2025\n0.87%\n10 Feb 2025 -\n11 Feb 2025\n0.87%\n09 Feb 2025 -\n10 Feb 2025\n0.87%\n08 Feb 2025 -\n09 Feb 2025\n0.87%\n07 Feb 2025 -\n08 Feb 2025\n0.87%\n06 Feb 2025 -\n07 Feb 2025\n0.87%\n05 Feb 2025 -\n06 Feb 2025\n0.87%\n04 Feb 2025 -\n05 Feb 2025\n0.87%\n03 Feb 2025 -\n04 Feb 2025\n0.87%\n02 Feb 2025 -\n03 Feb 2025\n0.87%\n01 Feb 2025 -\n02 Feb 2025\n0.87%\n31 Jan 2025 -\n01 Feb 2025\n0.87%\n30 Jan 2025 -\n31 Jan 2025\n0.87%\n29 Jan 2025 -\n30 Jan 2025\n0.87%\n28 Jan 2025 -\n29 Jan 2025\n0.88%\n27 Jan 2025 -\n28 Jan 2025\n0.88%\n26 Jan 2025 -\n27 Jan 2025\n0.87%\n25 Jan 2025 -\n26 Jan 2025\n0.87%\n24 Jan 2025 -\n25 Jan 2025\n0.87%\n23 Jan 2025 -\n24 Jan 2025\n0.87%\n22 Jan 2025 -\n23 Jan 2025\n0.87%\n21 Jan 2025 -\n22 Jan 2025\n0.87%\n20 Jan 2025 -\n21 Jan 2025\n0.87%\n19 Jan 2025 -\n20 Jan 2025\n0.87%\n18 Jan 2025 -\n19 Jan 2025\n0.87%\n17 Jan 2025 -\n18 Jan 2025\n0.87%\n16 Jan 2025 -\n17 Jan 2025\n0.87%\n15 Jan 2025 -\n16 Jan 2025\n0.87%\n14 Jan 2025 -\n15 Jan 2025\n0.87%\n13 Jan 2025 -\n14 Jan 2025\n0.88%\n12 Jan 2025 -\n13 Jan 2025\n0.87%\n11 Jan 2025 -\n12 Jan 2025\n0.87%\n10 Jan 2025 -\n11 Jan 2025\n0.87%\n09 Jan 2025 -\n10 Jan 2025\n0.87%\n08 Jan 2025 -\n09 Jan 2025\n0.87%\n07 Jan 2025 -\n08 Jan 2025\n0.87%\n06 Jan 2025 -\n07 Jan 2025\n0.87%\n05 Jan 2025 -\n06 Jan 2025\n0.87%\n04 Jan 2025 -\n05 Jan 2025\n0.87%\n03 Jan 2025 -\n04 Jan 2025\n0.87%\n02 Jan 2025 -\n03 Jan 2025\n0.87%\n01 Jan 2025 -\n02 Jan 2025\n0.87%\n31 Dec 2024 -\n01 Jan 2025\n0.87%\n30 Dec 2024 -\n31 Dec 2024\n0.87%\n29 Dec 2024 -\n30 Dec 2024\n0.87%\n28 Dec 2024 -\n29 Dec 2024\n0.87%\n27 Dec 2024 -\n28 Dec 2024\n0.87%\n26 Dec 2024 -\n27 Dec 2024\n0.87%\n25 Dec 2024 -\n26 Dec 2024\n0.87%\n24 Dec 2024 -\n25 Dec 2024\n0.87%\n23 Dec 2024 -\n24 Dec 2024\n0.87%\n22 Dec 2024 -\n23 Dec 2024\n0.87%\n21 Dec 2024 -\n22 Dec 2024\n0.87%\n20 Dec 2024 -\n21 Dec 2024\n0.87%\n19 Dec 2024 -\n20 Dec 2024\n0.87%\n18 Dec 2024 -\n19 Dec 2024\n0.87%\n17 Dec 2024 -\n18 Dec 2024\n0.87%\n16 Dec 2024 -\n17 Dec 2024\n0.87%\n15 Dec 2024 -\n16 Dec 2024\n0.87%\n14 Dec 2024 -\n15 Dec 2024\n0.87%\n13 Dec 2024 -\n14 Dec 2024\n0.87%\n12 Dec 2024 -\n13 Dec 2024\n0.87%\n11 Dec 2024 -\n12 Dec 2024\n0.87%\n10 Dec 2024 -\n11 Dec 2024\n0.87%\n09 Dec 2024 -\n10 Dec 2024\n0.87%\n08 Dec 2024 -\n09 Dec 2024\n0.87%\n07 Dec 2024 -\n08 Dec 2024\n0.87%\n06 Dec 2024 -\n07 Dec 2024\n0.87%\n05 Dec 2024 -\n06 Dec 2024\n0.87%\n04 Dec 2024 -\n05 Dec 2024\n0.87%\n03 Dec 2024 -\n04 Dec 2024\n0.87%\n02 Dec 2024 -\n03 Dec 2024\n0.87%\n01 Dec 2024 -\n02 Dec 2024\n0.87%\n30 Nov 2024 -\n01 Dec 2024\n0.87%\n29 Nov 2024 -\n30 Nov 2024\n0.87%\n28 Nov 2024 -\n29 Nov 2024\n0.87%\n27 Nov 2024 -\n28 Nov 2024\n0.87%\n26 Nov 2024 -\n27 Nov 2024\n0.87%\n25 Nov 2024 -\n26 Nov 2024\n0.87%\n24 Nov 2024 -\n25 Nov 2024\n0.88%\n23 Nov 2024 -\n24 Nov 2024\n0.88%\n22 Nov 2024 -\n23 Nov 2024\n0.88%\n21 Nov 2024 -\n22 Nov 2024\n0.88%\n20 Nov 2024 -\n21 Nov 2024\n0.88%\n19 Nov 2024 -\n20 Nov 2024\n0.89%\n18 Nov 2024 -\n19 Nov 2024\n0.89%\n17 Nov 2024 -\n18 Nov 2024\n0.89%\n16 Nov 2024 -\n17 Nov 2024\n0.89%\n15 Nov 2024 -\n16 Nov 2024\n0.89%\n14 Nov 2024 -\n15 Nov 2024\n0.89%\n13 Nov 2024 -\n14 Nov 2024\n0.89%\n12 Nov 2024 -\n13 Nov 2024\n0.88%\n11 Nov 2024 -\n12 Nov 2024\n0.88%\n10 Nov 2024 -\n11 Nov 2024\n0.88%\n09 Nov 2024 -\n10 Nov 2024\n0.88%\n08 Nov 2024 -\n09 Nov 2024\n0.88%\n07 Nov 2024 -\n08 Nov 2024\n0.88%\n06 Nov 2024 -\n07 Nov 2024\n0.88%\n05 Nov 2024 -\n06 Nov 2024\n0.88%\n31 Oct 2024 -\n05 Nov 2024\n0.88%\n02 Oct 2024 -\n31 Oct 2024\n0.88%\n01 Oct 2024 -\n02 Oct 2024\n0.88%\n30 Sep 2024 -\n01 Oct 2024\n0.88%\n29 Sep 2024 -\n30 Sep 2024\n0.88%\n28 Sep 2024 -\n29 Sep 2024\n0.88%\n27 Sep 2024 -\n28 Sep 2024\n0.88%\n26 Sep 2024 -\n27 Sep 2024\n0.88%\n25 Sep 2024 -\n26 Sep 2024\n0.88%\n24 Sep 2024 -\n25 Sep 2024\n0.88%\n23 Sep 2024 -\n24 Sep 2024\n0.88%\n22 Sep 2024 -\n23 Sep 2024\n0.88%\n21 Sep 2024 -\n22 Sep 2024\n0.88%\n20 Sep 2024 -\n21 Sep 2024\n0.88%\n19 Sep 2024 -\n20 Sep 2024\n0.88%\n18 Sep 2024 -\n19 Sep 2024\n0.88%\n17 Sep 2024 -\n18 Sep 2024\n0.88%\n16 Sep 2024 -\n17 Sep 2024\n0.88%\n15 Sep 2024 -\n16 Sep 2024\n0.88%\n14 Sep 2024 -\n15 Sep 2024\n0.88%\n13 Sep 2024 -\n14 Sep 2024\n0.88%\n12 Sep 2024 -\n13 Sep 2024\n0.88%\n11 Sep 2024 -\n12 Sep 2024\n0.88%\n10 Sep 2024 -\n11 Sep 2024\n0.88%\n09 Sep 2024 -\n10 Sep 2024\n0.88%\n08 Sep 2024 -\n09 Sep 2024\n0.88%\n07 Sep 2024 -\n08 Sep 2024\n0.88%\n06 Sep 2024 -\n07 Sep 2024\n0.88%\n05 Sep 2024 -\n06 Sep 2024\n0.88%\n04 Sep 2024 -\n05 Sep 2024\n0.88%\n03 Sep 2024 -\n04 Sep 2024\n0.88%\n02 Sep 2024 -\n03 Sep 2024\n0.88%\n01 Sep 2024 -\n02 Sep 2024\n0.88%\n31 Aug 2024 -\n01 Sep 2024\n0.88%\n30 Aug 2024 -\n31 Aug 2024\n0.88%\n29 Aug 2024 -\n30 Aug 2024\n0.88%\n28 Aug 2024 -\n29 Aug 2024\n0.88%\n27 Aug 2024 -\n28 Aug 2024\n0.88%\n26 Aug 2024 -\n27 Aug 2024\n0.88%\n25 Aug 2024 -\n26 Aug 2024\n0.88%\n24 Aug 2024 -\n25 Aug 2024\n0.88%\n23 Aug 2024 -\n24 Aug 2024\n0.88%\n22 Aug 2024 -\n23 Aug 2024\n0.88%\n21 Aug 2024 -\n22 Aug 2024\n0.89%\n20 Aug 2024 -\n21 Aug 2024\n0.90%\n19 Aug 2024 -\n20 Aug 2024\n0.90%\n18 Aug 2024 -\n19 Aug 2024\n0.90%\n17 Aug 2024 -\n18 Aug 2024\n0.90%\n16 Aug 2024 -\n17 Aug 2024\n0.90%\n15 Aug 2024 -\n16 Aug 2024\n0.90%\n14 Aug 2024 -\n15 Aug 2024\n0.90%\n13 Aug 2024 -\n14 Aug 2024\n0.90%\n12 Aug 2024 -\n13 Aug 2024\n0.90%\n11 Aug 2024 -\n12 Aug 2024\n0.90%\n10 Aug 2024 -\n11 Aug 2024\n0.90%\n09 Aug 2024 -\n10 Aug 2024\n0.90%\n08 Aug 2024 -\n09 Aug 2024\n0.90%\n07 Aug 2024 -\n08 Aug 2024\n0.90%\n06 Aug 2024 -\n07 Aug 2024\n0.90%\n05 Aug 2024 -\n06 Aug 2024\n0.90%\n04 Aug 2024 -\n05 Aug 2024\n0.90%\n03 Aug 2024 -\n04 Aug 2024\n0.90%\n02 Aug 2024 -\n03 Aug 2024\n0.90%\n01 Aug 2024 -\n02 Aug 2024\n0.90%\n31 Jul 2024 -\n01 Aug 2024\n0.90%\n30 Jul 2024 -\n31 Jul 2024\n0.90%\n29 Jul 2024 -\n30 Jul 2024\n0.90%\n28 Jul 2024 -\n29 Jul 2024\n0.90%\n27 Jul 2024 -\n28 Jul 2024\n0.90%\n26 Jul 2024 -\n27 Jul 2024\n0.90%\n25 Jul 2024 -\n26 Jul 2024\n0.90%\n24 Jul 2024 -\n25 Jul 2024\n0.90%\n23 Jul 2024 -\n24 Jul 2024\n0.90%\n22 Jul 2024 -\n23 Jul 2024\n0.89%\n21 Jul 2024 -\n22 Jul 2024\n0.89%\n20 Jul 2024 -\n21 Jul 2024\n0.89%\n19 Jul 2024 -\n20 Jul 2024\n0.89%\n18 Jul 2024 -\n19 Jul 2024\n0.89%\n17 Jul 2024 -\n18 Jul 2024\n0.89%\n16 Jul 2024 -\n17 Jul 2024\n0.89%\n15 Jul 2024 -\n16 Jul 2024\n0.89%\n14 Jul 2024 -\n15 Jul 2024\n0.89%\n13 Jul 2024 -\n14 Jul 2024\n0.89%\n12 Jul 2024 -\n13 Jul 2024\n0.89%\n11 Jul 2024 -\n12 Jul 2024\n0.89%\n10 Jul 2024 -\n11 Jul 2024\n0.89%\n09 Jul 2024 -\n10 Jul 2024\n0.89%\n08 Jul 2024 -\n09 Jul 2024\n0.89%\n07 Jul 2024 -\n08 Jul 2024\n0.89%\n06 Jul 2024 -\n07 Jul 2024\n0.89%\n05 Jul 2024 -\n06 Jul 2024\n0.89%\n04 Jul 2024 -\n05 Jul 2024\n0.89%\n03 Jul 2024 -\n04 Jul 2024\n0.89%\n02 Jul 2024 -\n03 Jul 2024\n0.89%\n01 Jul 2024 -\n02 Jul 2024\n0.89%\n30 Jun 2024 -\n01 Jul 2024\n0.89%\n29 Jun 2024 -\n30 Jun 2024\n0.89%\n28 Jun 2024 -\n29 Jun 2024\n0.89%\n27 Jun 2024 -\n28 Jun 2024\n0.89%\n26 Jun 2024 -\n27 Jun 2024\n0.89%\n25 Jun 2024 -\n26 Jun 2024\n0.90%\n24 Jun 2024 -\n25 Jun 2024\n0.90%\n23 Jun 2024 -\n24 Jun 2024\n0.90%\n22 Jun 2024 -\n23 Jun 2024\n0.90%\n21 Jun 2024 -\n22 Jun 2024\n0.90%\n20 Jun 2024 -\n21 Jun 2024\n0.90%\n19 Jun 2024 -\n20 Jun 2024\n0.90%\n18 Jun 2024 -\n19 Jun 2024\n0.90%\n17 Jun 2024 -\n18 Jun 2024\n0.90%\n16 Jun 2024 -\n17 Jun 2024\n0.90%\n15 Jun 2024 -\n16 Jun 2024\n0.90%\n14 Jun 2024 -\n15 Jun 2024\n0.90%\n13 Jun 2024 -\n14 Jun 2024\n0.90%\n12 Jun 2024 -\n13 Jun 2024\n0.90%\n11 Jun 2024 -\n12 Jun 2024\n0.90%\n10 Jun 2024 -\n11 Jun 2024\n0.90%\n09 Jun 2024 -\n10 Jun 2024\n0.90%\n08 Jun 2024 -\n09 Jun 2024\n0.90%\n07 Jun 2024 -\n08 Jun 2024\n0.90%\n06 Jun 2024 -\n07 Jun 2024\n0.90%\n05 Jun 2024 -\n06 Jun 2024\n0.90%\n04 Jun 2024 -\n05 Jun 2024\n0.91%\n03 Jun 2024 -\n04 Jun 2024\n0.90%\n02 Jun 2024 -\n03 Jun 2024\n0.91%\n01 Jun 2024 -\n02 Jun 2024\n0.91%\n31 May 2024 -\n01 Jun 2024\n0.91%\n30 May 2024 -\n31 May 2024\n0.91%\n29 May 2024 -\n30 May 2024\n0.90%\n28 May 2024 -\n29 May 2024\n0.90%\n27 May 2024 -\n28 May 2024\n0.90%\n26 May 2024 -\n27 May 2024\n0.91%\n25 May 2024 -\n26 May 2024\n0.91%\n24 May 2024 -\n25 May 2024\n0.91%\n23 May 2024 -\n24 May 2024\n0.90%\n22 May 2024 -\n23 May 2024\n0.90%\n21 May 2024 -\n22 May 2024\n0.90%\n20 May 2024 -\n21 May 2024\n0.90%\n19 May 2024 -\n20 May 2024\n0.90%\n18 May 2024 -\n19 May 2024\n0.90%\n17 May 2024 -\n18 May 2024\n0.90%\n16 May 2024 -\n17 May 2024\n0.91%\n15 May 2024 -\n16 May 2024\n0.91%\n14 May 2024 -\n15 May 2024\n0.91%\n13 May 2024 -\n14 May 2024\n0.91%\n12 May 2024 -\n13 May 2024\n0.91%\n11 May 2024 -\n12 May 2024\n0.91%\n10 May 2024 -\n11 May 2024\n0.91%\n09 May 2024 -\n10 May 2024\n0.91%\n08 May 2024 -\n09 May 2024\n0.91%\n07 May 2024 -\n08 May 2024\n0.91%\n06 May 2024 -\n07 May 2024\n0.91%\n05 May 2024 -\n06 May 2024\n0.91%\n04 May 2024 -\n05 May 2024\n0.91%\n03 May 2024 -\n04 May 2024\n0.91%\n02 May 2024 -\n03 May 2024\n0.91%\n01 May 2024 -\n02 May 2024\n0.91%\n30 Apr 2024 -\n01 May 2024\n0.91%\n29 Apr 2024 -\n30 Apr 2024\n0.91%\n28 Apr 2024 -\n29 Apr 2024\n0.91%\n27 Apr 2024 -\n28 Apr 2024\n0.91%\n26 Apr 2024 -\n27 Apr 2024\n0.91%\n25 Apr 2024 -\n26 Apr 2024\n0.91%\n24 Apr 2024 -\n25 Apr 2024\n0.91%\n23 Apr 2024 -\n24 Apr 2024\n0.91%\n22 Apr 2024 -\n23 Apr 2024\n0.91%\n21 Apr 2024 -\n22 Apr 2024\n0.91%\n20 Apr 2024 -\n21 Apr 2024\n0.91%\n19 Apr 2024 -\n20 Apr 2024\n0.91%\n18 Apr 2024 -\n19 Apr 2024\n0.91%\n17 Apr 2024 -\n18 Apr 2024\n0.91%\n16 Apr 2024 -\n17 Apr 2024\n0.91%\n15 Apr 2024 -\n16 Apr 2024\n0.91%\n14 Apr 2024 -\n15 Apr 2024\n0.91%\n13 Apr 2024 -\n14 Apr 2024\n0.91%\n12 Apr 2024 -\n13 Apr 2024\n0.91%\n11 Apr 2024 -\n12 Apr 2024\n0.91%\n10 Apr 2024 -\n11 Apr 2024\n0.91%\n09 Apr 2024 -\n10 Apr 2024\n0.91%\n08 Apr 2024 -\n09 Apr 2024\n0.91%\n07 Apr 2024 -\n08 Apr 2024\n0.91%\n06 Apr 2024 -\n07 Apr 2024\n0.91%\n05 Apr 2024 -\n06 Apr 2024\n0.91%\n04 Apr 2024 -\n05 Apr 2024\n0.91%\n03 Apr 2024 -\n04 Apr 2024\n0.91%\n02 Apr 2024 -\n03 Apr 2024\n0.91%\n01 Apr 2024 -\n02 Apr 2024\n0.91%\n31 Mar 2024 -\n01 Apr 2024\n0.92%\n30 Mar 2024 -\n31 Mar 2024\n0.92%\n29 Mar 2024 -\n30 Mar 2024\n0.92%\n28 Mar 2024 -\n29 Mar 2024\n0.92%\n27 Mar 2024 -\n28 Mar 2024\n0.92%\n26 Mar 2024 -\n27 Mar 2024\n0.92%\n25 Mar 2024 -\n26 Mar 2024\n0.93%\n24 Mar 2024 -\n25 Mar 2024\n0.93%\n23 Mar 2024 -\n24 Mar 2024\n0.93%\n22 Mar 2024 -\n23 Mar 2024\n0.93%\n21 Mar 2024 -\n22 Mar 2024\n0.93%\n20 Mar 2024 -\n21 Mar 2024\n0.93%\n19 Mar 2024 -\n20 Mar 2024\n0.93%\n18 Mar 2024 -\n19 Mar 2024\n0.93%\n17 Mar 2024 -\n18 Mar 2024\n0.93%\n16 Mar 2024 -\n17 Mar 2024\n0.93%\n15 Mar 2024 -\n16 Mar 2024\n0.93%\n14 Mar 2024 -\n15 Mar 2024\n0.93%\n13 Mar 2024 -\n14 Mar 2024\n0.93%\n12 Mar 2024 -\n13 Mar 2024\n0.92%\n11 Mar 2024 -\n12 Mar 2024\n0.92%\n10 Mar 2024 -\n11 Mar 2024\n0.92%\n09 Mar 2024 -\n10 Mar 2024\n0.92%\n08 Mar 2024 -\n09 Mar 2024\n0.92%\n07 Mar 2024 -\n08 Mar 2024\n0.92%\n06 Mar 2024 -\n07 Mar 2024\n0.92%\n05 Mar 2024 -\n06 Mar 2024\n0.92%\n04 Mar 2024 -\n05 Mar 2024\n0.92%\n03 Mar 2024 -\n04 Mar 2024\n0.92%\n02 Mar 2024 -\n03 Mar 2024\n0.92%\n01 Mar 2024 -\n02 Mar 2024\n0.92%\n29 Feb 2024 -\n01 Mar 2024\n0.93%\n28 Feb 2024 -\n29 Feb 2024\n0.93%\n27 Feb 2024 -\n28 Feb 2024\n0.92%\n26 Feb 2024 -\n27 Feb 2024\n0.92%\n25 Feb 2024 -\n26 Feb 2024\n0.92%\n24 Feb 2024 -\n25 Feb 2024\n0.92%\n23 Feb 2024 -\n24 Feb 2024\n0.92%\n22 Feb 2024 -\n23 Feb 2024\n0.92%\n21 Feb 2024 -\n22 Feb 2024\n0.92%\n20 Feb 2024 -\n21 Feb 2024\n0.92%\n19 Feb 2024 -\n20 Feb 2024\n0.92%\n18 Feb 2024 -\n19 Feb 2024\n0.92%\n17 Feb 2024 -\n18 Feb 2024\n0.92%\n16 Feb 2024 -\n17 Feb 2024\n0.92%\n15 Feb 2024 -\n16 Feb 2024\n0.92%\n14 Feb 2024 -\n15 Feb 2024\n0.93%\n13 Feb 2024 -\n14 Feb 2024\n0.93%\n12 Feb 2024 -\n13 Feb 2024\n0.93%\n11 Feb 2024 -\n12 Feb 2024\n0.92%\n10 Feb 2024 -\n11 Feb 2024\n0.92%\n09 Feb 2024 -\n10 Feb 2024\n0.92%\n08 Feb 2024 -\n09 Feb 2024\n0.92%\n07 Feb 2024 -\n08 Feb 2024\n0.92%\n06 Feb 2024 -\n07 Feb 2024\n0.92%\n05 Feb 2024 -\n06 Feb 2024\n0.93%\n04 Feb 2024 -\n05 Feb 2024\n0.92%\n03 Feb 2024 -\n04 Feb 2024\n0.92%\n02 Feb 2024 -\n03 Feb 2024\n0.92%\n01 Feb 2024 -\n02 Feb 2024\n0.93%\n31 Jan 2024 -\n01 Feb 2024\n0.92%\n30 Jan 2024 -\n31 Jan 2024\n0.93%\n29 Jan 2024 -\n30 Jan 2024\n0.93%\n28 Jan 2024 -\n29 Jan 2024\n0.93%\n27 Jan 2024 -\n28 Jan 2024\n0.93%\n26 Jan 2024 -\n27 Jan 2024\n0.93%\n25 Jan 2024 -\n26 Jan 2024\n0.93%\n24 Jan 2024 -\n25 Jan 2024\n0.93%\n23 Jan 2024 -\n24 Jan 2024\n0.93%\n22 Jan 2024 -\n23 Jan 2024\n0.93%\n21 Jan 2024 -\n22 Jan 2024\n0.93%\n20 Jan 2024 -\n21 Jan 2024\n0.93%\n19 Jan 2024 -\n20 Jan 2024\n0.93%\n18 Jan 2024 -\n19 Jan 2024\n0.93%\n17 Jan 2024 -\n18 Jan 2024\n0.93%\n16 Jan 2024 -\n17 Jan 2024\n0.93%\n15 Jan 2024 -\n16 Jan 2024\n0.93%\n14 Jan 2024 -\n15 Jan 2024\n0.93%\n13 Jan 2024 -\n14 Jan 2024\n0.93%\n12 Jan 2024 -\n13 Jan 2024\n0.93%\n11 Jan 2024 -\n12 Jan 2024\n0.93%\n10 Jan 2024 -\n11 Jan 2024\n0.93%\n09 Jan 2024 -\n10 Jan 2024\n0.93%\n08 Jan 2024 -\n09 Jan 2024\n0.93%\n07 Jan 2024 -\n08 Jan 2024\n0.93%\n06 Jan 2024 -\n07 Jan 2024\n0.93%\n05 Jan 2024 -\n06 Jan 2024\n0.93%\n04 Jan 2024 -\n05 Jan 2024\n0.93%\n03 Jan 2024 -\n04 Jan 2024\n0.93%\n02 Jan 2024 -\n03 Jan 2024\n0.93%\n01 Jan 2024 -\n02 Jan 2024\n0.93%\n31 Dec 2023 -\n01 Jan 2024\n0.92%\n30 Dec 2023 -\n31 Dec 2023\n0.92%\n29 Dec 2023 -\n30 Dec 2023\n0.92%\n28 Dec 2023 -\n29 Dec 2023\n0.92%\n27 Dec 2023 -\n28 Dec 2023\n0.92%\n26 Dec 2023 -\n27 Dec 2023\n0.92%\n25 Dec 2023 -\n26 Dec 2023\n0.92%\n24 Dec 2023 -\n25 Dec 2023\n0.92%\n23 Dec 2023 -\n24 Dec 2023\n0.92%\n22 Dec 2023 -\n23 Dec 2023\n0.92%\n21 Dec 2023 -\n22 Dec 2023\n0.92%\n20 Dec 2023 -\n21 Dec 2023\n0.92%\n19 Dec 2023 -\n20 Dec 2023\n0.92%\n18 Dec 2023 -\n19 Dec 2023\n0.92%\n17 Dec 2023 -\n18 Dec 2023\n0.92%\n16 Dec 2023 -\n17 Dec 2023\n0.92%\n15 Dec 2023 -\n16 Dec 2023\n0.92%\n14 Dec 2023 -\n15 Dec 2023\n0.92%\n13 Dec 2023 -\n14 Dec 2023\n0.92%\n12 Dec 2023 -\n13 Dec 2023\n0.92%\n11 Dec 2023 -\n12 Dec 2023\n0.92%\n10 Dec 2023 -\n11 Dec 2023\n0.92%\n09 Dec 2023 -\n10 Dec 2023\n0.92%\n08 Dec 2023 -\n09 Dec 2023\n0.92%\n07 Dec 2023 -\n08 Dec 2023\n0.92%\n06 Dec 2023 -\n07 Dec 2023\n0.92%\n05 Dec 2023 -\n06 Dec 2023\n0.92%\n04 Dec 2023 -\n05 Dec 2023\n0.92%\n03 Dec 2023 -\n04 Dec 2023\n0.92%\n02 Dec 2023 -\n03 Dec 2023\n0.92%\n01 Dec 2023 -\n02 Dec 2023\n0.92%\n30 Nov 2023 -\n01 Dec 2023\n0.92%\n29 Nov 2023 -\n30 Nov 2023\n0.92%\n28 Nov 2023 -\n29 Nov 2023\n0.92%\n27 Nov 2023 -\n28 Nov 2023\n0.92%\n26 Nov 2023 -\n27 Nov 2023\n0.92%\n25 Nov 2023 -\n26 Nov 2023\n0.92%\n24 Nov 2023 -\n25 Nov 2023\n0.92%\n23 Nov 2023 -\n24 Nov 2023\n0.92%\n22 Nov 2023 -\n23 Nov 2023\n0.92%\n21 Nov 2023 -\n22 Nov 2023\n0.92%\n20 Nov 2023 -\n21 Nov 2023\n0.93%\n19 Nov 2023 -\n20 Nov 2023\n0.93%\n18 Nov 2023 -\n19 Nov 2023\n0.93%\n17 Nov 2023 -\n18 Nov 2023\n0.93%\n16 Nov 2023 -\n17 Nov 2023\n0.93%\n15 Nov 2023 -\n16 Nov 2023\n0.93%\n14 Nov 2023 -\n15 Nov 2023\n0.93%\n13 Nov 2023 -\n14 Nov 2023\n0.93%\n12 Nov 2023 -\n13 Nov 2023\n0.93%\n11 Nov 2023 -\n12 Nov 2023\n0.93%\n10 Nov 2023 -\n11 Nov 2023\n0.93%\n09 Nov 2023 -\n10 Nov 2023\n0.93%\n08 Nov 2023 -\n09 Nov 2023\n0.93%\n07 Nov 2023 -\n08 Nov 2023\n0.93%\n06 Nov 2023 -\n07 Nov 2023\n0.93%\n05 Nov 2023 -\n06 Nov 2023\n0.93%\n04 Nov 2023 -\n05 Nov 2023\n0.93%\n03 Nov 2023 -\n04 Nov 2023\n0.93%\n02 Nov 2023 -\n03 Nov 2023\n0.93%\n01 Nov 2023 -\n02 Nov 2023\n0.93%\n31 Oct 2023 -\n01 Nov 2023\n0.93%\n30 Oct 2023 -\n31 Oct 2023\n0.93%\n29 Oct 2023 -\n30 Oct 2023\n0.93%\n28 Oct 2023 -\n29 Oct 2023\n0.93%\n27 Oct 2023 -\n28 Oct 2023\n0.93%\n26 Oct 2023 -\n27 Oct 2023\n0.93%\n25 Oct 2023 -\n26 Oct 2023\n0.94%\n24 Oct 2023 -\n25 Oct 2023\n0.94%\n23 Oct 2023 -\n24 Oct 2023\n0.94%\n22 Oct 2023 -\n23 Oct 2023\n0.94%\n21 Oct 2023 -\n22 Oct 2023\n0.94%\n20 Oct 2023 -\n21 Oct 2023\n0.94%\n19 Oct 2023 -\n20 Oct 2023\n0.93%\n18 Oct 2023 -\n19 Oct 2023\n0.93%\n17 Oct 2023 -\n18 Oct 2023\n0.93%\n16 Oct 2023 -\n17 Oct 2023\n0.93%\n15 Oct 2023 -\n16 Oct 2023\n0.94%\n14 Oct 2023 -\n15 Oct 2023\n0.94%\n13 Oct 2023 -\n14 Oct 2023\n0.94%\n12 Oct 2023 -\n13 Oct 2023\n0.93%\n11 Oct 2023 -\n12 Oct 2023\n0.94%\n10 Oct 2023 -\n11 Oct 2023\n0.94%\n09 Oct 2023 -\n10 Oct 2023\n0.94%\n08 Oct 2023 -\n09 Oct 2023\n0.94%\n07 Oct 2023 -\n08 Oct 2023\n0.94%\n06 Oct 2023 -\n07 Oct 2023\n0.94%\n05 Oct 2023 -\n06 Oct 2023\n0.94%\n04 Oct 2023 -\n05 Oct 2023\n0.94%\n03 Oct 2023 -\n04 Oct 2023\n0.94%\n02 Oct 2023 -\n03 Oct 2023\n0.94%\n01 Oct 2023 -\n02 Oct 2023\n0.94%\n30 Sep 2023 -\n01 Oct 2023\n0.94%\n29 Sep 2023 -\n30 Sep 2023\n0.94%\n28 Sep 2023 -\n29 Sep 2023\n0.94%\n27 Sep 2023 -\n28 Sep 2023\n0.94%\n26 Sep 2023 -\n27 Sep 2023\n0.94%\n25 Sep 2023 -\n26 Sep 2023\n0.94%\n24 Sep 2023 -\n25 Sep 2023\n0.94%\n23 Sep 2023 -\n24 Sep 2023\n0.94%\n22 Sep 2023 -\n23 Sep 2023\n0.94%\n21 Sep 2023 -\n22 Sep 2023\n0.94%\n20 Sep 2023 -\n21 Sep 2023\n0.94%\n19 Sep 2023 -\n20 Sep 2023\n0.94%\n18 Sep 2023 -\n19 Sep 2023\n0.94%\n17 Sep 2023 -\n18 Sep 2023\n0.94%\n16 Sep 2023 -\n17 Sep 2023\n0.93%\n15 Sep 2023 -\n16 Sep 2023\n0.93%\n14 Sep 2023 -\n15 Sep 2023\n0.94%\n13 Sep 2023 -\n14 Sep 2023\n0.94%\n12 Sep 2023 -\n13 Sep 2023\n0.94%\n11 Sep 2023 -\n12 Sep 2023\n0.93%\n10 Sep 2023 -\n11 Sep 2023\n0.93%\n09 Sep 2023 -\n10 Sep 2023\n0.93%\n08 Sep 2023 -\n09 Sep 2023\n0.93%\n07 Sep 2023 -\n08 Sep 2023\n0.93%\n06 Sep 2023 -\n07 Sep 2023\n0.94%\n05 Sep 2023 -\n06 Sep 2023\n0.94%\n04 Sep 2023 -\n05 Sep 2023\n0.94%\n03 Sep 2023 -\n04 Sep 2023\n0.94%\n02 Sep 2023 -\n03 Sep 2023\n0.94%\n01 Sep 2023 -\n02 Sep 2023\n0.94%\n31 Aug 2023 -\n01 Sep 2023\n0.94%\n31 Jul 2023 -\n31 Aug 2023\n0.88%\n30 Jun 2023 -\n31 Jul 2023\n0.88%\n31 May 2023 -\n30 Jun 2023\n0.88%\n30 Apr 2023 -\n31 May 2023\n0.88%\n31 Mar 2023 -\n30 Apr 2023\n0.77%\n28 Feb 2023 -\n31 Mar 2023\n0.77%\n31 Jan 2023 -\n28 Feb 2023\n0.77%\n31 Dec 2022 -\n31 Jan 2023\n0.77%\n31 Dec 2022 -\n31 Dec 2022\n0.77%\n31 Dec 2022 -\n31 Dec 2022\n0.77%\n30 Nov 2022 -\n31 Dec 2022\n0.80%\n30 Nov 2022 -\n30 Nov 2022\n0.80%\n30 Nov 2022 -\n30 Nov 2022\n0.80%\n30 Nov 2022 -\n30 Nov 2022\n0.80%\n31 Oct 2022 -\n30 Nov 2022\n0.80%\n31 Oct 2022 -\n31 Oct 2022\n0.80%\n31 Oct 2022 -\n31 Oct 2022\n0.80%\n31 Oct 2022 -\n31 Oct 2022\n0.80%\n30 Sep 2022 -\n31 Oct 2022\n0.80%\n30 Sep 2022 -\n30 Sep 2022\n0.80%\n30 Sep 2022 -\n30 Sep 2022\n0.80%\n30 Sep 2022 -\n30 Sep 2022\n0.80%\n31 Aug 2022 -\n30 Sep 2022\n0.81%\n31 Aug 2022 -\n31 Aug 2022\n0.81%\n31 Aug 2022 -\n31 Aug 2022\n0.81%\n31 Jul 2022 -\n31 Aug 2022\n0.57%\n31 Jul 2022 -\n31 Jul 2022\n0.57%\n31 Jul 2022 -\n31 Jul 2022\n0.57%\n30 Jun 2022 -\n31 Jul 2022\n0.58%\n30 Jun 2022 -\n30 Jun 2022\n0.58%\n30 Jun 2022 -\n30 Jun 2022\n0.58%\n31 May 2022 -\n30 Jun 2022\n0.58%\n31 May 2022 -\n31 May 2022\n0.58%\n31 May 2022 -\n31 May 2022\n0.58%\n30 Apr 2022 -\n31 May 2022\n0.58%\n30 Apr 2022 -\n30 Apr 2022\n0.58%\n30 Apr 2022 -\n30 Apr 2022\n0.58%\nExpense ratio, exit load and tax\nExpense ratio: 0.81%\nInclusive of GST\nExit load\nExit load of 0.25% if redeemed within 30 days and 0.10% if redeemed after 30 days but on or before 90 days.\nStamp duty\n0.005% (from July 1st, 2020)\nTax implication\nIf you redeem within one year, returns are taxed at 20%. If you redeem after one year, returns exceeding Rs 1.25 lakh in a financial year are taxed at 12.5%.\nUnderstand terms\nCheck past data\nFund management\nRama Iyer Srinivasan\nFeb 2022\n- Present\nView details\nEducation\nMr. Srinivasan is M.Com and MFM.\nExperience\nPrior to joining SBI Mutual Fund he has worked with Principal AMC, Oppenheimer & Co, Indosuez WI Carr and Motilal Oswal.\nAlso manages these schemes\nSBI Equity Hybrid Fund Direct Plan Growth\nSBI MNC Direct Plan Growth\nSBI Focused Fund Direct Plan Growth\nSBI Small Cap Fund Direct Growth\nSBI Tax Advantage Fund Series III Direct Growth\nSBI Long Term Advantage Fund Series IV Direct Growth\nSBI Multicap Fund Direct Growth\nSaurabh Pant\nApr 2024\n- Present\nView details\nEducation\nMr. Pant is a B.Com (H), MBE and CFA (Level III).\nExperience\nHe has been associated with SBI Mutual Fund since 2007.\nAlso manages these schemes\nSBI Large Cap Direct Plan Growth\nSBI Large & Midcap Fund Direct Plan Growth\nSBI Multicap Fund Direct Growth\nPradeep Kesavan\nDec 2023\n- Present\nView details\nEducation\nMr. Kesavan has done B.Com, MBA (Finance) and CFA\nExperience\nPrior to joining SBI MF, he has worked with Elara Capital, Accenture Strategy, Morgan Stanley and 3i Infotech\nAlso manages these schemes\nSBI Arbitrage Opportunities Fund Direct Growth\nSBI Large Cap Direct Plan Growth\nSBI Equity Hybrid Fund Direct Plan Growth\nSBI Infrastructure Fund Direct Growth\nSBI Comma Fund Direct Growth\nSBI ESG Exclusionary Strategy Fund Direct Plan Growth\nSBI MNC Direct Plan Growth\nSBI Mid Cap Direct Plan Growth\nSBI Flexicap Fund Direct Growth\nSBI Large & Midcap Fund Direct Plan Growth\nSBI Focused Fund Direct Plan Growth\nSBI Healthcare Opportunities Fund Direct Plan Growth\nSBI Gold Direct Plan Growth\nSBI Credit Risk Fund Direct Growth\nSBI Savings Fund Direct Growth\nSBI Magnum Medium Duration Fund Direct Growth\nSBI Nifty Index Direct Plan Growth\nSBI Contra Direct Plan Growth\nSBI Multi Asset Allocation Fund Direct Growth\nSBI Consumption Opportunities Fund Direct Growth\nSBI Technology Opportunities Fund Direct Growth\nSBI Small Cap Fund Direct Growth\nSBI Banking & Financial Services Fund Direct Growth\nSBI Corporate Bond Fund Direct Growth\nSBI Equity Minimum Variance Fund Direct Growth\nSBI Floating Rate Debt Fund Direct Growth\nSBI Retirement Benefit Fund Aggressive Plan Direct Growth\nSBI Retirement Benefit Fund Aggressive Hybrid Plan Direct Growth\nSBI Retirement Benefit Fund Conservative Plan Direct Growth\nSBI Retirement Benefit Fund Conservative Hybrid Plan Direct Growth\nSBI Balanced Advantage Fund Direct Growth\nSBI Multicap Fund Direct Growth\nSBI Dividend Yield Fund Direct Growth\nSBI Energy Opportunities Fund Direct Growth\nSBI Automotive Opportunities Fund Direct Growth\nSBI Quant Fund Direct Growth\nFund house & investment objective\nSBI Mutual Fund\nRank (total assets)\n#1 in India\nTotal AUM\n₹11,84,451.93Cr\nDate of Incorporation\n29 Jun 1987\nSBI Multicap Fund Direct Growth is a Equity Mutual Fund Scheme launched by SBI Mutual Fund.     This scheme was made available to investors on 29\nSBI Multicap Fund Direct Growth is a Equity Mutual Fund Scheme launched by SBI Mutual Fund.     This scheme was made available to investors on 29 Jun 1987.     Rama Iyer Srinivasan is the Current Fund Manager of SBI Multicap Fund Direct Growth fund.     The fund currently has an Asset Under Management(AUM) of ₹11,84,452 Cr and     the Latest NAV as of 14 Nov 2025 is ₹17.94.\nThe SBI Multicap Fund Direct Growth is rated Very High risk.     Minimum SIP Investment is set to ₹500.     Minimum Lumpsum Investment is ₹5,000.     Exit load of 0.25% if redeemed within 30 days and 0.10% if redeemed after 30 days but on or before 90 days.\n...Read more\nInvestment Objective\nThe scheme seeks to provide investors with opportunities for long term growth in capital from a diversified portfolio of equity and equity related ins\nThe scheme seeks to provide investors with opportunities for long term growth in capital from a diversified portfolio of equity and equity related instruments across market capitalization.\n...Read more\nFund benchmark\nNifty 500 Multicap 50:25:25 Total Return Index\nScheme Information Document(SID)\nFund house contact details\nAddress\n9th Floor-Crescenzo, C-38 & 39-G Block, Bandra-Kurla Complex,Bandra (East) Mumbai 400051\nPhone\n022-61793000 / 1800-425-5425\nLaunch Date\n29 Jun 1987\nE-mail\nNA\nWebsite\nwww.sbimf.com\nSBI Mutual Fund\nAsset Management Company\nCustodian\nSBI SG Global Securities Services Pvt.Ltd.\nRegistrar & Transfer Agent\nCams\nAddress\n7th Floor, Tower II, Rayala Towers, 158, Anna Salai,\nEmail\nenq_h@camsonline.com\nWebsite\nwww.camsonline.com\nDisclaimer\nThis content is derived from publicly available information, internal sources, and other third-party sources believed to be reliable. We, at Groww Invest Tech Pvt. Ltd. (Formerly known as Nextbillion Technology Pvt. Ltd) (Groww), do not guarantee the accuracy of such information, or assure its completeness, or warrant that such information will not be changed.\nAll comparisons are done with the category average metrics for this category.\nPros and cons\nCategory: Equity Multi Cap\nPros\nLower expense ratio: 0.81%\n1Y annualised returns higher than category average by 4.1%\nCons\n3Y annualised returns lower than category average by 0.62%\nCompare funds\nSBI Multicap Fund Direct Growth\nVS\nAdd mutual fund to compare\nFAQs\nHow to Invest in SBI Multicap Fund Direct Growth?\nYou can easily invest in SBI Multicap Fund Direct Growth in a hassle-free manner on Groww. The\nprocess is extremely simple, quick and completely paperless. Invest in a few minutes with the following steps:\nLog on to your Groww account\nSearch for SBI Multicap Fund Direct Growth from the search box\nIn order to invest, you will have to complete all the KYC formalities which are completely online and paperless\nand take a few minutes to complete\nOnce you are done with that, you can start investing in SBI Multicap Fund Direct Growth as SIP or lumpsum as per your\ninvestment objective and risk tolerance\nWhat kind of returns does SBI Multicap Fund Direct Growth provide?\nThe SBI Multicap Fund Direct Growth has been there from 08 Mar 2022 and the average annual returns provided by this fund is 10.50% since its inception.\nHow much expense ratio is charged by SBI Multicap Fund Direct Growth?\nThe term\nExpense Ratio\nused for SBI Multicap Fund Direct Growth or any other mutual fund is the annual\ncharges one needs to pay to the Mutual Fund company for managing your investments in that fund.\nThe Expense Ratio of SBI Multicap Fund Direct Growth is 0.81% as of 17 Nov 2025...\nWhat is the AUM of SBI Multicap Fund Direct Growth?\nThe AUM, short for\nAssets Under Management\nof SBI Multicap Fund Direct Growth is ₹23,986.25Cr as of 17 Nov 2025.\nHow to Redeem SBI Multicap Fund Direct Growth?\nIf you want to sell your SBI Multicap Fund Direct Growth holdings, go to your holding on the app or\nweb and simply click on it. You will get two options - redeem & invest more; click on redeem and enter your\ndesired amount or if you wish to redeem the entire holding amount then select the 'redeem all' checkbox.\nCan I invest in SIP and Lump Sum of SBI Multicap Fund Direct Growth?\nYou can select either\nSIP\nor\nLumpsum\ninvestment of SBI Multicap Fund Direct Growth based on\nyour investment objective and risk tolerance.\nWhat is the NAV of SBI Multicap Fund Direct Growth?\nThe NAV of SBI Multicap Fund Direct Growth is ₹17.94 as of 14 Nov 2025.\nWhat is the PE and PB ratio of SBI Multicap Fund Direct Growth?\nThe\nPE ratio\nratio of SBI Multicap Fund Direct Growth is determined by dividing the market price by\nits earnings per share and the\nPB ratio\nof the same is evaluated by dividing the stock price per share by its book value\nper share (BVPS).\nLooking to invest in mutual funds?\nExplore diversified funds designed for every investor\nInvest Now\nHome\n>\nMutual Funds\n>\nSBI Mutual Fund\n>\nSBI Multicap Fund Direct Growth\nVaishnavi Tech Park, South Tower, 3rd Floor\nSarjapur Main Road, Bellandur, Bengaluru – 560103\nKarnataka\nContact Us\nDownload the App\nGROWW\nAbout Us\nPricing\nBlog\nMedia & Press\nCareers\nHelp & Support\nTrust & Safety\nInvestor Relations\nPRODUCTS\nStocks\nF&O\nMTF\nETF\nIPO\nMutual Funds\nCommodities\nGroww Terminal\n915 Terminal\nStocks Screener\nAlgo Trading\nGroww Digest\nDemat Account\nGroww AMC\n© 2016-2025 Groww. All rights reserved.\nVersion: 6.8.8\nShare Market\nIndices\nF&O\nMutual Funds\nETFs\nFunds By Groww\nCalculators\nIPO\nMiscellaneous\nTop Gainers Stocks\n52 Weeks High Stocks\nTata Motors\nNHPC\nITC\nWipro\nBSE\nNTPC\nTop Losers Stocks\n52 Weeks Low Stocks\nIREDA\nState Bank of India\nAdani Power\nCDSL\nCochin Shipyard\nSJVN\nMost Traded Stocks\nStocks Market Calender\nTata Steel\nTata Power\nBharat Heavy Electricals\nIndian Oil Corporation\nHUDCO\nSAIL\nStocks Feed\nSuzlon Energy\nZomato (Eternal)\nYes Bank\nInfosys\nNBCC\nIRCTC\nShare Market Live Update\nFII DII Activity\nIRFC\nBharat Electronics\nHDFC Bank\nVedanta\nReliance Power\nJaiprakash Power Ventures\nNIFTY 50\nNIFTY Midcap 100\nNIFTY 100\nUS Tech 100\nNIFTY Realty\nNikkei index\nSENSEX\nNIFTY Smallcap 100\nNIFTY Auto\nDow Jones Futures\nNIFTY PSU Bank\nNIFTY FMCG\nNIFTY BANK\nNIFTY MIDCAP 150\nKOSPI Index\nDow Jones Index\nGift Nifty\nBSE BANKEX\nIndia VIX\nNIFTY Pharma\nHANG SENG Index\nBSE 100\nFTSE 100 Index\nS&P 500\nNIFTY NEXT 50\nNIFTY Metal\nDAX Index\nNIFTY Fin Service\nCAC Index\nNifty Pvt Bank\nNIFTY Bank Options\nSBI Options\nBajaj Finance Options\nAxis Bank Options\nHindustan Unilever Options\nNIFTY Bank Futures\nFinnifty Futures\nITC Futures\nICICI Bank Futures\nBiocon Futures\nIndusind Bank Futures\nNIFTY 50 Options\nHDFC Bank Options\nWipro  Options\nDLF Options\nREC  Options\nYes Bank Futures\nZomato Futures\nAshok Leyland Futures\nHDFC Bank Futures\nUPL Futures\nAdani Enterprises Futures\nBse Sensex Options\nTata Steel Options\nNTPC Options\nBajaj Auto Options\nIndusind Bank Options\nTata Motors Futures\nInfosys Futures\nAsian Paints Futures\nLupin Futures\nCipla Futures\nIDFC First Bank Futures\nFinnifty Options\nInfosys Options\nAsian Paints Options\nCoal India Options\nAshok Leyland Options\nTata Steel Futures\nBSE Sensex Futures\nWipro Futures\nDLF Futures\nBajaj Finance Futures\nPiramal Enterprises Futures\nTata Motors Options\nITC Options\nICICI Bank Options\nAdani Enterprises Options\nNIFTY 50 Futures\nCoal India Futures\nAxis Bank Futures\nVedanta Futures\nReliance Industries Futures\nHindustan Copper Futures\nMF Screener\nDebt Mutual Funds\nBest Multicap Mutual funds\nBest Contra Mutual funds\nBest Conservative Mutual funds\nSBI Contra Fund\nNippon India Nifty 500 Momentum 50 Index Fund\nHDFC Balanced Advantage Fund\nQuant Mid Cap Fund\nBank of India Small Cap Fund\nQuant Multi Asset Fund\nNippon India\nTATA\nBandhan\nEdelweiss\nHSBC\nUnion\nQuantum\nShriram\nCompare Mutual Funds\nBest Debt Mutual funds\nBest Large Cap Mutual funds\nBest Value Mutual funds\nParag Parikh Flexi Cap Fund\nHDFC Mid Cap Opportunities Fund\nMotilal Oswal Nifty India Defence Index Fund\nICICI Prudential India Opportunities Fund\nKotak Small Cap Fund\nCanara Robeco Bluechip Equity Fund\nGrowwMF\nMotilal Oswal\nAditya Birla\nAxis\nBank of India\nBajaj Finserv\nHelios\nITI\nTrust\nMF Knowledge Centre\nBest Equity Mutual funds\nBest Small Cap Mutual funds\nBest Arbitrage Mutual funds\nMotilal Oswal Midcap Fund\nSBI Small Cap Fund\nHDFC Small Cap Fund\nKotak Multicap Fund\nICICI Prudential Infrastructure Fund\nBandhan Nifty Alpha 50 Index Fund\nSBI\nQuant\nMirae Asset\nDSP\nBaroda BNP Paribas\nMahindra Manulife\nSundaram\nSamco\nTaurus\nMutual Fund Houses\nBest Hybrid Mutual funds\nBest ELSS Mutual funds\nBest Dividend Yield Mutual funds\nNippon India Small Cap Fund\nHDFC Flexi Cap Fund\nTata Small Cap Fund\nTata Ethical Fund\nMirae Asset ELSS Tax Saver Fund\nQuant Infrastructure Fund\nHDFC\nPPFAS\nUTI\nKotak Mahindra\nZerodha\nInvesco\nNavi\nPGIM\nMutual Funds Categories\nBest MidCap Mutual funds\nBest Sector Mutual funds\nBest Aggressive Mutual funds\nQuant Small Cap Fund\nSBI Magnum Children's Benefit Fund\nUTI Nifty 50 Index Fund\nJM Flexicap Fund\nHSBC Small Cap Fund\nFranklin India Multi Cap Fund\nICICI Prudential\nLIC\nCanara Robeco\nWhiteoak\nFranklin Templeton\nNJ\nJM\n360 One\nInternational\nSilver\nMidcap\nLiquid\nDebt\nIndex\nBank Nifty\nNifty IT\nEquity\nNifty 50\nNifty Metal\nNifty Auto\nCommodity\nNifty Next 50\nHealthcare\nGroww\nGold\nSensex\nDefence\nGroww Arbitrage Fund\nGroww ELSS Tax Saver Fund\nGroww Banking & Financial Services Fund\nGroww Gold ETF FOF\nGroww Gold ETF\nGroww Short Duration Fund\nGroww Aggressive Hybrid Fund\nGroww Nifty Smallcap 250 Index Fund\nGroww Multicap Fund\nGroww Nifty India Defence ETF\nGroww Liquid Fund\nGroww Dynamic Bond Fund\nGroww Nifty Non Cyclical Consumer Index Fund\nGroww Nifty India Railways PSU Index Fund\nGroww Nifty India Railways ETF\nGroww Large Cap Fund\nGroww Overnight Fund\nGroww Nifty EV & New Age Automotive ETF FoF\nGroww Nifty 200 ETF FoF\nGroww Value Fund\nGroww Nifty Total Market Index Fund\nGroww Nifty India Defence ETF FoF\nGroww Silver ETF\nSIP Calculator\nBrokerage Calculator\nRD Calculator\nHRA Calculator\nHome Loan EMI Calculator\nLumpsum Calculator\nMargin Calculator\nFD Calculator\nSalary Calculator\nSWP Calculator\nStock Average Calculator\nEPF Calculator\nTDS Calculator\nMF Calculator\nSSY Calculator\nIncome Tax Calculator\nEMI Calculator\nStep-Up SIP Calculator\nPPF Calculator\nGST Calculator\nCar Loan EMI Calculator\nWhat is IPO?\nWhat is Grey Market Premium?\nOpen IPOs\nMainboard IPOs\nUpcoming IPOs\nSME IPOs\nClosed IPOs\nHow to Apply for an IPO\nNFO\nPricing\nTrust & Safety\nRecurring Deposit\nIntraday\nBlog\nInvestor Relations\nGroww Digest\nCorporate Bonds\nMedia & Press\nGold Rates\nSitemap\nHUF Demat Account\nCareers\nGlossary\nAbout Us\nHelp & Support\nFixed Deposit\nShow More\nOthers:\nNSE\nBSE\nMCX\nTerms and Conditions\nPolicies and Procedures\nRegulatory & Other Info\nPrivacy Policy\nDisclosure\nSMART ODR\nDownload Forms\nInformation Security Practices\nInvestor Charter and Grievance\nBug Bounty\nMutual Funds:\nA\nB\nC\nD\nE\nF\nG\nH\nI\nJ\nK\nL\nM\nN\nO\nP\nQ\nR\nS\nT\nU\nV\nW\nX\nY\nZ\nOthers",
    "tables": [
      {
        "headers": [
          "Name",
          "Sector",
          "Instrument",
          "Assets"
        ],
        "rows": [
          [
            "Kotak Mahindra Bank Ltd.",
            "Financial",
            "Equity",
            "4.10%"
          ],
          [
            "HDFC Bank Ltd.",
            "Financial",
            "Equity",
            "3.95%"
          ],
          [
            "K.P.R. Mill Ltd.",
            "Textiles",
            "Equity",
            "3.52%"
          ],
          [
            "Adani Power Ltd.",
            "Energy",
            "Equity",
            "3.41%"
          ],
          [
            "Bajaj Finserv Ltd.",
            "Financial",
            "Equity",
            "3.26%"
          ],
          [
            "Hindalco Industries Ltd.",
            "Metals & Mining",
            "Equity",
            "3.19%"
          ],
          [
            "ICICI Bank Ltd.",
            "Financial",
            "Equity",
            "3.04%"
          ],
          [
            "Bharti Airtel Ltd.",
            "Communication",
            "Equity",
            "2.95%"
          ],
          [
            "Paradeep Phosphates Ltd.",
            "Chemicals",
            "Equity",
            "2.85%"
          ],
          [
            "Dalmia Bharat Ltd.",
            "Construction",
            "Equity",
            "2.75%"
          ],
          [
            "Jubilant FoodWorks Ltd.",
            "Services",
            "Equity",
            "2.74%"
          ],
          [
            "Asian Paints Ltd.",
            "Chemicals",
            "Equity",
            "2.73%"
          ],
          [
            "Divi's Laboratories Ltd.",
            "Healthcare",
            "Equity",
            "2.58%"
          ],
          [
            "NMDC Ltd.",
            "Metals & Mining",
            "Equity",
            "2.50%"
          ],
          [
            "Indus Towers Ltd.",
            "Communication",
            "Equity",
            "2.49%"
          ],
          [
            "Torrent Power Ltd.",
            "Energy",
            "Equity",
            "2.38%"
          ],
          [
            "Muthoot Finance Ltd.",
            "Financial",
            "Equity",
            "2.05%"
          ],
          [
            "United Breweries Ltd.",
            "Consumer Staples",
            "Equity",
            "2.03%"
          ],
          [
            "Blue Star Ltd.",
            "Consumer Discretionary",
            "Equity",
            "2.03%"
          ],
          [
            "Berger Paints India Ltd.",
            "Chemicals",
            "Equity",
            "1.97%"
          ],
          [
            "Krishna Institute of Medical Sciences Ltd",
            "Healthcare",
            "Equity",
            "1.95%"
          ],
          [
            "Axis Bank Ltd.",
            "Financial",
            "Equity",
            "1.82%"
          ],
          [
            "Vishal Mega Mart Ltd.",
            "Services",
            "Equity",
            "1.63%"
          ],
          [
            "Kalpataru Projects International Ltd.",
            "Capital Goods",
            "Equity",
            "1.54%"
          ],
          [
            "Aptus Value Housing Finance India Ltd.",
            "Financial",
            "Equity",
            "1.41%"
          ],
          [
            "EIH Ltd.",
            "Services",
            "Equity",
            "1.40%"
          ],
          [
            "Infosys Ltd.",
            "Technology",
            "Equity",
            "1.38%"
          ],
          [
            "V-Mart Retail Ltd.",
            "Services",
            "Equity",
            "1.38%"
          ],
          [
            "TTK Prestige Ltd.",
            "Consumer Discretionary",
            "Equity",
            "1.34%"
          ],
          [
            "Page Industries Ltd.",
            "Textiles",
            "Equity",
            "1.32%"
          ],
          [
            "Carborundum Universal Ltd.",
            "Metals & Mining",
            "Equity",
            "1.32%"
          ],
          [
            "Aether Industries Ltd.",
            "Chemicals",
            "Equity",
            "1.26%"
          ],
          [
            "Eternal Ltd.",
            "Services",
            "Equity",
            "1.22%"
          ],
          [
            "V-Guard Industries Ltd.",
            "Consumer Discretionary",
            "Equity",
            "1.20%"
          ],
          [
            "JSW Cement Ltd.",
            "Construction",
            "Equity",
            "1.14%"
          ],
          [
            "Archean Chemical Industries Ltd.",
            "Chemicals",
            "Equity",
            "1.13%"
          ],
          [
            "Jupiter Life Line Hospitals Ltd.",
            "Healthcare",
            "Equity",
            "1.12%"
          ],
          [
            "Mrs. Bectors Food Specialities Ltd.",
            "Consumer Staples",
            "Equity",
            "1.12%"
          ],
          [
            "Tata Steel Ltd.",
            "Metals & Mining",
            "Equity",
            "1.11%"
          ],
          [
            "The Federal Bank Ltd.",
            "Financial",
            "Equity",
            "0.99%"
          ],
          [
            "Sona BLW Precision Forgings Ltd.",
            "Automobile",
            "Equity",
            "0.99%"
          ],
          [
            "Petronet LNG Ltd.",
            "Energy",
            "Equity",
            "0.88%"
          ],
          [
            "State Bank of India",
            "Financial",
            "Equity",
            "0.78%"
          ],
          [
            "Nazara Technologies Ltd.",
            "Technology",
            "Equity",
            "0.78%"
          ],
          [
            "Canara Bank",
            "Financial",
            "Equity",
            "0.77%"
          ],
          [
            "Punjab National Bank",
            "Financial",
            "Equity",
            "0.75%"
          ],
          [
            "Elgi Equipments Ltd.",
            "Capital Goods",
            "Equity",
            "0.70%"
          ],
          [
            "Balkrishna Industries Ltd.",
            "Automobile",
            "Equity",
            "0.64%"
          ],
          [
            "Kalpataru Ltd.",
            "Others",
            "Equity",
            "0.56%"
          ],
          [
            "VIP Industries Ltd.",
            "Consumer Discretionary",
            "Equity",
            "0.51%"
          ],
          [
            "GOI",
            "Sovereign",
            "GOI Sec",
            "0.43%"
          ],
          [
            "Sai Silks (Kalamandir) Ltd.",
            "Textiles",
            "Equity",
            "0.42%"
          ],
          [
            "Electronics Mart India Ltd.",
            "Services",
            "Equity",
            "0.41%"
          ],
          [
            "Stanley Lifestyles Ltd.",
            "Consumer Discretionary",
            "Equity",
            "0.31%"
          ],
          [
            "Relaxo Footwears Ltd.",
            "Consumer Staples",
            "Equity",
            "0.29%"
          ],
          [
            "HDB Financial Services Ltd.",
            "Financial",
            "Equity",
            "0.29%"
          ],
          [
            "Brigade Hotel Ventures Ltd.",
            "Services",
            "Equity",
            "0.29%"
          ],
          [
            "Brainbees Solutions Ltd.",
            "Consumer Staples",
            "Equity",
            "0.28%"
          ],
          [
            "Escorts Kubota Ltd.",
            "Automobile",
            "Equity",
            "0.28%"
          ],
          [
            "Reserve Bank of India",
            "Financial",
            "T-Bills",
            "0.21%"
          ],
          [
            "Deepak Fertilisers And Petrochemicals Corporation Ltd.",
            "Chemicals",
            "Equity",
            "0.08%"
          ],
          [
            "Reserve Bank of India",
            "Financial",
            "T-Bills",
            "0.06%"
          ],
          [
            "Craftsman Automation Ltd.",
            "Automobile",
            "Equity",
            "0.05%"
          ]
        ]
      },
      {
        "headers": [
          "Min. for 1st investment",
          "₹5,000"
        ],
        "rows": [
          [
            "Min. for 2nd investment onwards",
            "₹1,000"
          ]
        ]
      },
      {
        "headers": [
          "Min. for SIP",
          "₹500"
        ],
        "rows": []
      },
      {
        "headers": [
          "",
          "6M",
          "1Y",
          "3Y",
          "All"
        ],
        "rows": [
          [
            "Fund returns",
            "NA",
            "10.5%",
            "18.3%",
            "17.2%"
          ],
          [
            "Category average",
            "NA",
            "6.4%",
            "18.9%",
            "NA"
          ],
          [
            "Rank with in category",
            "NA",
            "7",
            "14",
            "NA"
          ]
        ]
      },
      {
        "headers": [
          "Equity, Multi Cap funds",
          "Rating",
          "1Y",
          "3Y",
          "Fund Size(Cr)"
        ],
        "rows": [
          [
            "Kotak Multicap Fund Direct Growth",
            "4",
            "10.3%",
            "24.8%",
            "21,541.46"
          ],
          [
            "Axis Multicap Fund Direct Growth",
            "4",
            "9.2%",
            "23.5%",
            "9,099.31"
          ],
          [
            "Nippon India Multi Cap Fund Direct Growth",
            "5",
            "7.9%",
            "22.8%",
            "49,313.70"
          ],
          [
            "HDFC Multi Cap Fund Direct Growth",
            "4",
            "7.9%",
            "22.2%",
            "19,732.03"
          ],
          [
            "ICICI Prudential Multicap Fund Direct Plan Growth",
            "4",
            "7.4%",
            "20.8%",
            "16,067.20"
          ]
        ]
      },
      {
        "headers": [
          "Rank (total assets)",
          "#1 in India"
        ],
        "rows": [
          [
            "Total AUM",
            "₹11,84,451.93Cr"
          ]
        ]
      },
      {
        "headers": [
          "Date of Incorporation",
          "29 Jun 1987"
        ],
        "rows": []
      },
      {
        "headers": [
          "Fund benchmark",
          "Nifty 500 Multicap 50:25:25 Total Return Index"
        ],
        "rows": []
      }
    ],
    "metadata": {
      "url": "https://groww.in/mutual-funds/sbi-multicap-fund-direct-growth",
      "title": "SBI Multicap Fund Direct Growth - NAV, Mutual Fund Performance & Portfolio",
      "last_modified": null,
      "breadcrumbs": []
    },
    "factual_data": {
      "expense_ratio_regular": "0.25",
      "expense_ratio_direct": "0.81",
      "exit_load": "0.81",
      "minimum_sip": "500",
      "minimum_lumpsum": "1",
      "lock_in_period": null,
      "riskometer": null,
      "benchmark": null
    },
    "scraped_date": "2025-11-17T22:21:25.460212",
    "scheme_name": "SBI Multicap Fund",
    "document_type": "groww_listing",
    "scheme_name_validated": true,
    "match_score": 1.0
  },
  {
    "url": "https://www.sbimf.com/sbimf-scheme-details/sbi-nifty-index-fund-13",
    "title": "SBI Nifty Index Fund",
    "content": "SBI Nifty Index Fund\nScheme Type :\nAn open-ended Scheme tracking Nifty 50 Index\nPassive Solutions\nOpen Ended\nAn open-ended Scheme tracking Nifty 50 Index\nVERY HIGH Risk\nReturns                                                     for Regular-Growth\n14.03%\n14.03%\n7.06%\n13.3%\n17.88%\nSince Inception\n1 Year\n3 Year\n5 Year\nSince Inception\nSince Inception\n1 Year\n3 Year\n5 Year\nReturns for Direct growth\n12.79%\n12.79%\n7.3%\n13.62%\n18.24%\nSince Inception\n1 Year\n3 Year\n5 Year\nSince Inception\nSince Inception\n1 Year\n3 Year\n5 Year\nAUM as on 31 Oct 2025\n₹11420.52Cr\nDate of Allotment\n17 Jan, 2002\nExit Load\n0%\nview details\nFor exit within 15 days from the date of allotment - 0.20% For exit on or after 15 days from the date of allotment – Nil\nBenchmark :\nScheme Benchmark: Nifty 50 TRI\nAdditional Benchmark: BSE Sensex TRI\nSuitable for :\nLong-Term Capital Appreciation\nCompare Fund\nInvest\nEnter SIP Amount\nEnter SIP Amount\nMin. Amount Rs.\n500\nEnter Lumpsum Amount\nEnter Lumpsum Amount\nMin. Lumpsum amount Rs.\n5,000\n(For Additional Investment Rs. 1,000)\nAdd to Cart\nProceed to Invest\n313 people\nare already invested\nHistorical NAV\nSBI NIfty Index Fund - Regular Plan - Growth\nSBI NIfty Index Fund - Regular Plan - Growth\nSBI Nifty Index Fund - Regular Plan - IDCW\nSBI NIfty Index Fund - Direct Plan - Growth\nSBI Nifty Index Fund - Direct Plan - IDCW\n1 Year\n1 Year\n3 Year\n5 Year\nNAV as on\nNov 17, 2025\nNAV stands for Net Asset Value.\n₹\n230.2158\n(\n+0.40% one day change\n)\nPast Performance may or may not be sustained in future\nInvestment Criteria\nMin Lumpsum\n₹ 5,000\n& in multiples of 1\nMin Add Lumpsum\n₹ 1,000\n& in multiples of 1\nMin SIP Amount\n₹ 500\nReturns Calculator\nMonthly SIP\nLumpsum\nMonthly SIP\nMonthly SIP\nLumpsum\nEnter Investment Amount\n5 %\n6 %\n7 %\n8 %\n9 %\n10 %\n11 %\n12 %\n13 %\n14 %\n15 %\n16 %\n17 %\n18 %\n19 %\n20 %\n21 %\n22 %\n5 %\n5 %\n6 %\n7 %\n8 %\n9 %\n10 %\n11 %\n12 %\n13 %\n14 %\n15 %\n16 %\n17 %\n18 %\n19 %\n20 %\n21 %\n22 %\nDuration\n1Y\nNet Return\n₹6,165.009\nFund Overview\nPerformance\nDocuments\nFund Data\nIndex Constituent\nFund Overview\nInvestment Objective\nThe scheme will invest in stocks comprising the Nifty 50 index in the same proportion as their weightage in the index with the objective of achieving returns equivalent to the Total Returns Index of Nifty 50 index by minimizing the performance difference between the benchmark index and the scheme. The Total Returns Index is an index that reflects the returns on the index from index gain/loss plus dividend payments by the constituent stocks.\nMr. Raviprakash Sharma\nRaviprakash Sharma has over 24 years of experience in Indian capital markets spanning across Equity and Fixed Income segments. Raviprakash joined SBI Funds Management Limited (SBIFM) in 2011 and currently is Head &ndash; Equity Dealing and Fund Manager. Prior to SBIFM, Raviprakash has been associated with HDFC Asset Management in the portfolio management services division. In his earlier assignments he has also worked with Citigroup Wealth Advisors India Pvt. Ltd. (as a Financial Advisor), Kotak Securities Ltd. (Non-Discretionary PMS) as well as with Birla Sun Life Securities Ltd. (Fixed Income Segment). Raviprakash is a Commerce graduate from Mumbai University and a Chartered Accountant from ICAI. He is also a Charterholder of the CFA Institute, USA.\n...\nSee More\nManaging this fund since\nFeb 2011\nMore Funds\nmanaged by\nMr. Raviprakash Sharma\nProduct Label\nThis product is suitable for investors who are seeking*\nLong term capital appreciation\nPassive Investment in stocks comprising the Nifty 50 Index in the same proportion as in the index to achieve returns equivalent to the Total returns Index of Nifty 50 Index\n*Investors should consult their financial advisors if in doubt whether the product is suitable for them.\nRiskometer\nSBI Nifty Index Fund\nLow\nLow to Moderate\nModerate\nModerately High\nHigh\nVery High\nRISKOMETER\nThe risk of the scheme is\nVery High\nBenchmark Riskometer\nNifty 50 TRI\nLow\nLow to Moderate\nModerate\nModerately High\nHigh\nVery High\nRISKOMETER\nThe risk of the benchmark is\nVery High\nPerformance\nRegular Growth\nDirect Growth\nCompounded Annualized Growth Rate Performance\n1Y\n3Y\n5Y\n10Y\nSince Inception\nSBI Nifty Index Fund\n7.06%\n13.3%\n17.88%\n12.79%\n14.03%\nScheme Benchmark: Nifty 50 TRI\nBenchmark\n7.59%\n13.9%\n18.56%\n13.67%\n15.69%\nAdditional Benchmark: BSE Sensex TRI\nAdditional Benchmark\n6.99%\n12.77%\n17.59%\n13.53%\n16.11%\nCurrent Value of Standard Investment of ₹10,000\n1Y\n3Y\n5Y\n10Y\nSince Inception\nSBI Nifty Index Fund\n₹10706\n₹14548\n₹22779\n₹33360\n₹227588\nScheme Benchmark: Nifty 50 TRI\nBenchmark\n₹10759\n₹14781\n₹23449\n₹36060\n₹321215\nAdditional Benchmark: BSE Sensex TRI\nAdditional Benchmark\n₹10699\n₹14346\n₹22502\n₹35630\n₹349954\nNotes:\nDifferent plans shall have different expense structure. In case of return calculated the IDCW option, it is assumed that dividend declared under the schemes have been reinvested at the prevailing NAV\nPast performance may or may not be sustained in future and same may not necessarily provide the basis for comparison with other investment\nLoad is not considered for computation of returns\nPeriod for which scheme’s performance has been provided is computed basis last day of the month-end preceding the date of advertisement. In case, the start/end date of the concerned period is a non-business day, the NAV of the previous date is considered for computation of returns\nThe data of the last working day has been considered for the calculation of performance\nWherever TRI data since inception for benchmarks is not available, benchmark performance is calculated using composite of CAGR and TRI values of the benchmark\nThe performance of the schemes is benchmarked to the Total Return variant of the Index\nTo view other open ended funds managed by the fund manager go to the Fund Manager section\nCompounded Annualized Growth Rate Performance\n1Y\n3Y\n5Y\n10Y\nSince Inception\nSBI Nifty Index Fund\n7.3%\n13.62%\n18.24%\n13.21%\n12.79%\nScheme Benchmark: Nifty 50 TRI\nBenchmark\n7.59%\n13.9%\n18.56%\n13.67%\n13.46%\nAdditional Benchmark: BSE Sensex TRI\nAdditional Benchmark\n6.99%\n12.77%\n17.59%\n13.53%\n13.48%\nCurrent Value of Standard Investment of ₹10,000\n1Y\n3Y\n5Y\n10Y\nSince Inception\nSBI Nifty Index Fund\n₹10730\n₹14671\n₹23129\n₹34641\n₹46878\nScheme Benchmark: Nifty 50 TRI\nBenchmark\n₹10759\n₹14781\n₹23449\n₹36060\n₹50584\nAdditional Benchmark: BSE Sensex TRI\nAdditional Benchmark\n₹10699\n₹14346\n₹22502\n₹35630\n₹50714\nNotes:\nDifferent plans shall have different expense structure. In case of return calculated the IDCW option, it is assumed that dividend declared under the schemes have been reinvested at the prevailing NAV\nPast performance may or may not be sustained in future and same may not necessarily provide the basis for comparison with other investment\nLoad is not considered for computation of returns\nPeriod for which scheme’s performance has been provided is computed basis last day of the month-end preceding the date of advertisement. In case, the start/end date of the concerned period is a non-business day, the NAV of the previous date is considered for computation of returns\nThe data of the last working day has been considered for the calculation of performance\nWherever TRI data since inception for benchmarks is not available, benchmark performance is calculated using composite of DCAGR and TRI values of the benchmark\nThe performance of the schemes is benchmarked to the Total Return variant of the Index\nTo view other open ended funds managed by the fund manager go to the Fund Manager section\nDocuments\nFund Data\nQuantitative Data\nExpense Ratio Regular  in % (as on 31 Oct ,2025)\n:\n0.38\nExpense Ratio Direct  in % (as on 31 Oct ,2025)\n:\n0.19\nTracking Error Direct (as on 14 Nov ,2025)\n:\n0.015 %\nTracking Error Regular (as on 14 Nov ,2025)\n:\n0.0198 %\nSharpe Ratio\n:\n0.64\nStandard Deviation\n:\n11.69%\nBeta\n:\n1\n*Tracking Error is computed using Total Returns Index for 1 Year Period ending  14 Nov ,2025 based on day-end NAV respectively.\n**All expense ratios are inclusive of GST on Management Fees\nTracking Difference  (As on 31-Oct-2025)  Direct\nPeriod\nTracking difference\n1 Yr.\n-0.29\n3 Yr.\n-0.2822\n5 Yr.\n-0.3252\n10 Yr.\n-0.455\nInception.\n-0.6704\n*Tracking difference is computed based on annualised returns of dividend adjusted NAVs from Crisil Fund Analyser tool.\nTracking Difference  (As on 31-Oct-2025)  Regular\nPeriod\nTracking difference\n1 Yr.\n-0.531\n3 Yr.\n-0.6011\n5 Yr.\n-0.6843\n10 Yr.\n-0.8804\nInception.\n-1.6627\n*Tracking difference is computed based on annualised returns of dividend adjusted NAVs from Crisil Fund Analyser tool.\nIndex Constituent\nEnter Date\n4\nSubmit\nPlease provide the Date\nFAQ Section\nStart your investment in\n×\nSBI Magnum Fund Ultra Short Duration\nEdit Plan\nDirect - Growth\nDirect - IDCW\nRegular - Growth\nRegular - IDCW\nSelect IDCW option\nReinvest\nPayout\nIDCW option is required.\nSBI Magnum Fund Ultra Short Duration\nDirect - Growth\nMonthly SIP\n₹500\nStart Date\n26 Feb 2023\nEdit\nExisting Scheme in Cart\nLooks like you already have an existing\nSIP\nin this this scheme in your cart.\nSIP\ndetails listed below:\nEXISTING\nSIP\nDETAILS\nScheme Name\nSBI Magnum Fund Ultra Short Duration - Direct Growth\nSIP\nAmount\n500\nFrequency\nWeekly\nStart Date\n3 June 2023\nEnd Date\n3 June 2032\nTop-up Frequency\nYearly\nTop-up in\nAmount\nTop-up Percent\n5%\nAdd to Cart without Top-up\nAdd to Cart with Top-up\nProceed with existing SIP\nProceed with new SIP\nProceed with existing Lumpsum\nProceed with new Lumpsum\nLumpsum\nStart SIP\nLumpsum Amount\n₹\nMinimum Amount is Rs\nfor Lumpsum/Additional Purchase as applicable\nPlease enter Lumpsum Amount.\nMaximum Amount is Rs 1000000000 for Lumpsum/Additional Purchase as applicable\nAmount should be in multiple of Rs\nfor Lumpsum/Additional Purchase as applicable\nDemat Option\ni\nUnits will be allocated to your Demat Account\nNSDL\nCDSL\nDemat Account No\nIN\nPlease enter a valid 14 digit Demat Account Number\nPlease enter a valid 16 digit Demat Account Number\nDemat Account Number is required\nSIP Amount\n₹\n₹500\n₹1000\n₹2500\nEnter SIP amount.\nSIP amount must be greater than\nfor a\nSIP\nInvestment amount for SBI Small Cap Fund is restricted to Rs.25000 per PAN (first holder/Guardian) per month.\nMaximum Amount is Rs 100000000 for SIP as applicable.\nAmount should be in multiple of Rs\nfor a SIP\nSIP Frequency\nMonthly\nWeekly\nYearly\nMonthly\nWeekly\nYearly\nSIP Start Date\nSelect Day of Installment.\nSIP Tenure\n5 Year\n10 Year\n25 Year\n30 Year\nSelect Custom Date\n5 Year\n10 Year\n25 Year\n30 Year\nSelect Custom Date\nSIP will start on\n& run till\nOne Last Step, Top-Up\nTop-up in\nPercentage\nAmount\nTop-up Frequency\nHalf Yearly\nYearly\nTop-up Percentage\n5%\n10%\n15%\n20%\n25%\n30%\n35%\n40%\n45%\n50%\n55%\n60%\n65%\n70%\n75%\n80%\n85%\n90%\n95%\n100%\n5%\n10%\n15%\n20%\n25%\n30%\n35%\n40%\n45%\n50%\n55%\n60%\n65%\n70%\n75%\n80%\n85%\n90%\n95%\n100%\nTop-up Amount\n₹\nSIP Top Up amount must be greater than Rs 500 amount\nSIP Top Up amount must be in multiples of Rs.500\nSIP Top Up amount is required\nSIP Top Up amount must be less than ₹ 1,00,00,000\nNo. of top-ups\n1\n2\n3\n4\n5\n6\n7\n8\n9\n10\n11\n12\n13\n14\n15\n16\n17\n18\n19\n20\n21\n22\n23\n24\n25\n26\n27\n28\n29\n30\n31\n32\n33\n34\n35\n36\n37\n38\n39\n40\n41\n42\n43\n44\n45\n46\n47\n48\n49\n50\n1\n2\n3\n4\n5\n6\n7\n8\n9\n10\n11\n12\n13\n14\n15\n16\n17\n18\n19\n20\n21\n22\n23\n24\n25\n26\n27\n28\n29\n30\n31\n32\n33\n34\n35\n36\n37\n38\n39\n40\n41\n42\n43\n44\n45\n46\n47\n48\n49\n50\nPlease select No. of topups.\nMax SIP Amount : ₹\nTop Up Max Amount must not Exceed ₹1,00,00,000/-\nThe remaining tenure of your SIP is less than\nto top up a SIP please ensure a minimum of\nare available.\nTop up Till\nSelect Day of Installment.\nMax SIP Amount: ₹\nTop Up Max Amount must not Exceed ₹1,00,00,000/-\nYour top up will end on date\nBy opting out of SIP top-up, you lose out on multiplying your wealth\nSetup Auto Transfer\nAs you grow older, we can dynamically shift your Investments to\na more conservative plan\nLearn More\nThis fund has a lock in period of 5 years or till the investor\nattains the age of 65 whichever is earlier\nI want to top-up my SIP amount\nYour peers (20-30 yrs) usually top-up their SIPs annually\nTop-up Frequency\nHalf-yearly\nYearly\nTop-up in\nAmount\nPercentage\nTop-up Amount\n₹\nMax. amount ₹5,000\nTop-up Till\nAdd to Cart\nInvest Now\nProceed without Top-up\nProceed with Top-up\nHow Auto Transfer Work\nIn case of Auto Transfer, all investment will be made depending on the investor's age. at the time\nof investment into the suitable corresponding investment Plan.Association of investment plan to\nage-groups and risk appetite of investors is illustrated in the following table.\nAge Range(year)\nplan\nUpto 40\nAggresive\n40-50\nAggresive Hybrid\n50-60\nConservative Hybrid\nAbove 60\nConservative\nBasis your date of birth\nregistered in this folio\nis most suitable to you.The fund is subject to a lock in of 5 Years.\nClose\nSetup Auto Transfer\nEmail\nFrom\n*\nEnter Name\nEnter Name\nPlease provide name\nTo\n*\nEnter Email\nEnter Email\nPlease provide valid email(s)\n(max upto 10 email id's allowed separated by ,)\nSubject\n*\nSend\nReset\nFund Overview\nPortfolio Breakup\nPerformance\nFund Data\nIndex Constituent\nSimilar Funds\nView All Funds\nReceive Assistance\nEnter Name\nEnter Name\nPlease enter name\nEnter City\nEnter City\nPlease enter city\nEnter Mobile Number\nEnter Mobile Number\nPlease enter a mobile number\nPlease enter a valid mobile number\nEnter Email ID\nEnter Email ID\nPlease enter an email ID\nPlease enter a valid email ID\nSubmit\nCancel\nLoading...\nMessage Sent!\nGo Back\nSuccess\nFailure\nMessage Sent!\nGo Back\nX",
    "tables": [
      {
        "headers": [
          "Compounded Annualized Growth Rate Performance",
          "1Y",
          "3Y",
          "5Y",
          "10Y",
          "Since Inception"
        ],
        "rows": [
          [
            "SBI Nifty Index Fund",
            "7.06%",
            "13.3%",
            "17.88%",
            "12.79%",
            "14.03%"
          ],
          [
            "Scheme Benchmark: Nifty 50 TRIBenchmark",
            "7.59%",
            "13.9%",
            "18.56%",
            "13.67%",
            "15.69%"
          ],
          [
            "Additional Benchmark: BSE Sensex TRIAdditional Benchmark",
            "6.99%",
            "12.77%",
            "17.59%",
            "13.53%",
            "16.11%"
          ]
        ]
      },
      {
        "headers": [
          "Current Value of Standard Investment of ₹10,000",
          "1Y",
          "3Y",
          "5Y",
          "10Y",
          "Since Inception"
        ],
        "rows": [
          [
            "SBI Nifty Index Fund",
            "₹10706",
            "₹14548",
            "₹22779",
            "₹33360",
            "₹227588"
          ],
          [
            "Scheme Benchmark: Nifty 50 TRIBenchmark",
            "₹10759",
            "₹14781",
            "₹23449",
            "₹36060",
            "₹321215"
          ],
          [
            "Additional Benchmark: BSE Sensex TRIAdditional Benchmark",
            "₹10699",
            "₹14346",
            "₹22502",
            "₹35630",
            "₹349954"
          ]
        ]
      },
      {
        "headers": [
          "Compounded Annualized Growth Rate Performance",
          "1Y",
          "3Y",
          "5Y",
          "10Y",
          "Since Inception"
        ],
        "rows": [
          [
            "SBI Nifty Index Fund",
            "7.3%",
            "13.62%",
            "18.24%",
            "13.21%",
            "12.79%"
          ],
          [
            "Scheme Benchmark: Nifty 50 TRIBenchmark",
            "7.59%",
            "13.9%",
            "18.56%",
            "13.67%",
            "13.46%"
          ],
          [
            "Additional Benchmark: BSE Sensex TRIAdditional Benchmark",
            "6.99%",
            "12.77%",
            "17.59%",
            "13.53%",
            "13.48%"
          ]
        ]
      },
      {
        "headers": [
          "Current Value of Standard Investment of ₹10,000",
          "1Y",
          "3Y",
          "5Y",
          "10Y",
          "Since Inception"
        ],
        "rows": [
          [
            "SBI Nifty Index Fund",
            "₹10730",
            "₹14671",
            "₹23129",
            "₹34641",
            "₹46878"
          ],
          [
            "Scheme Benchmark: Nifty 50 TRIBenchmark",
            "₹10759",
            "₹14781",
            "₹23449",
            "₹36060",
            "₹50584"
          ],
          [
            "Additional Benchmark: BSE Sensex TRIAdditional Benchmark",
            "₹10699",
            "₹14346",
            "₹22502",
            "₹35630",
            "₹50714"
          ]
        ]
      },
      {
        "headers": [
          "Quantitative Data"
        ],
        "rows": [
          [
            "Expense Ratio Regular  in % (as on 31 Oct ,2025)",
            ":",
            "0.38"
          ],
          [
            "Expense Ratio Direct  in % (as on 31 Oct ,2025)",
            ":",
            "0.19"
          ],
          [
            "Tracking Error Direct (as on 14 Nov ,2025)",
            ":",
            "0.015 %"
          ],
          [
            "Tracking Error Regular (as on 14 Nov ,2025)",
            ":",
            "0.0198 %"
          ],
          [
            "Sharpe Ratio",
            ":",
            "0.64"
          ],
          [
            "Standard Deviation",
            ":",
            "11.69%"
          ],
          [
            "Beta",
            ":",
            "1"
          ]
        ]
      },
      {
        "headers": [
          "Tracking Difference  (As on 31-Oct-2025)  Direct"
        ],
        "rows": [
          [
            "Period",
            "Tracking difference"
          ],
          [
            "1 Yr.",
            "-0.29"
          ],
          [
            "3 Yr.",
            "-0.2822"
          ],
          [
            "5 Yr.",
            "-0.3252"
          ],
          [
            "10 Yr.",
            "-0.455"
          ],
          [
            "Inception.",
            "-0.6704"
          ]
        ]
      },
      {
        "headers": [
          "Tracking Difference  (As on 31-Oct-2025)  Regular"
        ],
        "rows": [
          [
            "Period",
            "Tracking difference"
          ],
          [
            "1 Yr.",
            "-0.531"
          ],
          [
            "3 Yr.",
            "-0.6011"
          ],
          [
            "5 Yr.",
            "-0.6843"
          ],
          [
            "10 Yr.",
            "-0.8804"
          ],
          [
            "Inception.",
            "-1.6627"
          ]
        ]
      },
      {
        "headers": [
          "Age Range(year)",
          "plan"
        ],
        "rows": [
          [
            "Upto 40",
            "Aggresive"
          ],
          [
            "40-50",
            "Aggresive Hybrid"
          ],
          [
            "50-60",
            "Conservative Hybrid"
          ],
          [
            "Above 60",
            "Conservative"
          ]
        ]
      }
    ],
    "metadata": {
      "url": "https://www.sbimf.com/sbimf-scheme-details/sbi-nifty-index-fund-13",
      "title": "SBI Nifty Index Fund",
      "last_modified": null,
      "breadcrumbs": []
    },
    "factual_data": {
      "expense_ratio_regular": "14.03",
      "expense_ratio_direct": "12.79",
      "exit_load": "0",
      "minimum_sip": null,
      "minimum_lumpsum": null,
      "lock_in_period": "5",
      "riskometer": "50",
      "benchmark": "Riskometer\nNifty 50 TRI\nLow\nLow to Moderate\nModerate\nModerately High\nHigh\nVery High\nRISKOMETER\nThe risk of the benchmark is\nVery High\nPerformance\nRegular Growth\nDirect Growth\nCompounded Annualized Growth Rate Performance\n1Y\n3Y\n5Y\n10Y\nSince Inception\nSBI Nifty Index"
    },
    "scraped_date": "2025-11-17T22:21:36.847331",
    "scheme_name": "SBI Nifty Index Fund",
    "document_type": "scheme_details",
    "scheme_name_validated": true,
    "match_score": 1.0
  },
  {
    "url": "https://www.sbimf.com/sbimf-scheme-details/sbi-small-cap-fund-329",
    "title": "SBI Small Cap Fund",
    "content": "SBI Small Cap Fund\nScheme Type :\nAn open-ended Equity Scheme predominantly investing in small cap stocks\nEQUITY\nOpen Ended\nAn open-ended Equity Scheme predominantly investing in small cap stocks\nVERY HIGH Risk\nReturns                                                     for Regular-Growth\n19.35%\n19.35%\n-3.21%\n15%\n24.29%\nSince Inception\n1 Year\n3 Year\n5 Year\nSince Inception\nSince Inception\n1 Year\n3 Year\n5 Year\nReturns for Direct growth\n23.82%\n23.82%\n-2.39%\n16.1%\n25.52%\nSince Inception\n1 Year\n3 Year\n5 Year\nSince Inception\nSince Inception\n1 Year\n3 Year\n5 Year\nAUM as on 31 Oct 2025\n₹36932.72Cr\nDate of Allotment\n09 Sep, 2009\nExit Load\n12%\nview details\nFor exit within 1 year from the date of allotment - 1%;\nFor exit after 1 year from the date of allotment - Nil.\nBenchmark :\nScheme Benchmark: BSE 250 SMALLCAP INDEX TRI\nAdditional Benchmark: BSE Sensex TRI\nSuitable for :\nLong-Term Capital Appreciation\nCompare Fund\nInvest\nEnter SIP Amount\nEnter SIP Amount\nMin. Amount Rs.\n500\nLumpsum Investments not available for the selected scheme\nAdd to Cart\nProceed to Invest\n4343 people\nare already invested\nHistorical NAV\nSBI Small Cap Fund - Regular Plan - Growth\nSBI Small Cap Fund - Direct Plan - IDCW\nSBI Small Cap Fund - Regular Plan - IDCW\nSBI Small Cap Fund - Regular Plan - Growth\nSBI Small Cap Fund - Direct Plan - Growth\n1 Year\n1 Year\n3 Year\n5 Year\nNAV as on\nNov 17, 2025\nNAV stands for Net Asset Value.\n₹\n172.4795\n(\n+0.43% one day change\n)\nCreated with Highcharts 8.1.2\nValues\nNov 2…\nNov 2024\nDec 2024\nJan 2025\nFeb 2025\nMar 2025\nApr 2025\nMay 2025\nJun 2025\nJul 2025\nAug 2025\nSep 2025\nOct 2025\nNov 2025\n140\n150\n160\n170\n180\n190\nPast Performance may or may not be sustained in future\nInvestment Criteria\nMin SIP Amount\n₹ 500\nReturns Calculator\nMonthly SIP\nMonthly SIP\nMonthly SIP\nEnter Investment Amount\n5 %\n6 %\n7 %\n8 %\n9 %\n10 %\n11 %\n12 %\n13 %\n14 %\n15 %\n16 %\n17 %\n18 %\n19 %\n20 %\n21 %\n22 %\n5 %\n5 %\n6 %\n7 %\n8 %\n9 %\n10 %\n11 %\n12 %\n13 %\n14 %\n15 %\n16 %\n17 %\n18 %\n19 %\n20 %\n21 %\n22 %\nDuration\n1Y\nNet Return\n₹6,165.009\nFund Overview\nPortfolio Breakup\nPerformance\nDocuments\nFund Data\nFund Overview\nSBI Small Cap Fund aims to provide investors with opportunities for long-term growth in capital by investing predominantly in a well-diversified basket of equity stocks of small cap companies.\nThe fund predominantly invests (minimum 65%) in small cap stocks.\nSBI Small Cap Fund can also take up to 35% exposure in other equities (including large and mid-cap companies) and/or debt and money market instruments.\nThe fund follows a blend of growth and value style of investing and will follow bottom-up investment strategy for stock selection.\nMr. R Srinivasan -\nR Srinivasan has over 30 years’ rich experience in the financial services space. He has been associated with SBI Funds Management Limited since 2009 and as CIO – Equity directly manages a number of funds. He was formerly the Head of Equity. Srinivasan is a postgraduate in Commerce and has done his MFM from the University of Mumbai.\n...\nSee More\nManaging this fund since\nNov 2013\nMore Funds\nmanaged by\nMr. R Srinivasan\nProduct Label\nThis product is suitable for investors who are seeking*\nLong term capital appreciation.\nInvestment in equity and equity-related securities predominantly of small cap companies.\n*Investors should consult their financial advisors if in doubt whether the product is suitable for them.\nRiskometer\nSBI Small Cap Fund\nLow\nLow to Moderate\nModerate\nModerately High\nHigh\nVery High\nRISKOMETER\nThe risk of the scheme is\nVery High\nBenchmark Riskometer\nBSE 250 SMALLCAP INDEX TRI\nLow\nLow to Moderate\nModerate\nModerately High\nHigh\nVery High\nRISKOMETER\nThe risk of the benchmark is\nVery High\nPortfolio Breakup\nTop Holdings\n(as on\n31 Oct 2025\n)\nCreated with Highcharts 8.1.2\n4.14%\n3.76%\n2.76%\n2.71%\n2.69%\n2.58%\n0\n2\n4\n6\n8\n10\n12\n14\nCASH, CASH EQUIVALENTS AND OTHERS\nATHER ENERGY LTD.\nSBFC FINANCE LTD.\nE.I.D-PARRY (INDIA) LTD.\nKALPATARU PROJECTS INTERNATIONAL LTD.\nCITY UNION BANK LTD.\nView all holdings\nSector Allocations\nCreated with Highcharts 8.1.2\n13.64%\n10.67%\n10.37%\n9.35%\n8.9%\n8.22%\n0\n2\n4\n6\n8\n10\n12\n14\n16\n18\n20\n22\n24\nFINANCIAL SERVICES\nCAPITAL GOODS\nCONSUMER DURABLES\nDERIVATIVES\nFAST MOVING CONSUMER GOODS\nCONSUMER SERVICES\nView all allocations\nAll Holdings\n(as on\n31 Oct 2025\n)\nAll Allocations\nPerformance\nRegular Growth\nDirect Growth\nCompounded Annualized Growth Rate Performance\n1Y\n3Y\n5Y\n10Y\nSince Inception\nSBI Smallcap Fund\n-3.21%\n15%\n24.29%\n18.34%\n19.35%\nScheme Benchmark: BSE 250 SMALLCAP INDEX TRI\nBenchmark\n-2.62%\n22.3%\n28.46%\n15.65%\n12.28%\nAdditional Benchmark: BSE Sensex TRI\nAdditional Benchmark\n6.99%\n12.77%\n17.59%\n13.53%\n12.22%\nCurrent Value of Standard Investment of ₹10,000\n1Y\n3Y\n5Y\n10Y\nSince Inception\nSBI Smallcap Fund\n₹9679\n₹15214\n₹29696\n₹53974\n₹174203\nScheme Benchmark: BSE 250 SMALLCAP INDEX TRI\nBenchmark\n₹9738\n₹18301\n₹35023\n₹42870\n₹64972\nAdditional Benchmark: BSE Sensex TRI\nAdditional Benchmark\n₹10699\n₹14346\n₹22502\n₹35630\n₹64428\nNotes:\nDifferent plans shall have different expense structure. In case of return calculated the IDCW option, it is assumed that dividend declared under the schemes have been reinvested at the prevailing NAV\nPast performance may or may not be sustained in future and same may not necessarily provide the basis for comparison with other investment\nLoad is not considered for computation of returns\nPeriod for which scheme’s performance has been provided is computed basis last day of the month-end preceding the date of advertisement. In case, the start/end date of the concerned period is a non-business day, the NAV of the previous date is considered for computation of returns\nThe data of the last working day has been considered for the calculation of performance\nWherever TRI data since inception for benchmarks is not available, benchmark performance is calculated using composite of CAGR and TRI values of the benchmark\nThe performance of the schemes is benchmarked to the Total Return variant of the Index\nTo view other open ended funds managed by the fund manager go to the Fund Manager section\nCompounded Annualized Growth Rate Performance\n1Y\n3Y\n5Y\n10Y\nSince Inception\nSBI Smallcap Fund\n-2.39%\n16.1%\n25.52%\n19.64%\n23.82%\nScheme Benchmark: BSE 250 SMALLCAP INDEX TRI\nBenchmark\n-2.62%\n22.3%\n28.46%\n15.65%\n14.65%\nAdditional Benchmark: BSE Sensex TRI\nAdditional Benchmark\n6.99%\n12.77%\n17.59%\n13.53%\n13.42%\nCurrent Value of Standard Investment of ₹10,000\n1Y\n3Y\n5Y\n10Y\nSince Inception\nSBI Smallcap Fund\n₹9761\n₹15655\n₹31202\n₹60222\n₹155263\nScheme Benchmark: BSE 250 SMALLCAP INDEX TRI\nBenchmark\n₹9738\n₹18301\n₹35023\n₹42870\n₹57837\nAdditional Benchmark: BSE Sensex TRI\nAdditional Benchmark\n₹10699\n₹14346\n₹22502\n₹35630\n₹50371\nNotes:\nDifferent plans shall have different expense structure. In case of return calculated the IDCW option, it is assumed that dividend declared under the schemes have been reinvested at the prevailing NAV\nPast performance may or may not be sustained in future and same may not necessarily provide the basis for comparison with other investment\nLoad is not considered for computation of returns\nPeriod for which scheme’s performance has been provided is computed basis last day of the month-end preceding the date of advertisement. In case, the start/end date of the concerned period is a non-business day, the NAV of the previous date is considered for computation of returns\nThe data of the last working day has been considered for the calculation of performance\nWherever TRI data since inception for benchmarks is not available, benchmark performance is calculated using composite of DCAGR and TRI values of the benchmark\nThe performance of the schemes is benchmarked to the Total Return variant of the Index\nTo view other open ended funds managed by the fund manager go to the Fund Manager section\nDocuments\nFile Name\nFile Type\nFile Size\nSBI Small Cap Fund  Factsheet October 2025\n1  MB\nSBI SMALL CAP FUND MONTHLY PORTFOLIO - OCTOBER 2025\n84  KB\nSID - SBI Small Cap Fund\n2  MB\nKIM - SBI Small Cap Fund\n377  KB\nDownload\nFund Data\nQuantitative Data\nExpense Ratio Regular  in % (as on 31 Oct ,2025)\n:\n1.56\nExpense Ratio Direct  in % (as on 31 Oct ,2025)\n:\n0.75\nSharpe Ratio\n:\n0.61\nStandard Deviation\n:\n14.29%\nBeta\n:\n0.72\nSource: CRISIL Fund Analyser\nRisk Free rate: FBIL Overnight Mibor rate (9.39% as on 30 Sep, 2024) basis for ratio calculation : 3 Years Monthly Data points\n**All expense ratios are inclusive of GST on Management Fees\nIDCW History\nChoose Plan\nSBI Small Cap Fund - Direct Plan - IDCW\nSBI Small Cap Fund - Direct Plan - IDCW\nSBI Small Cap Fund - Regular Plan - IDCW\nRecord Date\nIDCW*\nNAV(₹)\n09 Mar 2018\n11.1\n40.7137\n28 Aug 2015\n4.3\n27.86300\nFace Value: ₹ 10\nPursuant to payment of IDCW, the NAV of IDCW Option of schemes/plans would fall to the extent of payout and statutory levy, if applicable.\nAfter dividend distribution tax.\nFAQ Section\nHow to Invest in SBI Small Cap Fund?\n> Log in to the website.\n> Choose between Lumpsum or Systematic Investment Plan (SIP).\n> Choose your bank and preferred payment method.\n> An OTP will be sent to your registered email ID and mobile number.\n> Your transaction will be processed after OTP verification.\nWhat is the current NAV of SBI Small Cap Fund?\nLatest closing NAV as on 17 Nov, 2025 for SBI Small Cap Fund - Regular Plan - Growth is Rs. 172.4795\nWhat is the AUM of SBI Small Cap Fund?\nAUM of SBI Small Cap Fund is 36932.72 Cr.\nWhat is the Riskometer level of SBI Small Cap Fund?\nSBI Small Cap Fund is rated as a VERY HIGH. Benchmark Riskometer for this fund is S&P BSE Small Cap Index.\nWhat are the top holdings of SBI Small Cap Fund?\nTop Holdings for the fund as per percentage of amount invested is as follows:\n> CASH, CASH EQUIVALENTS AND OTHERS : 4.14 %\n> ATHER ENERGY LTD. : 3.76 %\n> SBFC FINANCE LTD. : 2.76 %\n> E.I.D-PARRY (INDIA) LTD. : 2.71 %\n> KALPATARU PROJECTS INTERNATIONAL LTD. : 2.69 %\n> CITY UNION BANK LTD. : 2.58 %\nIs there any lock-in period for SBI Small Cap Fund?\nNo lock-in period is applicable for this fund.\nWhat is the expense ratio of SBI Small Cap Fund?\nExpense ratio for Regular scheme is 1.56% as on 31 Oct 2025 and Expense Ratio for Direct Scheme is 0.75% as on 31 Oct 2025\nHow can I redeem my investments in SBI Small Cap Fund?\n> Login to your account.\n> In the Dashboard, go to the Portfolio Snapshot section and click on Transact > Redeem.\n> Enter the Amount/Units you wish to redeem.\n> An OTP will be sent to your registered email ID/mobile number.\n> After OTP verification, your redemption will be processed in 3 business working days.\nWhat are the top sectors SBI Small Cap Fund has invested in?\nSector Allocations for as per percentage of amount invested is as follows:\n> FINANCIAL SERVICES : 13.64 %\n> CAPITAL GOODS : 10.67 %\n> CONSUMER DURABLES : 10.37 %\n> DERIVATIVES : 9.35 %\n> FAST MOVING CONSUMER GOODS : 8.9 %\n> CONSUMER SERVICES : 8.22 %\nWho manages the SBI Small Cap Fund?\nThe Fund manager for this fund is:\n> Mr. R Srinivasan since November 2013\nWhat is the minimum investment in SBI Small Cap Fund?\nMinimum Lumpsum Amount applicable for this fund is Rs. 5000 in multiples of 1.\nMinimum Additional Lumpsum Amount applicable for this fund is Rs. 1000 in multiples of 1.\nMinimum SIP Amount applicable for fund is Rs. 500\nStart your investment in\n×\nSBI Magnum Fund Ultra Short Duration\nEdit Plan\nDirect - Growth\nDirect - IDCW\nRegular - Growth\nRegular - IDCW\nSelect IDCW option\nReinvest\nPayout\nIDCW option is required.\nSBI Magnum Fund Ultra Short Duration\nDirect - Growth\nMonthly SIP\n₹500\nStart Date\n26 Feb 2023\nEdit\nExisting Scheme in Cart\nLooks like you already have an existing\nSIP\nin this this scheme in your cart.\nSIP\ndetails listed below:\nEXISTING\nSIP\nDETAILS\nScheme Name\nSBI Magnum Fund Ultra Short Duration - Direct Growth\nSIP\nAmount\n500\nFrequency\nWeekly\nStart Date\n3 June 2023\nEnd Date\n3 June 2032\nTop-up Frequency\nYearly\nTop-up in\nAmount\nTop-up Percent\n5%\nAdd to Cart without Top-up\nAdd to Cart with Top-up\nProceed with existing SIP\nProceed with new SIP\nProceed with existing Lumpsum\nProceed with new Lumpsum\nLumpsum\nStart SIP\nLumpsum Amount\n₹\nMinimum Amount is Rs\nfor Lumpsum/Additional Purchase as applicable\nPlease enter Lumpsum Amount.\nMaximum Amount is Rs 1000000000 for Lumpsum/Additional Purchase as applicable\nAmount should be in multiple of Rs\nfor Lumpsum/Additional Purchase as applicable\nDemat Option\ni\nUnits will be allocated to your Demat Account\nNSDL\nCDSL\nDemat Account No\nIN\nPlease enter a valid 14 digit Demat Account Number\nPlease enter a valid 16 digit Demat Account Number\nDemat Account Number is required\nSIP Amount\n₹\n₹500\n₹1000\n₹2500\nEnter SIP amount.\nSIP amount must be greater than\nfor a\nSIP\nInvestment amount for SBI Small Cap Fund is restricted to Rs.25000 per PAN (first holder/Guardian) per month.\nMaximum Amount is Rs 100000000 for SIP as applicable.\nAmount should be in multiple of Rs\nfor a SIP\nSIP Frequency\nMonthly\nWeekly\nYearly\nMonthly\nWeekly\nYearly\nSIP Start Date\nSelect Day of Installment.\nSIP Tenure\n5 Year\n10 Year\n25 Year\n30 Year\nSelect Custom Date\n5 Year\n10 Year\n25 Year\n30 Year\nSelect Custom Date\nSIP will start on\n& run till\nOne Last Step, Top-Up\nTop-up in\nPercentage\nAmount\nTop-up Frequency\nHalf Yearly\nYearly\nTop-up Percentage\n5%\n10%\n15%\n20%\n25%\n30%\n35%\n40%\n45%\n50%\n55%\n60%\n65%\n70%\n75%\n80%\n85%\n90%\n95%\n100%\n5%\n10%\n15%\n20%\n25%\n30%\n35%\n40%\n45%\n50%\n55%\n60%\n65%\n70%\n75%\n80%\n85%\n90%\n95%\n100%\nTop-up Amount\n₹\nSIP Top Up amount must be greater than Rs 500 amount\nSIP Top Up amount must be in multiples of Rs.500\nSIP Top Up amount is required\nSIP Top Up amount must be less than ₹ 1,00,00,000\nNo. of top-ups\n1\n2\n3\n4\n5\n6\n7\n8\n9\n10\n11\n12\n13\n14\n15\n16\n17\n18\n19\n20\n21\n22\n23\n24\n25\n26\n27\n28\n29\n30\n31\n32\n33\n34\n35\n36\n37\n38\n39\n40\n41\n42\n43\n44\n45\n46\n47\n48\n49\n50\n1\n2\n3\n4\n5\n6\n7\n8\n9\n10\n11\n12\n13\n14\n15\n16\n17\n18\n19\n20\n21\n22\n23\n24\n25\n26\n27\n28\n29\n30\n31\n32\n33\n34\n35\n36\n37\n38\n39\n40\n41\n42\n43\n44\n45\n46\n47\n48\n49\n50\nPlease select No. of topups.\nMax SIP Amount : ₹\nTop Up Max Amount must not Exceed ₹1,00,00,000/-\nThe remaining tenure of your SIP is less than\nto top up a SIP please ensure a minimum of\nare available.\nTop up Till\nSelect Day of Installment.\nMax SIP Amount: ₹\nTop Up Max Amount must not Exceed ₹1,00,00,000/-\nYour top up will end on date\nBy opting out of SIP top-up, you lose out on multiplying your wealth\nSetup Auto Transfer\nAs you grow older, we can dynamically shift your Investments to\na more conservative plan\nLearn More\nThis fund has a lock in period of 5 years or till the investor\nattains the age of 65 whichever is earlier\nI want to top-up my SIP amount\nYour peers (20-30 yrs) usually top-up their SIPs annually\nTop-up Frequency\nHalf-yearly\nYearly\nTop-up in\nAmount\nPercentage\nTop-up Amount\n₹\nMax. amount ₹5,000\nTop-up Till\nAdd to Cart\nInvest Now\nProceed without Top-up\nProceed with Top-up\nHow Auto Transfer Work\nIn case of Auto Transfer, all investment will be made depending on the investor's age. at the time\nof investment into the suitable corresponding investment Plan.Association of investment plan to\nage-groups and risk appetite of investors is illustrated in the following table.\nAge Range(year)\nplan\nUpto 40\nAggresive\n40-50\nAggresive Hybrid\n50-60\nConservative Hybrid\nAbove 60\nConservative\nBasis your date of birth\nregistered in this folio\nis most suitable to you.The fund is subject to a lock in of 5 Years.\nClose\nSetup Auto Transfer\nEmail\nFrom\n*\nEnter Name\nEnter Name\nPlease provide name\nTo\n*\nEnter Email\nEnter Email\nPlease provide valid email(s)\n(max upto 10 email id's allowed separated by ,)\nSubject\n*\nSend\nReset\nFund Overview\nPortfolio Breakup\nPerformance\nFund Data\nSimilar Funds\nView All Funds\nReceive Assistance\nEnter Name\nEnter Name\nPlease enter name\nEnter City\nEnter City\nPlease enter city\nEnter Mobile Number\nEnter Mobile Number\nPlease enter a mobile number\nPlease enter a valid mobile number\nEnter Email ID\nEnter Email ID\nPlease enter an email ID\nPlease enter a valid email ID\nSubmit\nCancel\nLoading...\nMessage Sent!\nGo Back\nSuccess\nFailure\nMessage Sent!\nGo Back\nX",
    "tables": [
      {
        "headers": [
          "Compounded Annualized Growth Rate Performance",
          "1Y",
          "3Y",
          "5Y",
          "10Y",
          "Since Inception"
        ],
        "rows": [
          [
            "SBI Smallcap Fund",
            "-3.21%",
            "15%",
            "24.29%",
            "18.34%",
            "19.35%"
          ],
          [
            "Scheme Benchmark: BSE 250 SMALLCAP INDEX TRIBenchmark",
            "-2.62%",
            "22.3%",
            "28.46%",
            "15.65%",
            "12.28%"
          ],
          [
            "Additional Benchmark: BSE Sensex TRIAdditional Benchmark",
            "6.99%",
            "12.77%",
            "17.59%",
            "13.53%",
            "12.22%"
          ]
        ]
      },
      {
        "headers": [
          "Current Value of Standard Investment of ₹10,000",
          "1Y",
          "3Y",
          "5Y",
          "10Y",
          "Since Inception"
        ],
        "rows": [
          [
            "SBI Smallcap Fund",
            "₹9679",
            "₹15214",
            "₹29696",
            "₹53974",
            "₹174203"
          ],
          [
            "Scheme Benchmark: BSE 250 SMALLCAP INDEX TRIBenchmark",
            "₹9738",
            "₹18301",
            "₹35023",
            "₹42870",
            "₹64972"
          ],
          [
            "Additional Benchmark: BSE Sensex TRIAdditional Benchmark",
            "₹10699",
            "₹14346",
            "₹22502",
            "₹35630",
            "₹64428"
          ]
        ]
      },
      {
        "headers": [
          "Compounded Annualized Growth Rate Performance",
          "1Y",
          "3Y",
          "5Y",
          "10Y",
          "Since Inception"
        ],
        "rows": [
          [
            "SBI Smallcap Fund",
            "-2.39%",
            "16.1%",
            "25.52%",
            "19.64%",
            "23.82%"
          ],
          [
            "Scheme Benchmark: BSE 250 SMALLCAP INDEX TRIBenchmark",
            "-2.62%",
            "22.3%",
            "28.46%",
            "15.65%",
            "14.65%"
          ],
          [
            "Additional Benchmark: BSE Sensex TRIAdditional Benchmark",
            "6.99%",
            "12.77%",
            "17.59%",
            "13.53%",
            "13.42%"
          ]
        ]
      },
      {
        "headers": [
          "Current Value of Standard Investment of ₹10,000",
          "1Y",
          "3Y",
          "5Y",
          "10Y",
          "Since Inception"
        ],
        "rows": [
          [
            "SBI Smallcap Fund",
            "₹9761",
            "₹15655",
            "₹31202",
            "₹60222",
            "₹155263"
          ],
          [
            "Scheme Benchmark: BSE 250 SMALLCAP INDEX TRIBenchmark",
            "₹9738",
            "₹18301",
            "₹35023",
            "₹42870",
            "₹57837"
          ],
          [
            "Additional Benchmark: BSE Sensex TRIAdditional Benchmark",
            "₹10699",
            "₹14346",
            "₹22502",
            "₹35630",
            "₹50371"
          ]
        ]
      },
      {
        "headers": [
          "File Name",
          "File Type",
          "File Size"
        ],
        "rows": [
          [
            "SBI Small Cap Fund  Factsheet October 2025",
            "",
            "1  MB"
          ],
          [
            "SBI SMALL CAP FUND MONTHLY PORTFOLIO - OCTOBER 2025",
            "",
            "84  KB"
          ],
          [
            "SID - SBI Small Cap Fund",
            "",
            "2  MB"
          ],
          [
            "KIM - SBI Small Cap Fund",
            "",
            "377  KB"
          ]
        ]
      },
      {
        "headers": [
          "Quantitative Data"
        ],
        "rows": [
          [
            "Expense Ratio Regular  in % (as on 31 Oct ,2025)",
            ":",
            "1.56"
          ],
          [
            "Expense Ratio Direct  in % (as on 31 Oct ,2025)",
            ":",
            "0.75"
          ],
          [
            "Sharpe Ratio",
            ":",
            "0.61"
          ],
          [
            "Standard Deviation",
            ":",
            "14.29%"
          ],
          [
            "Beta",
            ":",
            "0.72"
          ]
        ]
      },
      {
        "headers": [
          "Record Date",
          "IDCW*",
          "NAV(₹)"
        ],
        "rows": [
          [
            "09 Mar 2018",
            "11.1",
            "40.7137"
          ],
          [
            "28 Aug 2015",
            "4.3",
            "27.86300"
          ]
        ]
      },
      {
        "headers": [
          "Age Range(year)",
          "plan"
        ],
        "rows": [
          [
            "Upto 40",
            "Aggresive"
          ],
          [
            "40-50",
            "Aggresive Hybrid"
          ],
          [
            "50-60",
            "Conservative Hybrid"
          ],
          [
            "Above 60",
            "Conservative"
          ]
        ]
      }
    ],
    "metadata": {
      "url": "https://www.sbimf.com/sbimf-scheme-details/sbi-small-cap-fund-329",
      "title": "SBI Small Cap Fund",
      "last_modified": null,
      "breadcrumbs": []
    },
    "factual_data": {
      "expense_ratio_regular": "1.56",
      "expense_ratio_direct": "0.75",
      "exit_load": "12",
      "minimum_sip": "500",
      "minimum_lumpsum": "5000",
      "lock_in_period": "5",
      "riskometer": "250",
      "benchmark": "BSE 250 SMALLCAP INDEX"
    },
    "scraped_date": "2025-11-17T22:21:51.486101",
    "scheme_name": "SBI Small Cap Fund",
    "document_type": "scheme_details",
    "scheme_name_validated": true,
    "match_score": 1.0
  },
  {
    "url": "https://www.sbimf.com/sbimf-scheme-details/sbi-equity-hybrid-fund-5",
    "title": "SBI Equity Hybrid Fund",
    "content": "SBI Equity Hybrid Fund\nScheme Type :\nAn open-ended Hybrid Scheme investing predominantly in equity and equity related instruments\nHYBRID\nOpen Ended\nAn open-ended Hybrid Scheme investing predominantly in equity and equity related instruments\nVERY HIGH Risk\nReturns                                                     for Regular-Growth\n15.22%\n15.22%\n12.42%\n14.15%\n16.93%\nSince Inception\n1 Year\n3 Year\n5 Year\nSince Inception\nSince Inception\n1 Year\n3 Year\n5 Year\nReturns for Direct growth\n15.04%\n15.04%\n13.16%\n14.92%\n17.73%\nSince Inception\n1 Year\n3 Year\n5 Year\nSince Inception\nSince Inception\n1 Year\n3 Year\n5 Year\nAUM as on 31 Oct 2025\n₹81965.33Cr\nDate of Allotment\n09 Oct, 1995\nExit Load\n12%\nview details\nFor exit within 12 months from the date  of allotment:\n- For 10% of investment - Nil\n- For remaining investments - 1.00%\nFor exit after 12 months from the date of allotment - Nil.\nBenchmark :\nScheme Benchmark: CRISIL Hybrid 35+65 - Aggressive Index\nAdditional Benchmark: BSE Sensex TRI\nSuitable for :\nLong-Term Capital Appreciation\nCompare Fund\nInvest\nEnter SIP Amount\nEnter SIP Amount\nMin. Amount Rs.\n500\nEnter Lumpsum Amount\nEnter Lumpsum Amount\nMin. Lumpsum amount Rs.\n1,000\n(For Additional Investment Rs. 1,000)\nAdd to Cart\nProceed to Invest\n2010 people\nare already invested\nHistorical NAV\nSBI Equity Hybrid Fund - Regular Plan - Growth\nSBI Equity Hybrid Fund - Regular Plan - IDCW\nSBI Equity Hybrid Fund - Regular Plan - Growth\nSBI Equity Hybrid Fund - Direct Plan - IDCW\nSBI Equity Hybrid Fund - Direct Plan - Growth\n1 Year\n1 Year\n3 Year\n5 Year\nNAV as on\nNov 17, 2025\nNAV stands for Net Asset Value.\n₹\n312.5363\n(\n+0.21% one day change\n)\nCreated with Highcharts 8.1.2\nValues\nNov 2…\nNov 2024\nDec 2024\nJan 2025\nFeb 2025\nMar 2025\nApr 2025\nMay 2025\nJun 2025\nJul 2025\nAug 2025\nSep 2025\nOct 2025\nNov 2025\n260\n270\n280\n290\n300\n310\n320\nPast Performance may or may not be sustained in future\nInvestment Criteria\nMin Lumpsum\n₹ 1,000\n& in multiples of 1\nMin Add Lumpsum\n₹ 1,000\n& in multiples of 1\nMin SIP Amount\n₹ 500\nReturns Calculator\nMonthly SIP\nLumpsum\nMonthly SIP\nMonthly SIP\nLumpsum\nEnter Investment Amount\n5 %\n6 %\n7 %\n8 %\n9 %\n10 %\n11 %\n12 %\n13 %\n14 %\n15 %\n16 %\n17 %\n18 %\n19 %\n20 %\n21 %\n22 %\n5 %\n5 %\n6 %\n7 %\n8 %\n9 %\n10 %\n11 %\n12 %\n13 %\n14 %\n15 %\n16 %\n17 %\n18 %\n19 %\n20 %\n21 %\n22 %\nDuration\n1Y\nNet Return\n₹6,165.009\nFund Overview\nPortfolio Breakup\nPerformance\nDocuments\nFund Data\nFund Overview\nSBI Equity Hybrid Fund aims to provide investors with opportunities for long-term capital appreciation with liquidity of an open-ended scheme by investing in a mix of debt and equity.\nThe fund invests in a diversified portfolio of stocks of high growth companies and balance the risk through investing the rest in fixed income securities.\nSBI Equity Hybrid Fund invests minimum of 65% in equity and equity related instruments.\nAt any point of time, the fund will allocate assets in the range of 20-35% towards debt and money market instruments.\nMr. R Srinivasan -\nR Srinivasan has over 30 years’ rich experience in the financial services space. He has been associated with SBI Funds Management Limited since 2009 and as CIO – Equity directly manages a number of funds. He was formerly the Head of Equity. Srinivasan is a postgraduate in Commerce and has done his MFM from the University of Mumbai.\n...\nSee More\nManaging this fund since\nJan 2012\nMore Funds\nmanaged by\nMr. R Srinivasan\nMr. Rajeev Radhakrishnan -\nRajeev Radhakrishnan has over 22 years experience in the Asset Management industry with around 20 years experience in fixed income funds management and dealing. Rajeev joined SBI Funds Management Limited (SBIFML) in 2008 as a Fixed Income Fund manager and later became Head - Fixed Income. He is currently CIO - Fixed Income and directly manages many of our flagship funds. Over this extensive experience in the asset management industry, he has managed Fixed Income products across liquid, money markets, hybrid, and active duration across various credit and interest rate cycles. Rajeev has also successfully led the mandate for unwinding the illiquid credit portfolio of a major fund house based on the mandate assigned by the Honourable Supreme Court and SEBI.Prior to joining SBIFML, Rajeev was associated with UTI Asset Management for seven years as co-Fund Manager, Fixed Income. During this initial tenure in UTIMF, Rajeev has had experience in equity and sectoral research for a brief period of 18 months, where he was associated with the unwinding of the US 64 portfolio, before shifting to Fixed Income dealing and subsequently to Fixed Income research and portfolio management.Rajeev is an Engineering graduate and holds a Master's degree in Finance from Mumbai University. He is also a Charter holder of the CFA Institute, USA. Rajeev is currently a member of the IRDAI consultative committee on Investments. He is also a Board member of the Indian Association of Investment Professionals (CFA India Society) & a member of the AMFI valuation committee. With a keen interest in identifying macroeconomic trends, Rajeev is also a periodic contributor to various external publications and media debates with respect to Fixed Income market trends.\n...\nSee More\nManaging this fund since\nNov 2023\nMore Funds\nmanaged by\nMr. Rajeev Radhakrishnan\nMs. Mansi Sajeja -\nMansi Sajeja joined SBIFM in 2009. Prior to joining SBIFM Mansi was a senior rating analyst at ICRA Limited (A Moody's Investors Service Company) for over three years. Mansi holds bachelor's degree in Financial & Investment analysis from Delhi University and has completed post graduation diploma in Business Management from MDI, Gurgaon. She is also a Charter holder of the CFA Institute, USA.\n...\nSee More\nManaging this fund since\nDec 2023\nMore Funds\nmanaged by\nMs. Mansi Sajeja\nVideos for\nSBI Equity Hybrid Fund\nProduct Label\nThis product is suitable for investors who are seeking*\nLong term capital appreciation.\nInvestments primarily in equity and equity related instruments, with exposure in debt and money market instruments.\n*Investors should consult their financial advisors if in doubt whether the product is suitable for them.\nRiskometer\nSBI Equity Hybrid Fund\nLow\nLow to Moderate\nModerate\nModerately High\nHigh\nVery High\nRISKOMETER\nThe risk of the scheme is\nVery High\nBenchmark Riskometer\nCRISIL Hybrid 35+65 - Aggressive Index\nLow\nLow to Moderate\nModerate\nModerately High\nHigh\nVery High\nRISKOMETER\nThe risk of the benchmark is\nHigh\nPortfolio Breakup\nTop Holdings\n(as on\n31 Oct 2025\n)\nCreated with Highcharts 8.1.2\n8.53%\n5.3%\n4.58%\n3.99%\n3.77%\n3.59%\n0\n2\n4\n6\n8\n10\n12\n14\n16\n18\nGOVERNMENT OF INDIA\nHDFC BANK LTD.\nCASH, CASH EQUIVALENTS AND OTHERS\nBHARTI AIRTEL LTD.\nSTATE BANK OF INDIA\nKOTAK MAHINDRA BANK LTD.\nView all holdings\nSector Allocations\nCreated with Highcharts 8.1.2\n28.83%\n8.53%\n8.52%\n8.08%\n4.79%\n4.58%\n0\n2\n4\n6\n8\n10\n12\n14\n16\n18\n20\n22\n24\n26\n28\n30\n32\n34\n36\n38\nFINANCIAL SERVICES\nSOVEREIGN\nPOWER\nSERVICES\nCONSUMER SERVICES\nCASH, CASH EQUIVALENTS AND OTHERS#\nView all allocations\nAll Holdings\n(as on\n31 Oct 2025\n)\nAll Allocations\nPerformance\nRegular Growth\nDirect Growth\nCompounded Annualized Growth Rate Performance\n1Y\n3Y\n5Y\n10Y\nSince Inception\nSBI Equity Hybrid Fund\n12.42%\n14.15%\n16.93%\n12.4%\n15.22%\nScheme Benchmark: CRISIL Hybrid 35+65 - Aggressive Index\nBenchmark\n6.76%\n13.08%\n15.36%\n12.43%\nNA\nAdditional Benchmark: BSE Sensex TRI\nAdditional Benchmark\n6.99%\n12.77%\n17.59%\n13.53%\n12.73%\nCurrent Value of Standard Investment of ₹10,000\n1Y\n3Y\n5Y\n10Y\nSince Inception\nSBI Equity Hybrid Fund\n₹11242\n₹14878\n₹21876\n₹32219\n₹709647\nScheme Benchmark: CRISIL Hybrid 35+65 - Aggressive Index\nBenchmark\n₹10676\n₹14463\n₹20442\n₹32291\nNA\nAdditional Benchmark: BSE Sensex TRI\nAdditional Benchmark\n₹10699\n₹14346\n₹22502\n₹35630\n₹367455\nNotes:\nDifferent plans shall have different expense structure. In case of return calculated the IDCW option, it is assumed that dividend declared under the schemes have been reinvested at the prevailing NAV\nPast performance may or may not be sustained in future and same may not necessarily provide the basis for comparison with other investment\nLoad is not considered for computation of returns\nPeriod for which scheme’s performance has been provided is computed basis last day of the month-end preceding the date of advertisement. In case, the start/end date of the concerned period is a non-business day, the NAV of the previous date is considered for computation of returns\nThe data of the last working day has been considered for the calculation of performance\nWherever TRI data since inception for benchmarks is not available, benchmark performance is calculated using composite of CAGR and TRI values of the benchmark\nThe performance of the schemes is benchmarked to the Total Return variant of the Index\nTo view other open ended funds managed by the fund manager go to the Fund Manager section\nCompounded Annualized Growth Rate Performance\n1Y\n3Y\n5Y\n10Y\nSince Inception\nSBI Equity Hybrid Fund\n13.16%\n14.92%\n17.73%\n13.32%\n15.04%\nScheme Benchmark: CRISIL Hybrid 35+65 - Aggressive Index\nBenchmark\n6.76%\n13.08%\n15.36%\n12.43%\n12.46%\nAdditional Benchmark: BSE Sensex TRI\nAdditional Benchmark\n6.99%\n12.77%\n17.59%\n13.53%\n13.48%\nCurrent Value of Standard Investment of ₹10,000\n1Y\n3Y\n5Y\n10Y\nSince Inception\nSBI Equity Hybrid Fund\n₹11316\n₹15181\n₹22638\n₹34952\n₹60435\nScheme Benchmark: CRISIL Hybrid 35+65 - Aggressive Index\nBenchmark\n₹10676\n₹14463\n₹20442\n₹32291\n₹45175\nAdditional Benchmark: BSE Sensex TRI\nAdditional Benchmark\n₹10699\n₹14346\n₹22502\n₹35630\n₹50714\nNotes:\nDifferent plans shall have different expense structure. In case of return calculated the IDCW option, it is assumed that dividend declared under the schemes have been reinvested at the prevailing NAV\nPast performance may or may not be sustained in future and same may not necessarily provide the basis for comparison with other investment\nLoad is not considered for computation of returns\nPeriod for which scheme’s performance has been provided is computed basis last day of the month-end preceding the date of advertisement. In case, the start/end date of the concerned period is a non-business day, the NAV of the previous date is considered for computation of returns\nThe data of the last working day has been considered for the calculation of performance\nWherever TRI data since inception for benchmarks is not available, benchmark performance is calculated using composite of DCAGR and TRI values of the benchmark\nThe performance of the schemes is benchmarked to the Total Return variant of the Index\nTo view other open ended funds managed by the fund manager go to the Fund Manager section\nDocuments\nFile Name\nFile Type\nFile Size\nSBI Equity Hybrid Fund  Factsheet October 2025\n469  KB\nSBI Equity Hybrid Fund MONTHLY PORTFOLIO - OCTOBER 2025\n89  KB\nSID - SBI Equity Hybrid Fund\n1  MB\nKIM - SBI Equity Hybrid Fund\n341  KB\nDownload\nFund Data\nQuantitative Data\nExpense Ratio Regular  in % (as on 31 Oct ,2025)\n:\n1.38\nExpense Ratio Direct  in % (as on 31 Oct ,2025)\n:\n0.72\nSharpe Ratio\n:\n0.82\nAvg Macaulay Duration\n:\n4.94\nStandard Deviation\n:\n8.83%\nBeta\n:\n0.98\nModified Duration  (in Years)\n:\n4.7153\nAverage Maturity\n:\n7.76 years\nYield To Maturity\n:\n7.07\n**All expense ratios are inclusive of GST on Management Fees\nIDCW History\nChoose Plan\nSBI Equity Hybrid Fund - Regular Plan - IDCW\nSBI Equity Hybrid Fund - Regular Plan - IDCW\nSBI Equity Hybrid Fund - Direct Plan - IDCW\nRecord Date\nIDCW*\nNAV(₹)\n10 Feb 2020\n0.8588464\n31.8472\n07 Feb 2019\n0.1770817\n27.7551\n28 Sep 2018\n0.2567685\n27.3468\n06 Jul 2018\n0.407288\n27.8671\nFace Value: ₹ 10\nPursuant to payment of IDCW, the NAV of IDCW Option of schemes/plans would fall to the extent of payout and statutory levy, if applicable.\nAfter dividend distribution tax.\nFAQ Section\nHow to Invest in SBI Equity Hybrid Fund?\n> Log in to the website.\n> Choose between Lumpsum or Systematic Investment Plan (SIP).\n> Choose your bank and preferred payment method.\n> An OTP will be sent to your registered email ID and mobile number.\n> Your transaction will be processed after OTP verification.\nWhat is the current NAV of SBI Equity Hybrid Fund?\nLatest closing NAV as on 17 Nov, 2025 for SBI Equity Hybrid Fund - Regular Plan - Growth is Rs. 312.5363\nWhat is the AUM of SBI Equity Hybrid Fund?\nAUM of SBI Equity Hybrid Fund is 81965.33 Cr.\nWhat is the Riskometer level of SBI Equity Hybrid Fund?\nSBI Equity Hybrid Fund is rated as a VERY HIGH. Benchmark Riskometer for this fund is CRISIL Hybrid 35 + 65 – Aggressive Index.\nWhat are the top holdings of SBI Equity Hybrid Fund?\nTop Holdings for the fund as per percentage of amount invested is as follows:\n> GOVERNMENT OF INDIA : 8.53 %\n> HDFC BANK LTD. : 5.3 %\n> CASH, CASH EQUIVALENTS AND OTHERS : 4.58 %\n> BHARTI AIRTEL LTD. : 3.99 %\n> STATE BANK OF INDIA : 3.77 %\n> KOTAK MAHINDRA BANK LTD. : 3.59 %\nIs there any lock-in period for SBI Equity Hybrid Fund?\nNo lock-in period is applicable for this fund.\nWhat is the expense ratio of SBI Equity Hybrid Fund?\nExpense ratio for Regular scheme is 1.38% as on 31 Oct 2025 and Expense Ratio for Direct Scheme is 0.72% as on 31 Oct 2025\nHow can I redeem my investments in SBI Equity Hybrid Fund?\n> Login to your account.\n> In the Dashboard, go to the Portfolio Snapshot section and click on Transact > Redeem.\n> Enter the Amount/Units you wish to redeem.\n> An OTP will be sent to your registered email ID/mobile number.\n> After OTP verification, your redemption will be processed in 3 business working days.\nWhat are the top sectors SBI Equity Hybrid Fund has invested in?\nSector Allocations for as per percentage of amount invested is as follows:\n> FINANCIAL SERVICES : 28.83 %\n> SOVEREIGN : 8.53 %\n> POWER : 8.52 %\n> SERVICES : 8.08 %\n> CONSUMER SERVICES : 4.79 %\n> CASH, CASH EQUIVALENTS AND OTHERS# : 4.58 %\nWho manages the SBI Equity Hybrid Fund?\nThe Fund managers for this fund are:\n> Mr. R Srinivasan since January 2012\n> Mr. Rajeev Radhakrishnan since November 2023\n> Ms. Mansi Sajeja since December 2023\nWhat is the minimum investment in SBI Equity Hybrid Fund?\nMinimum Lumpsum Amount applicable for this fund is Rs. 1000 in multiples of 1.\nMinimum Additional Lumpsum Amount applicable for this fund is Rs. 1000 in multiples of 1.\nMinimum SIP Amount applicable for fund is Rs. 500\nStart your investment in\n×\nSBI Magnum Fund Ultra Short Duration\nEdit Plan\nDirect - Growth\nDirect - IDCW\nRegular - Growth\nRegular - IDCW\nSelect IDCW option\nReinvest\nPayout\nIDCW option is required.\nSBI Magnum Fund Ultra Short Duration\nDirect - Growth\nMonthly SIP\n₹500\nStart Date\n26 Feb 2023\nEdit\nExisting Scheme in Cart\nLooks like you already have an existing\nSIP\nin this this scheme in your cart.\nSIP\ndetails listed below:\nEXISTING\nSIP\nDETAILS\nScheme Name\nSBI Magnum Fund Ultra Short Duration - Direct Growth\nSIP\nAmount\n500\nFrequency\nWeekly\nStart Date\n3 June 2023\nEnd Date\n3 June 2032\nTop-up Frequency\nYearly\nTop-up in\nAmount\nTop-up Percent\n5%\nAdd to Cart without Top-up\nAdd to Cart with Top-up\nProceed with existing SIP\nProceed with new SIP\nProceed with existing Lumpsum\nProceed with new Lumpsum\nLumpsum\nStart SIP\nLumpsum Amount\n₹\nMinimum Amount is Rs\nfor Lumpsum/Additional Purchase as applicable\nPlease enter Lumpsum Amount.\nMaximum Amount is Rs 1000000000 for Lumpsum/Additional Purchase as applicable\nAmount should be in multiple of Rs\nfor Lumpsum/Additional Purchase as applicable\nDemat Option\ni\nUnits will be allocated to your Demat Account\nNSDL\nCDSL\nDemat Account No\nIN\nPlease enter a valid 14 digit Demat Account Number\nPlease enter a valid 16 digit Demat Account Number\nDemat Account Number is required\nSIP Amount\n₹\n₹500\n₹1000\n₹2500\nEnter SIP amount.\nSIP amount must be greater than\nfor a\nSIP\nInvestment amount for SBI Small Cap Fund is restricted to Rs.25000 per PAN (first holder/Guardian) per month.\nMaximum Amount is Rs 100000000 for SIP as applicable.\nAmount should be in multiple of Rs\nfor a SIP\nSIP Frequency\nMonthly\nWeekly\nYearly\nMonthly\nWeekly\nYearly\nSIP Start Date\nSelect Day of Installment.\nSIP Tenure\n5 Year\n10 Year\n25 Year\n30 Year\nSelect Custom Date\n5 Year\n10 Year\n25 Year\n30 Year\nSelect Custom Date\nSIP will start on\n& run till\nOne Last Step, Top-Up\nTop-up in\nPercentage\nAmount\nTop-up Frequency\nHalf Yearly\nYearly\nTop-up Percentage\n5%\n10%\n15%\n20%\n25%\n30%\n35%\n40%\n45%\n50%\n55%\n60%\n65%\n70%\n75%\n80%\n85%\n90%\n95%\n100%\n5%\n10%\n15%\n20%\n25%\n30%\n35%\n40%\n45%\n50%\n55%\n60%\n65%\n70%\n75%\n80%\n85%\n90%\n95%\n100%\nTop-up Amount\n₹\nSIP Top Up amount must be greater than Rs 500 amount\nSIP Top Up amount must be in multiples of Rs.500\nSIP Top Up amount is required\nSIP Top Up amount must be less than ₹ 1,00,00,000\nNo. of top-ups\n1\n2\n3\n4\n5\n6\n7\n8\n9\n10\n11\n12\n13\n14\n15\n16\n17\n18\n19\n20\n21\n22\n23\n24\n25\n26\n27\n28\n29\n30\n31\n32\n33\n34\n35\n36\n37\n38\n39\n40\n41\n42\n43\n44\n45\n46\n47\n48\n49\n50\n1\n2\n3\n4\n5\n6\n7\n8\n9\n10\n11\n12\n13\n14\n15\n16\n17\n18\n19\n20\n21\n22\n23\n24\n25\n26\n27\n28\n29\n30\n31\n32\n33\n34\n35\n36\n37\n38\n39\n40\n41\n42\n43\n44\n45\n46\n47\n48\n49\n50\nPlease select No. of topups.\nMax SIP Amount : ₹\nTop Up Max Amount must not Exceed ₹1,00,00,000/-\nThe remaining tenure of your SIP is less than\nto top up a SIP please ensure a minimum of\nare available.\nTop up Till\nSelect Day of Installment.\nMax SIP Amount: ₹\nTop Up Max Amount must not Exceed ₹1,00,00,000/-\nYour top up will end on date\nBy opting out of SIP top-up, you lose out on multiplying your wealth\nSetup Auto Transfer\nAs you grow older, we can dynamically shift your Investments to\na more conservative plan\nLearn More\nThis fund has a lock in period of 5 years or till the investor\nattains the age of 65 whichever is earlier\nI want to top-up my SIP amount\nYour peers (20-30 yrs) usually top-up their SIPs annually\nTop-up Frequency\nHalf-yearly\nYearly\nTop-up in\nAmount\nPercentage\nTop-up Amount\n₹\nMax. amount ₹5,000\nTop-up Till\nAdd to Cart\nInvest Now\nProceed without Top-up\nProceed with Top-up\nHow Auto Transfer Work\nIn case of Auto Transfer, all investment will be made depending on the investor's age. at the time\nof investment into the suitable corresponding investment Plan.Association of investment plan to\nage-groups and risk appetite of investors is illustrated in the following table.\nAge Range(year)\nplan\nUpto 40\nAggresive\n40-50\nAggresive Hybrid\n50-60\nConservative Hybrid\nAbove 60\nConservative\nBasis your date of birth\nregistered in this folio\nis most suitable to you.The fund is subject to a lock in of 5 Years.\nClose\nSetup Auto Transfer\nEmail\nFrom\n*\nEnter Name\nEnter Name\nPlease provide name\nTo\n*\nEnter Email\nEnter Email\nPlease provide valid email(s)\n(max upto 10 email id's allowed separated by ,)\nSubject\n*\nSend\nReset\nFund Overview\nPortfolio Breakup\nPerformance\nFund Data\nSimilar Funds\nView All Funds\nReceive Assistance\nEnter Name\nEnter Name\nPlease enter name\nEnter City\nEnter City\nPlease enter city\nEnter Mobile Number\nEnter Mobile Number\nPlease enter a mobile number\nPlease enter a valid mobile number\nEnter Email ID\nEnter Email ID\nPlease enter an email ID\nPlease enter a valid email ID\nSubmit\nCancel\nLoading...\nMessage Sent!\nGo Back\nSuccess\nFailure\nMessage Sent!\nGo Back\nX",
    "tables": [
      {
        "headers": [
          "Compounded Annualized Growth Rate Performance",
          "1Y",
          "3Y",
          "5Y",
          "10Y",
          "Since Inception"
        ],
        "rows": [
          [
            "SBI Equity Hybrid Fund",
            "12.42%",
            "14.15%",
            "16.93%",
            "12.4%",
            "15.22%"
          ],
          [
            "Scheme Benchmark: CRISIL Hybrid 35+65 - Aggressive IndexBenchmark",
            "6.76%",
            "13.08%",
            "15.36%",
            "12.43%",
            "NA"
          ],
          [
            "Additional Benchmark: BSE Sensex TRIAdditional Benchmark",
            "6.99%",
            "12.77%",
            "17.59%",
            "13.53%",
            "12.73%"
          ]
        ]
      },
      {
        "headers": [
          "Current Value of Standard Investment of ₹10,000",
          "1Y",
          "3Y",
          "5Y",
          "10Y",
          "Since Inception"
        ],
        "rows": [
          [
            "SBI Equity Hybrid Fund",
            "₹11242",
            "₹14878",
            "₹21876",
            "₹32219",
            "₹709647"
          ],
          [
            "Scheme Benchmark: CRISIL Hybrid 35+65 - Aggressive IndexBenchmark",
            "₹10676",
            "₹14463",
            "₹20442",
            "₹32291",
            "NA"
          ],
          [
            "Additional Benchmark: BSE Sensex TRIAdditional Benchmark",
            "₹10699",
            "₹14346",
            "₹22502",
            "₹35630",
            "₹367455"
          ]
        ]
      },
      {
        "headers": [
          "Compounded Annualized Growth Rate Performance",
          "1Y",
          "3Y",
          "5Y",
          "10Y",
          "Since Inception"
        ],
        "rows": [
          [
            "SBI Equity Hybrid Fund",
            "13.16%",
            "14.92%",
            "17.73%",
            "13.32%",
            "15.04%"
          ],
          [
            "Scheme Benchmark: CRISIL Hybrid 35+65 - Aggressive IndexBenchmark",
            "6.76%",
            "13.08%",
            "15.36%",
            "12.43%",
            "12.46%"
          ],
          [
            "Additional Benchmark: BSE Sensex TRIAdditional Benchmark",
            "6.99%",
            "12.77%",
            "17.59%",
            "13.53%",
            "13.48%"
          ]
        ]
      },
      {
        "headers": [
          "Current Value of Standard Investment of ₹10,000",
          "1Y",
          "3Y",
          "5Y",
          "10Y",
          "Since Inception"
        ],
        "rows": [
          [
            "SBI Equity Hybrid Fund",
            "₹11316",
            "₹15181",
            "₹22638",
            "₹34952",
            "₹60435"
          ],
          [
            "Scheme Benchmark: CRISIL Hybrid 35+65 - Aggressive IndexBenchmark",
            "₹10676",
            "₹14463",
            "₹20442",
            "₹32291",
            "₹45175"
          ],
          [
            "Additional Benchmark: BSE Sensex TRIAdditional Benchmark",
            "₹10699",
            "₹14346",
            "₹22502",
            "₹35630",
            "₹50714"
          ]
        ]
      },
      {
        "headers": [
          "File Name",
          "File Type",
          "File Size"
        ],
        "rows": [
          [
            "SBI Equity Hybrid Fund  Factsheet October 2025",
            "",
            "469  KB"
          ],
          [
            "SBI Equity Hybrid Fund MONTHLY PORTFOLIO - OCTOBER 2025",
            "",
            "89  KB"
          ],
          [
            "SID - SBI Equity Hybrid Fund",
            "",
            "1  MB"
          ],
          [
            "KIM - SBI Equity Hybrid Fund",
            "",
            "341  KB"
          ]
        ]
      },
      {
        "headers": [
          "Quantitative Data"
        ],
        "rows": [
          [
            "Expense Ratio Regular  in % (as on 31 Oct ,2025)",
            ":",
            "1.38"
          ],
          [
            "Expense Ratio Direct  in % (as on 31 Oct ,2025)",
            ":",
            "0.72"
          ],
          [
            "Sharpe Ratio",
            ":",
            "0.82"
          ],
          [
            "Avg Macaulay Duration",
            ":",
            "4.94"
          ],
          [
            "Standard Deviation",
            ":",
            "8.83%"
          ],
          [
            "Beta",
            ":",
            "0.98"
          ],
          [
            "Modified Duration  (in Years)",
            ":",
            "4.7153"
          ],
          [
            "Average Maturity",
            ":",
            "7.76 years"
          ],
          [
            "Yield To Maturity",
            ":",
            "7.07"
          ]
        ]
      },
      {
        "headers": [
          "Record Date",
          "IDCW*",
          "NAV(₹)"
        ],
        "rows": [
          [
            "10 Feb 2020",
            "0.8588464",
            "31.8472"
          ],
          [
            "07 Feb 2019",
            "0.1770817",
            "27.7551"
          ],
          [
            "28 Sep 2018",
            "0.2567685",
            "27.3468"
          ],
          [
            "06 Jul 2018",
            "0.407288",
            "27.8671"
          ]
        ]
      },
      {
        "headers": [
          "Age Range(year)",
          "plan"
        ],
        "rows": [
          [
            "Upto 40",
            "Aggresive"
          ],
          [
            "40-50",
            "Aggresive Hybrid"
          ],
          [
            "50-60",
            "Conservative Hybrid"
          ],
          [
            "Above 60",
            "Conservative"
          ]
        ]
      }
    ],
    "metadata": {
      "url": "https://www.sbimf.com/sbimf-scheme-details/sbi-equity-hybrid-fund-5",
      "title": "SBI Equity Hybrid Fund",
      "last_modified": null,
      "breadcrumbs": []
    },
    "factual_data": {
      "expense_ratio_regular": "1.38",
      "expense_ratio_direct": "0.72",
      "exit_load": "12",
      "minimum_sip": "500",
      "minimum_lumpsum": "1000",
      "lock_in_period": "5",
      "riskometer": "35",
      "benchmark": "performance is calculated using composite of CAGR and TRI values of the benchmark\nThe performance of the schemes is benchmarked to the Total Return variant of the Index"
    },
    "scraped_date": "2025-11-17T22:22:05.875304",
    "scheme_name": "SBI Equity Hybrid Fund",
    "document_type": "scheme_details",
    "scheme_name_validated": true,
    "match_score": 1.0
  }
]